Workbook

Sheet JOB
A1: "DIVISI" | B1: "JOB DESCRIPTION"
A2: BUSINESS CONSULTANT | B2: 1. Memastikan Data Kelolaan di Hubungi dengan maksimal
B3: 2. Daily Call Minimal 20 New Customer di Hubungi
B4: 3. Demo Aplikasi Prioritas Closing
B5: 4. Nasabah Potensial Harus lebih banyak dibanding Target Pencapaian
B6: 5. Mencapai Target setiap bulan mengukur KPI
B7: 6. Invite new member di group Pengguna Aplikasi Piposmart di WhatsApp
B8: 7. Melampirkan fhoto usaha laundry yang telah bekerja sama
B9: 8. Ajak nasabah, Aflisiasi, Referral untuk menjadi mitra piposmart

Sheet SOP Data Kelolaan 2026
A1: SOP kategori nasabah menjadi Nasabah Potensi dan Nasabah Tidak Potensi (di tarik) | J1: ✨ TO DO LIST SALES & CS
A2: Kategori Nasabah Potensi
A3: Nasabah dapat dikategorikan sebagai Nasabah Potensi apabila memenuhi salah satu atau beberapa indikator berikut:
A4: Nasabah responsif dan interaktif selama masa trial. | J4: 🔥 TEAM SALES
A5: Terdapat rencana demo atau training lanjutan.
A6: Nasabah aktif membahas harga atau skema langganan aplikasi. | J6: 1. Follow up data kelolaan 50 data
A7: Terjadi peningkatan transaksi selama masa penggunaan. | J7: 2. Follow up data nasabah new download - Project list & outlet
A8: Memberikan rekomendasi rekan atau mitra. | J8: 3. Follow up data nasabah potensi
A9: Memiliki progres komunikasi yang mengarah pada closing. | J9: 4. Follow up data nasabah jatuh tempo
J10: 5. Follow up mitra kelolaan
A11: Untuk nasabah potensi, tim bisnis wajib: | J11: 6. Posting konten harian (Story WhatsApp)
A12: Melakukan follow up secara berkala dan terjadwal | J12: 7. Posting konten di Instagram, Tiktok dan FB.
A13: Mencatat perkembangan pada kolom call & chat | J13: 8. Follow up nasabah yang belum memberikan rating & logo laundry
A14: Mengarahkan ke proses closing atau upgrade paket | J14: 9. Daily report follow up data kelolaan (WA Group)
J15: 10. Daily report follow up data jatuh tempo (WA Group)
A16: Kategori Nasabah Tidak Potensi (Ditarik) | J16: 11. Pengisian data kelolaan : Data kelolaan, report follow up, data kelolaan mitra, data kpi, report penjualan.
A17: Nasabah dapat dikategorikan sebagai Tidak Potensi dan dapat ditarik dari daftar aktif apabila memenuhi kriteria berikut: | J17: 💬 TEAM CS
A18: Akun nasabah teridentifikasi sebagai akun testing atau akun karyawan. | J18: 1. Follow up data nasabah existing (Jatuh tempo & Berlangganan)
A19: Telah dilakukan follow up maksimal 5 (lima) kali baik call maupun chat tanpa respons | J19: 2. Follow up data nasabah non-regustrasi akun (user temp)
A20: Status chat “centang 1” tanpa respons selama 2–3 hari berturut-turut | J20: 3. Follow up data nasabah unsubscribe
A21: Nasabah secara langsung meminta untuk tidak dihubungi kembali
A22: Nomor tidak aktif atau tidak dapat dihubungi selama 2–3 hari berturut-turut
A23: Menolak karena harga tidak sesuai setelah penawaran resmi diberikan
A24: Transaksi outlet tidak bertambah baik selama masa trial maupun setelah masa trial
A27: Modul Call Cs | J27: Modul Chat Cs
A29: 1. Call Contacted : | J29: 1. Chat Send :
A30: - Telepon memanggil atau tidak tersambung dengan nomor atau nasabah yang di tuju | J30: - Chat ceklis 1 atau tidak terkirim
A31: 2. Call Connected | J31: - Nomor tidak aktif, nomor di blokir
J32: 2. Chat Delivered
A33: - Telepon masuk dan berdering tapi nasabah tidak merespon | J33: - Chat ceklis 2 atau terkirim tapi nasabah tidak merespon
A34: - Nomor nasabah aktif | J34: - Nomor nasabah aktif
A35: 3. Call Engage : | J35: 3. Chat Engage :
A36: - Nasabah mengangkat telepon tapi tidak ada percakapan lanjut, di putuskan sepihak oleh nasabah | J36: - Nasabah membalas pean tapi tidak ada percakapan lanjut, di putuskan sepihak oleh nasabah
A37: - Nasabah masih sibuk saat di hubungi atau sedang di jalan | J37: - Nasabah masih sibuk saat di chat atau sedang di jalan
A38: 4. Call Interest : | J38: 4. Chat Interest :
A39: - Nasabah tertarik dan masuk pembahasan lanjut mengenai penggunaaan aplikasi, fitur-fitur yang ada dan mengenai harga berlangganan | J39: - Nasabah tertarik dan masuk pembahasan lanjut mengenai penggunaaan aplikasi, fitur-fitur yang ada dan mengenai harga berlangganan
A40: - Nasabah sudah ada gambaran akan berlangganan paket apa | J40: - Nasabah sudah ada gambaran akan berlangganan paket apa
A41: 5. Call Prospek : | J41: 5. Chat Prospek :
A42: - Nasabah potensi dan nasabah sudah sampai tahap training demo aplikasi melalui online meeting atau pun visit ke laundry (Batam) | J42: - Nasabah potensi dan nasabah sudah sampai tahap training demo aplikasi melalui online meeting atau pun visit ke laundry (Batam)
A43: 6. Call Uninterest : | J43: 6. Chat Uninterest :
A44: - Nasabah tidak tertarik setelah ada percakapan lanjut | J44: - Nasabah tidak tertarik setelah ada percakapan lanjut
... A51: 3. nasabah minta untuk tidak di hubungi lagi | J51: 3. nasabah minta untuk tidak di chat lagi

Sheet TARGET 
A2: Pencapaian TEAM HUNTER
A3: Tahun 2026
A4: Bulan | B4: Target User | C4: Target Omset | D4: Realisasi Membership | E4: Realisasi Omset | F4: Kekurangan User | G4: Kekurangan Omset | H4: Persentase Tercapai User (%) | I4: Persentase Target Booking (%) | J4: Penilaian Membership | K4: Penilaian Target | L4: User | M4: Pencapaian Week 1 | N4: User | O4: Pencapaian Week 2 | P4: User | Q4: Pencapaian Week 3 | R4: User | S4: Pencapaian Week 4
A5: Januari | B5: 20 | C5: 15000000 | D5: =L5+N5+P5+R5 -> 10 | E5: ='PotensiDemo '!M135 -> 12532297 | F5: =D5-B5 -> -10 | G5: =E5-C5 -> -2467703 | H5: =D5/B5 -> 0.5 | I5: =E5/C5 -> 0.83548647 | J5: =IF(H5>=100%,"Hijau",IF(H5>=70%,"Kuning",IF(H5>=50%,"Merah","Hitam"))) -> Merah | K5: =IF(I5>=100%,"Hijau",IF(I5>=70%,"Kuning",IF(I5>=50%,"Merah","Hitam"))) -> Kuning | L5: 3 | M5: ='PotensiDemo '!N126+'PotensiDemo '!N128+'PotensiDemo '!N129 -> 2854134 | N5: 5 | O5: ='PotensiDemo '!N123+'PotensiDemo '!N124+'PotensiDemo '!N122+'PotensiDemo '!N130+'PotensiDemo '!N131 -> 6692163 | P5: 1 | Q5: ='PotensiDemo '!N127 -> 1298000 | R5: 1 | S5: ='PotensiDemo '!N125 -> 1688000
A6: Februari | B6: 20 | C6: 15000000 | D6: =L6+N6+P6+R6 -> 4 | E6: ='PotensiDemo '!M116 -> 12591143 | F6: =D6-B6 -> -16 | G6: =E6-C6 -> -2408857 | H6: =D6/B6 -> 0.2 | I6: =E6/C6 -> 0.83940953 | J6: =IF(H6>=100%,"Hijau",IF(H6>=70%,"Kuning",IF(H6>=50%,"Merah","Hitam"))) -> Hitam | K6: =IF(I6>=100%,"Hijau",IF(I6>=70%,"Kuning",IF(I6>=50%,"Merah","Hitam"))) -> Kuning | L6: 1 | M6: ='PotensiDemo '!N101 -> 2078000 | N6: 1 | O6: ='PotensiDemo '!N103 -> 1298000 | P6: 2 | Q6: ='PotensiDemo '!N104+'PotensiDemo '!N105+'PotensiDemo '!N106+'PotensiDemo '!N107 -> 2150000 | R6: 0 | S6: 0
A7: Maret | B7: 35 | C7: 46100000 | D7: =L7+N7+P7+R7 -> 6 | E7: ='PotensiDemo '!M95 -> 8390000 | F7: =D7-B7 -> -29 | G7: =E7-C7 -> -37710000 | H7: =D7/B7 -> 0.17142857 | I7: =E7/C7 -> 0.18199566 | J7: =IF(H7>=100%,"Hijau",IF(H7>=70%,"Kuning",IF(H7>=50%,"Merah","Hitam"))) -> Hitam | K7: =IF(I7>=100%,"Hijau",IF(I7>=70%,"Kuning",IF(I7>=50%,"Merah","Hitam"))) -> Hitam | L7: 3 | M7: ='PotensiDemo '!N82+'PotensiDemo '!N83+'PotensiDemo '!N84 -> 4156000 | N7: 1 | O7: ='PotensiDemo '!N85 -> 858000 | P7: 1 | Q7: ='PotensiDemo '!N91 -> 1688000 | R7: 1 | S7: ='PotensiDemo '!N86 -> 1688000
A8: April | B8: 33 | C8: 42684888 | D8: =L8+N8+P8+R8 -> 5 | E8: ='PotensiDemo '!M76 -> 4707167 | F8: =D8-B8 -> -28 | G8: =E8-C8 -> -37977721 | H8: =D8/B8 -> 0.15151515 | I8: =E8/C8 -> 0.11027713 | J8: =IF(H8>=100%,"Hijau",IF(H8>=70%,"Kuning",IF(H8>=50%,"Merah","Hitam"))) -> Hitam | K8: =IF(I8>=100%,"Hijau",IF(I8>=70%,"Kuning",IF(I8>=50%,"Merah","Hitam"))) -> Hitam | L8: 3 | M8: ='PotensiDemo '!N57+'PotensiDemo '!N59+'PotensiDemo '!N60+'PotensiDemo '!N69 -> 3381086 | N8: 0 | O8: 0 | P8: 1 | Q8: 858000 | R8: 1 | S8: 468000
A9: Mei | B9: 18 | C9: 23894000 | D9: =L9+N9+P9+R9 -> 12 | E9: ='PotensiDemo '!M51 -> 15889022 | F9: =D9-B9 -> -6 | G9: =E9-C9 -> -8004978 | H9: =D9/B9 -> 0.66666667 | I9: =E9/C9 -> 0.66497958 | J9: =IF(H9>=100%,"Hijau",IF(H9>=70%,"Kuning",IF(H9>=50%,"Merah","Hitam"))) -> Merah | K9: =IF(I9>=100%,"Hijau",IF(I9>=70%,"Kuning",IF(I9>=50%,"Merah","Hitam"))) -> Merah | L9: 3 | M9: ='PotensiDemo '!N27+'PotensiDemo '!N28+'PotensiDemo '!N37 -> 3574020 | N9: 2 | O9: ='PotensiDemo '!N29+'PotensiDemo '!N38+'PotensiDemo '!N39+'PotensiDemo '!N40 -> 2309000 | P9: 3 | Q9: ='PotensiDemo '!N30+'PotensiDemo '!N36+'PotensiDemo '!N31 -> 4084000 | R9: 4 | S9: ='PotensiDemo '!N32+'PotensiDemo '!N33+'PotensiDemo '!N35+'PotensiDemo '!N34 -> 5922002
A10: Juni | B10: 18 | C10: 28150000 | D10: =L10+N10+P10+R10 -> 8 | E10: ='PotensiDemo '!M21 -> 7278118 | F10: =D10-B10 -> -10 | G10: =E10-C10 -> -20871882 | H10: =D10/B10 -> 0.44444444 | I10: =E10/C10 -> 0.25854771 | J10: =IF(H10>=100%,"Hijau",IF(H10>=70%,"Kuning",IF(H10>=50%,"Merah","Hitam"))) -> Hitam | K10: =IF(I10>=100%,"Hijau",IF(I10>=70%,"Kuning",IF(I10>=50%,"Merah","Hitam"))) -> Hitam | L10: 4 | M10: ='PotensiDemo '!N5+'PotensiDemo '!N6+'PotensiDemo '!N7+'PotensiDemo '!N8 -> 5326048 | N10: 2 | O10: ='PotensiDemo '!N9+'PotensiDemo '!N10 -> 976000 | P10: 2 | Q10: ='PotensiDemo '!N11+'PotensiDemo '!N12 -> 976070
A11: Juli | F11: =D11-B11 -> 0 | G11: =E11-C11 -> 0 | H11: =D11/B11 -> #DIV/0! | I11: =E11/C11 -> #DIV/0! | J11: =IF(H11>=100%,"Hijau",IF(H11>=70%,"Kuning",IF(H11>=50%,"Merah","Hitam"))) -> #DIV/0! | K11: =IF(I11>=100%,"Hijau",IF(I11>=70%,"Kuning",IF(I11>=50%,"Merah","Hitam"))) -> #DIV/0!
A12: Agustus | F12: =D12-B12 -> 0 | G12: =E12-C12 -> 0 | H12: =D12/B12 -> #DIV/0! | I12: =E12/C12 -> #DIV/0! | J12: =IF(H12>=100%,"Hijau",IF(H12>=70%,"Kuning",IF(H12>=50%,"Merah","Hitam"))) -> #DIV/0! | K12: =IF(I12>=100%,"Hijau",IF(I12>=70%,"Kuning",IF(I12>=50%,"Merah","Hitam"))) -> #DIV/0!
A13: September | F13: =D13-B13 -> 0 | G13: =E13-C13 -> 0 | H13: =D13/B13 -> #DIV/0! | I13: =E13/C13 -> #DIV/0! | J13: =IF(H13>=100%,"Hijau",IF(H13>=70%,"Kuning",IF(H13>=50%,"Merah","Hitam"))) -> #DIV/0! | K13: =IF(I13>=100%,"Hijau",IF(I13>=70%,"Kuning",IF(I13>=50%,"Merah","Hitam"))) -> #DIV/0!
A14: Oktober | F14: =D14-B14 -> 0 | G14: =E14-C14 -> 0 | H14: =D14/B14 -> #DIV/0! | I14: =E14/C14 -> #DIV/0! | J14: =IF(H14>=100%,"Hijau",IF(H14>=70%,"Kuning",IF(H14>=50%,"Merah","Hitam"))) -> #DIV/0! | K14: =IF(I14>=100%,"Hijau",IF(I14>=70%,"Kuning",IF(I14>=50%,"Merah","Hitam"))) -> #DIV/0!
A15: November | F15: =D15-B15 -> 0 | G15: =E15-C15 -> 0 | H15: =D15/B15 -> #DIV/0! | I15: =E15/C15 -> #DIV/0! | J15: =IF(H15>=100%,"Hijau",IF(H15>=70%,"Kuning",IF(H15>=50%,"Merah","Hitam"))) -> #DIV/0! | K15: =IF(I15>=100%,"Hijau",IF(I15>=70%,"Kuning",IF(I15>=50%,"Merah","Hitam"))) -> #DIV/0!
A16: Desember | F16: =D16-B16 -> 0 | G16: =E16-C16 -> 0 | H16: =D16/B16 -> #DIV/0! | I16: =E16/C16 -> #DIV/0! | J16: =IF(H16>=100%,"Hijau",IF(H16>=70%,"Kuning",IF(H16>=50%,"Merah","Hitam"))) -> #DIV/0! | K16: =IF(I16>=100%,"Hijau",IF(I16>=70%,"Kuning",IF(I16>=50%,"Merah","Hitam"))) -> #DIV/0!
A17: Total Target | B17: =SUM(B5:B16) -> 144 | C17: =SUM(C5:C16) -> 170828888 | D17: =SUM(D5:D16) -> 45 | E17: =SUM(E5:E16) -> 61387747 | F17: =D17-B17 -> -99 | G17: =C17-E17 -> 109441141 | H17: =D17/B17 -> 0.3125 | I17: =E17/C17 -> 0.35935226 | J17: =IF(H17>=100%,"Hijau",IF(H17>=70%,"Kuning",IF(H17>=50%,"Merah","Hitam"))) -> Hitam | K17: =IF(I17>=100%,"Hijau",IF(I17>=70%,"Kuning",IF(I17>=50%,"Merah","Hitam"))) -> Hitam
A18: Rata- rata Omset | D18: =D17/5 -> 9 | E18: =E17/5 -> 12277549
A19: Catatan Penting:
A20: Warna Hijau Tercapai 100%
A21: Warna Kuning Posisi Aman dgn min. capai 70%
A22: Warna Merah Posisi tidak aman dgn minimal capai 50% dr Target
A23: Warna Hitam Posisi Finalti dengan capai dibawah 30% dari Target
A25: TEAM HUNTER
A26: Target Juni 2026
A27: Pic Team Hunter | B27: Target User | C27: Target Nominal | D27: Realisasi | F27: Kekurangan
D28: User | E28: Omset | F28: User | G28: Omset
A29: Lidya | B29: =D42 -> 11 | C29: =F42 -> 14362000 | D29: 2 | E29: 2124086 | F29: =B29-D29 -> 9 | G29: =C29-E29 -> 12237914
A30: Total Pencapaian | B30: =sum(B29) -> 11 | C30: =sum(C29) -> 14362000 | D30: =sum(D29) -> 2 | E30: =sum(E29) -> 2124086 | F30: =sum(F29) -> 9 | G30: =sum(G29) -> 12237914
A31: Total Kekurangan [%] | B31: =B30/B30 -> 1 | C31: =C30/C30 -> 1 | D31: =D30/B30 -> 0.18181818 | E31: =E30/C30 -> 0.14789625 | F31: =F30/B30 -> 0.81818182 | G31: =G30/C30 -> 0.85210375
A33: Pic Team Hunter | B33: New Member | C33: Paket Langganan | D33: User | F33: Penjualan
D34: Target | E34: Realisasi | F34: Target | G34: Realisasi
B35: Basic 9 | C35: 702000 | D35: 1 | E35: 1 | F35: =C35*D35 -> 702000 | G35: =E35*C35 -> 702000
B36: Basic 12 | C36: 858000 | D36: 2 | E36: 3 | F36: =C36*D36 -> 1716000 | G36: =E36*C36 -> 2574000
B37: Business 9 | C37: 998000 | D37: 1 | E37: 0 | F37: =C37*D37 -> 998000 | G37: =E37*C37 -> 0
B38: Business 12 | C38: 1298000 | D38: 3 | E38: 0 | F38: =C38*D38 -> 3894000 | G38: =E38*C38 -> 0
B39: Pro 12 | C39: 1688000 | D39: 2 | E39: 1 | F39: =C39*D39 -> 3376000 | G39: =E39*C39 -> 1688000
B40: Jagoan Business | C40: 1598000 | D40: 1 | E40: 0 | F40: =C40*D40 -> 1598000 | G40: =E40*C40 -> 0
B41: Jagoan Pro | C41: 2078000 | D41: 1 | E41: 1 | F41: =C41*D41 -> 2078000 | G41: =E41*C41 -> 2078000
A42: Total Penjualan | D42: =sum(D35:D41) -> 11 | E42: =sum(E35:E41) -> 6 | F42: =sum(F35:F41) -> 14362000 | G42: =sum(G35:G41) -> 7042000
A43: Kekurangan | D43: =D42-E42 -> 5 | F43: =F42-G42 -> 7320000
A45: TEAM HUNTER
A46: Target Mei 2026
A47: Pic Team Hunter | B47: Target User | C47: Target Nominal | D47: Realisasi | F47: Kekurangan
D48: User | E48: Omset | F48: User | G48: Omset
A49: Lidya | B49: =D62 -> 11 | C49: =F62 -> 14368000 | D49: 2 | E49: 2124086 | F49: =B49-D49 -> 9 | G49: =C49-E49 -> 12243914
A50: Total Pencapaian | B50: =sum(B49) -> 11 | C50: =sum(C49) -> 14368000 | D50: =sum(D49) -> 2 | E50: =sum(E49) -> 2124086 | F50: =sum(F49) -> 9 | G50: =sum(G49) -> 12243914
A51: Total Kekurangan [%] | B51: =B50/B50 -> 1 | C51: =C50/C50 -> 1 | D51: =D50/B50 -> 0.18181818 | E51: =E50/C50 -> 0.14783449 | F51: =F50/B50 -> 0.81818182 | G51: =G50/C50 -> 0.85216551
A53: Pic Team Hunter | B53: New Member | C53: Paket Langganan | D53: User | F53: Penjualan
D54: Target | E54: Realisasi | F54: Target | G54: Realisasi
A55: Lidya | B55: Basic 12 | C55: 858000 | D55: 2 | E55: 1 | F55: =C55*D55 -> 1716000 | G55: =E55*C55 -> 858000
B56: Business 6 | C56: 708000 | D56: 1 | E56: 1 | F56: =C56*D56 -> 708000 | G56: =E56*C56 -> 708000
B57: Business 9 | C57: 998000 | D57: 1 | E57: 0 | F57: =C57*D57 -> 998000 | G57: =E57*C57 -> 0
B58: Business 12 | C58: 1298000 | D58: 3 | E58: 0 | F58: =C58*D58 -> 3894000 | G58: =E58*C58 -> 0
B59: Pro 12 | C59: 1688000 | D59: 2 | E59: 8 | F59: =C59*D59 -> 3376000 | G59: =E59*C59 -> 13504000
B60: Jagoan Business | C60: 1598000 | D60: 1 | E60: 0 | F60: =C60*D60 -> 1598000 | G60: =E60*C60 -> 0
B61: Jagoan Pro | C61: 2078000 | D61: 1 | E61: 0 | F61: =C61*D61 -> 2078000 | G61: =E61*C61 -> 0
A62: Total Penjualan | D62: =sum(D55:D61) -> 11 | E62: =sum(E55:E61) -> 10 | F62: =sum(F55:F61) -> 14368000 | G62: =sum(G55:G61) -> 15070000
A63: Kekurangan | D63: =D62-E62 -> 1 | F63: =F62-G62 -> -702000
A65: TEAM HUNTER
A66: Target April 2026
A67: Pic Team Hunter | B67: Target User | C67: Target Nominal | D67: Realisasi | F67: Kekurangan
D68: User | E68: Omset | F68: User | G68: Omset
A69: Lidya | B69: =D84 -> 10 | C69: =F84 -> 11541000 | D69: 2 | E69: 2124086 | F69: =B69-D69 -> 8 | G69: =C69-E69 -> 9416914
A70: Laura | B70: =D96 -> 10 | C70: =F96 -> 13760000 | D70: 1 | E70: 858000 | F70: =B70-D70 -> 9 | G70: =C70-E70 -> 12902000
A71: Total Pencapaian | B71: =sum(B69:B70) -> 20 | C71: =sum(C69:C70) -> 25301000 | D71: =sum(D69:D70) -> 3 | E71: =sum(E69:E70) -> 2982086 | F71: =sum(F69:F70) -> 17 | G71: =sum(G69:G70) -> 22318914
A72: Total Kekurangan [%] | B72: =B71/B71 -> 1 | C72: =C71/C71 -> 1 | D72: =D71/B71 -> 0.15 | E72: =E71/C71 -> 0.11786435 | F72: =F71/B71 -> 0.85 | G72: =G71/C71 -> 0.88213565
A74: Pic Team Hunter | B74: New Member | C74: Paket Langganan | D74: User | F74: Penjualan
D75: Target | E75: Realisasi | F75: Target | G75: Realisasi
A76: Lidya | B76: Printer Thermal | C76: 399000 | D76: 1 | E76: 1 | F76: =C76*D76 -> 399000 | G76: =E76*C76 -> 399000
B77: Pro 1 Bulan | C77: 168000 | D77: 1 | E77: 1 | F77: =C77*D77 -> 168000 | G77: 436086
B78: Basic 6 Bulan | C78: 468000 | D78: 1 | E78: 1 | F78: =C78*D78 -> 468000 | G78: =E78*C78 -> 468000
B79: Basic 12 | C79: 858000 | D79: 1 | E79: 1 | F79: =C79*D79 -> 858000 | G79: =E79*C79 -> 858000
B80: Business 12 | C80: 1298000 | D80: 2 | E80: 0 | F80: =C80*D80 -> 2596000 | G80: =E80*C80 -> 0
B81: Pro 12 | C81: 1688000 | D81: 2 | E81: 1 | F81: =C81*D81 -> 3376000 | G81: =E81*C81 -> 1688000
B82: Jagoan Business | C82: 1598000 | D82: 1 | E82: 0 | F82: =C82*D82 -> 1598000 | G82: =E82*C82 -> 0
B83: Jagoan Pro | C83: 2078000 | D83: 1 | E83: 0 | F83: =C83*D83 -> 2078000 | G83: =E83*C83 -> 0
A84: Total Penjualan | D84: =sum(D76:D83) -> 10 | E84: =sum(E76:E83) -> 5 | F84: =sum(F76:F83) -> 11541000 | G84: =sum(G76:G83) -> 3849086
A85: Kekurangan | D85: =D84-E84 -> 5 | F85: =F84-G84 -> 7691914
A87: Pic Team Hunter | B87: New Member | C87: Paket Langganan | D87: User | F87: Penjualan
D88: Target | E88: Realisasi | F88: Target | G88: Realisasi
A89: Laura | B89: Basic 12 | C89: 858000 | D89: 2 | E89: 0 | F89: =C89*D89 -> 1716000 | G89: 858000
B90: Business 6 | C90: 708000 | D90: 1 | E90: 0 | F90: =C90*D90 -> 708000 | G90: =E90*C90 -> 0
B91: Business 9 | C91: 998000 | D91: 0 | E91: 0 | F91: =C91*D91 -> 0 | G91: =E91*C91 -> 0
B92: Business 12 | C92: 1298000 | D92: 2 | E92: 0 | F92: =C92*D92 -> 2596000 | G92: =E92*C92 -> 0
B93: Pro 12 | C93: 1688000 | D93: 3 | E93: 0 | F93: =C93*D93 -> 5064000 | G93: =E93*C93 -> 0
B94: Jagoan Business | C94: 1598000 | D94: 1 | E94: 0 | F94: =C94*D94 -> 1598000 | G94: =E94*C94 -> 0
B95: Jagoan Pro | C95: 2078000 | D95: 1 | E95: 0 | F95: =C95*D95 -> 2078000 | G95: =E95*C95 -> 0
A96: Total Penjualan | D96: =sum(D89:D95) -> 10 | E96: =sum(E89:E95) -> 0 | F96: =sum(F89:F95) -> 13760000 | G96: =sum(G89:G95) -> 858000
A97: Kekurangan | D97: =D96-E96 -> 10 | F97: =F96-G96 -> 12902000
A101: TEAM HUNTER
A102: Target Maret 2026
A103: Pic Team Hunter | B103: Target User | C103: Target Nominal | D103: Realisasi | F103: Kekurangan
D104: User | E104: Omset | F104: User | G104: Omset
A105: Lidya | B105: =D119 -> 11 | C105: =F119 -> 14368000 | D105: =E119 -> 5 | E105: =G119 -> 6830000 | F105: =B105-D105 -> 6 | G105: =C105-E105 -> 7538000
A106: Laura | B106: =D131 -> 1 | C106: =F131 -> 1688000 | D106: =E131 -> 1 | E106: =G131 -> 1688000 | F106: =B106-D106 -> 0 | G106: =C106-E106 -> 0
A107: Total Pencapaian | B107: =sum(B105:B106) -> 12 | C107: =sum(C105:C106) -> 16056000 | D107: =sum(D105:D106) -> 6 | E107: =sum(E105:E106) -> 8518000 | F107: =sum(F105:F106) -> 6 | G107: =sum(G105:G106) -> 7538000
A108: Total Kekurangan [%] | B108: =B107/B107 -> 1 | C108: =C107/C107 -> 1 | D108: =D107/B107 -> 0.5 | E108: =E107/C107 -> 0.53051819 | F108: =F107/B107 -> 0.5 | G108: =G107/C107 -> 0.46948181
A110: Pic Team Hunter | B110: New Member | C110: Paket Langganan | D110: User | F110: Penjualan
D111: Target | E111: Realisasi | F111: Target | G111: Realisasi
A112: Lidya | B112: Basic 12 | C112: 858000 | D112: 2 | E112: 1 | F112: =C112*D112 -> 1716000 | G112: =E112*C112 -> 858000
...

Sheet JOBDESK 
A1: Ceklist daily jobdesk team sales
A2: PBGC 2 Lidya Marpaung
A3: Divisi : Business Growth Consultant
A4: No | B4: JobDesk | C4: Target | D4: Validasi (Businesse Control)
E5: 46176 | F5: 46177 | G5: 46178 | H5: 46181 | I5: 46182 | J5: 46183 | K5: 46184 | L5: 46185 | M5: 46188 | N5: 46190 | O5: 46191 | P5: 46192 | Q5: 46195 | R5: 46196 | S5: 46197 | T5: 46198 | U5: 46199 | V5: 46202 | W5: 46203
A6: 1 | B6: Follow up data kelolaan | C6: 50 | D6: FALSE | E6: TRUE | F6: TRUE | G6: FALSE | H6: TRUE | I6: TRUE | J6: TRUE | K6: TRUE | L6: TRUE | M6: TRUE | N6: TRUE | O6: FALSE | P6: FALSE | Q6: FALSE | R6: FALSE | S6: FALSE | T6: FALSE | U6: FALSE | V6: FALSE | W6: FALSE
A7: 2 | B7: Follow up data nasabah new download - Project list & new outlet | C7: 10 | D7: FALSE | E7: TRUE | F7: TRUE | G7: FALSE | H7: TRUE | I7: TRUE | J7: TRUE | K7: TRUE | L7: TRUE | M7: TRUE | N7: TRUE | O7: FALSE | P7: FALSE | Q7: FALSE | R7: FALSE | S7: FALSE | T7: FALSE | U7: FALSE | V7: FALSE | W7: FALSE
A8: 3 | B8: Follow up data nasabah potensi | C8: 5 | D8: FALSE | E8: TRUE | F8: TRUE | G8: FALSE | H8: TRUE | I8: TRUE | J8: TRUE | K8: TRUE | L8: TRUE | M8: TRUE | N8: TRUE | O8: FALSE | P8: FALSE | Q8: FALSE | R8: FALSE | S8: FALSE | T8: FALSE | U8: FALSE | V8: FALSE | W8: FALSE
A9: 4 | B9: Follow up data nasabah jatuh tempo | C9: 20 | D9: FALSE | E9: TRUE | F9: TRUE | G9: FALSE | H9: TRUE | I9: TRUE | J9: TRUE | K9: TRUE | L9: TRUE | M9: TRUE | N9: TRUE | O9: FALSE | P9: FALSE | Q9: FALSE | R9: FALSE | S9: FALSE | T9: FALSE | U9: FALSE | V9: FALSE | W9: FALSE
A10: 5 | B10: Follow up mitra kelolaan & akuisisi new mitra | C10: 5 | D10: FALSE | E10: TRUE | F10: FALSE | G10: FALSE | H10: TRUE | I10: FALSE | J10: FALSE | K10: TRUE | L10: FALSE | M10: FALSE | N10: FALSE | O10: FALSE | P10: FALSE | Q10: FALSE | R10: FALSE | S10: FALSE | T10: FALSE | U10: FALSE | V10: FALSE | W10: FALSE
A11: 6 | B11: Posting konten di whatsapp | C11: - | D11: FALSE | E11: TRUE | F11: TRUE | G11: FALSE | H11: TRUE | I11: TRUE | J11: TRUE | K11: TRUE | L11: TRUE | M11: TRUE | N11: TRUE | O11: TRUE | P11: FALSE | Q11: FALSE | R11: FALSE | S11: FALSE | T11: FALSE | U11: FALSE | V11: FALSE | W11: FALSE
A12: 7 | B12: Posting konten di Instagram, Tiktok dan Facebook | C12: - | D12: FALSE | E12: TRUE | F12: TRUE | G12: FALSE | H12: FALSE | I12: TRUE | J12: TRUE | K12: FALSE | L12: TRUE | M12: TRUE | N12: TRUE | O12: TRUE | P12: FALSE | Q12: FALSE | R12: FALSE | S12: FALSE | T12: FALSE | U12: FALSE | V12: FALSE | W12: FALSE
A13: 8 | B13: Follow up nasabah yang belum memberikan rating & logo laundry | C13: 5 | D13: FALSE | E13: TRUE | F13: TRUE | G13: FALSE | H13: TRUE | I13: FALSE | J13: FALSE | K13: TRUE | L13: FALSE | M13: FALSE | N13: TRUE | O13: FALSE | P13: FALSE | Q13: FALSE | R13: FALSE | S13: FALSE | T13: FALSE | U13: FALSE | V13: FALSE | W13: FALSE
A14: 9 | B14: Daily report follow up data kelolaan (WA Group) | C14: - | D14: FALSE | E14: FALSE | F14: FALSE | G14: FALSE | H14: FALSE | I14: FALSE | J14: FALSE | K14: FALSE | L14: FALSE | M14: FALSE | N14: FALSE | O14: FALSE | P14: FALSE | Q14: FALSE | R14: FALSE | S14: FALSE | T14: FALSE | U14: FALSE | V14: FALSE | W14: FALSE
A15: 10 | B15: Daily report follow up data jatuh tempo(WA Group) | C15: - | D15: FALSE | E15: TRUE | F15: TRUE | G15: FALSE | H15: TRUE | I15: TRUE | J15: FALSE | K15: TRUE | L15: TRUE | M15: TRUE | N15: TRUE | O15: FALSE | P15: FALSE | Q15: FALSE | R15: FALSE | S15: FALSE | T15: FALSE | U15: FALSE | V15: FALSE | W15: FALSE
A16: 11 | B16: Pengisian data kelolaan | C16: - | D16: FALSE | E16: TRUE | F16: TRUE | G16: FALSE | H16: TRUE | I16: TRUE | J16: TRUE | K16: TRUE | L16: TRUE | M16: TRUE | N16: TRUE | O16: FALSE | P16: FALSE | Q16: FALSE | R16: FALSE | S16: FALSE | T16: FALSE | U16: FALSE | V16: FALSE | W16: FALSE

Sheet K.-Lidya
A1: PT PIPOSMART DIGITAL INDONESIA
A2: Data Kelolaan Nasabah
A3: Pengertian Scorsing = 0. (Tidak Tertarik) 1. (New Download) 2. (Potensial) 3. (Berlangganan)
A4: Total Fu | B4: Tanggal Fu | C4: Tahun | D4: Bulan | E4: No | F4: Tanggal Dibagikan (Data) | G4: Status Akun | H4: Kode Baris | I4: Kode Owner | J4: Nama Owner | K4: Project/Brand | L4: Outlet | M4: No. HP Owner | N4: No. HP Outlet | O4: Create Date Project | P4: Expired Date | Q4: Total Transaksi | R4: Scor | S4: Call | T4: Chat | U4: Validitas | V4: Remaks | W4: Sumber Nasabah | X4: Finalisasi (Closing) | Y4: Nominal | Z4: Noted | AA4: Audit
A5: =COUNTIF('Call & Chat-Lidya'!$I$4:$I$2433,I5) -> 5 | B5: 46188 | C5: 2026 | D5: Juni | E5: 6 | F5: 46175 | G5: AKun Baru | H5: 11313 | I5: 18907 | J5: Bubble's~2 | K5: Bubble 2 | L5: Bubble 2 | M5: 085240267611 | O5: 46175 | P5: 46189 | Q5: 4 | R5: 3 | S5: NO CALL | T5: PROSPECT | U5: VALID | V5: (3) Berlangganan | X5: Basic | Y5: 858000 | Z5: reminder untuk perpanjangan berlanganan dan penjelasan promo berlangganan dan nasabah sudah melakukan pembayaran dan sudah aktivasi membership
A6: =COUNTIF('Call & Chat-Lidya'!$I$4:$I$2433,I6) -> 2 | B6: 46185 | C6: 2026 | D6: Juni | E6: 7 | F6: 46175 | G6: AKun Baru | H6: 10828 | I6: 18070 | J6: Ramlah 15 | K6: IRA LAUNDRY | L6: IRA LAUNDRY | M6: 085252472966 | N6: 082252472966 | O6: 46090 | P6: 46104 | Q6: 0 | R6: 0 | S6: CONTACTED | T6: NO CHAT | U6: INVALID | V6: (0) Tidak Merespon | Z6: Nomor tidak terhubung dengan wa
A7: =COUNTIF('Call & Chat-Lidya'!$I$4:$I$2433,I7) -> 2 | B7: 46185 | C7: 2026 | D7: Juni | E7: 8 | F7: 46175 | G7: AKun Baru | H7: 10850 | I7: 18104 | J7: Sofiah ichwani | K7: Azzahra laundry | L7: Azzahra laundry | M7: 081269923421 | N7: 081269923421 | O7: 46095 | P7: 46109 | Q7: 4 | R7: 1 | S7: CONTACTED | T7: DELIVERED | U7: VALID | V7: (0) Tidak Merespon
A8: =COUNTIF('Call & Chat-Lidya'!$I$4:$I$2433,I8) -> 1 | B8: 46175 | C8: 2026 | D8: Juni | E8: 9 | F8: 46175 | G8: AKun Baru | H8: 10854 | I8: 18108 | J8: Amanda Artha | K8: Laundry | L8: Laundry | M8: 089518979800 | N8: 08522236974 | O8: 46097 | R8: 0 | Z8: Akun tim karna sudah aktivasi membership tanpa ada bukti pembayaran dari transfer
A9: =COUNTIF('Call & Chat-Lidya'!$I$4:$I$2433,I9) -> 2 | B9: 46185 | C9: 2026 | D9: Juni | E9: 10 | F9: 46175 | G9: AKun Baru | H9: 10860 | I9: 18117 | J9: Aswar Anas | K9: Laundry.KU | L9: Laundry.KU | M9: 082291364112 | N9: 082291364112 | O9: 46098 | P9: 46112 | Q9: 0 | R9: 1 | S9: CONTACTED | T9: DELIVERED | U9: VALID | V9: (0) Tidak Merespon
A10: =COUNTIF('Call & Chat-Lidya'!$I$4:$I$2433,I10) -> 2 | B10: 46185 | C10: 2026 | D10: Juni | E10: 11 | F10: 46175 | G10: AKun Baru | H10: 10865 | I10: 18124 | J10: Slastia | K10: LAUNDRY 99 KARAWANG | L10: LAUNDRY 99 KARAWANG | M10: 089630415505 | N10: 089630415505 | O10: 46099 | P10: 46113 | Q10: 0 | R10: 1 | S10: CONTACTED | T10: DELIVERED | U10: VALID | V10: (0) Tidak Merespon
A11: =COUNTIF('Call & Chat-Lidya'!$I$4:$I$2433,I11) -> 2 | B11: 46185 | C11: 2026 | D11: Juni | E11: 12 | F11: 46175 | G11: AKun Baru | H11: 10867 | I11: 18126 | J11: Ica Vera | K11: terima uang | L11: terima uang | M11: 082128887889 | N11: 082128887889 | O11: 46100 | P11: 46114 | Q11: 0 | R11: 0 | S11: CONTACTED | T11: SENT | U11: INVALID | V11: (0) Tidak Merespon
A12: =COUNTIF('Call & Chat-Lidya'!$I$4:$I$2433,I12) -> 2 | B12: 46185 | C12: 2026 | D12: Juni | E12: 13 | F12: 46175 | G12: AKun Baru | H12: 10871 | I12: 18132 | J12: ori zapp | K12: Geubrina londry | L12: Geubrina londry | M12: 085136305406 | N12: 085136305406 | O12: 46102 | P12: 46116 | Q12: 2 | R12: 1 | S12: CONTACTED | T12: DELIVERED | U12: VALID | V12: (0) Tidak Merespon
A13: =COUNTIF('Call & Chat-Lidya'!$I$4:$I$2433,I13) -> 2 | B13: 46185 | C13: 2026 | D13: Juni | E13: 14 | F13: 46175 | G13: AKun Baru | H13: 10876 | I13: 18140 | J13: Batapas Laundry Express | K13: Batapas Laundry Express | L13: Batapas Laundry Express | M13: 085960224716 | N13: 085960224716 | O13: 46104 | P13: 46118 | Q13: 1 | R13: 1 | S13: CONTACTED | T13: DELIVERED | U13: VALID | V13: (0) Tidak Merespon
A14: =COUNTIF('Call & Chat-Lidya'!$I$4:$I$2433,I14) -> 2 | B14: 46185 | C14: 2026 | D14: Juni | E14: 15 | F14: 46175 | G14: AKun Baru | H14: 10880 | I14: 18147 | J14: Moja Wash BSD | K14: mo | L14: mo | M14: 087887700094 | N14: 087887700094 | O14: 46106 | P14: 46120 | Q14: 0 | R14: 1 | S14: CONNECTED | T14: DELIVERED | U14: VALID | V14: (0) Tidak Merespon
A15: =COUNTIF('Call & Chat-Lidya'!$I$4:$I$2433,I15) -> 4 | B15: 46185 | C15: 2026 | D15: Juni | E15: 16 | F15: 46175 | G15: AKun Baru | H15: 10882 | I15: 18150 | J15: Abimanyu | K15: Laundry Yook | L15: Laundry Yook | M15: 0882007927333 | N15: 0882007927333 | O15: 46106 | P15: 46120 | Q15: 55 | R15: 1 | S15: CONTACTED | T15: DELIVERED | U15: VALID | V15: (0) Tidak Merespon
A16: =COUNTIF('Call & Chat-Lidya'!$I$4:$I$2433,I16) -> 5 | B16: 46190 | C16: 2026 | D16: Juni | E16: 17 | F16: 46175 | G16: AKun Baru | H16: 11315 | I16: 18911 | J16: sigit purnomo | K16: Laundry | L16: Mamas Laundry | M16: 081289304588 | O16: 46175 | P16: 46189 | Q16: 0 | R16: 1 | S16: CONNECTED | T16: DELIVERED | U16: VALID | V16: (0) Tidak Merespon
A17: =COUNTIF('Call & Chat-Lidya'!$I$4:$I$2433,I17) -> 3 | B17: 46190 | C17: 2026 | D17: Juni | E17: 18 | F17: 46175 | G17: AKun Baru | H17: 11316 | I17: 18912 | J17: Syariah Laundry | K17: Syariah Laundry | L17: Syariah Laundry | M17: 082181951816 | N17: 082181951816 | O17: 46175 | P17: 46189 | Q17: 0 | R17: 1 | S17: CONNECTED | T17: DELIVERED | U17: VALID | V17: (0) Data Employee dan Trial
A18: =COUNTIF('Call & Chat-Lidya'!$I$4:$I$2433,I18) -> 4 | B18: 46190 | C18: 2026 | D18: Juni | E18: 19 | F18: 46175 | G18: AKun Baru | H18: 11317 | I18: 18913 | J18: Elfira Yanti | K18: buk Yanti laundry | L18: buk Yanti laundry | M18: 082280298103 | N18: 082280298103 | O18: 46175 | P18: 46189 | Q18: 1 | R18: 1 | S18: CONNECTED | T18: UNINTEREST | U18: VALID | V18: (0) Data Employee dan Trial | Z18: Aplikasi piposmartnya tidak digunakan
A19: =COUNTIF('Call & Chat-Lidya'!$I$4:$I$2433,I19) -> 4 | B19: 46190 | C19: 2026 | D19: Juni | E19: 20 | F19: 46175 | G19: AKun Baru | H19: 11318 | I19: 18916 | J19: Yanti Fitria Sari | K19: JA londry | L19: JA londry | M19: 085283284078 | N19: 85283284078 | O19: 46175 | P19: 46189 | Q19: 0 | R19: 0 | S19: CONTACTED | T19: SENT | U19: INVALID | V19: (0) Nomor Diblokir
A20: =COUNTIF('Call & Chat-Lidya'!$I$4:$I$2433,I20) -> 4 | B20: 46185 | C20: 2026 | D20: Juni | E20: 21 | F20: 46176 | G20: AKun Baru | H20: 10882 | I20: 18150 | J20: Abimanyu | K20: WOW LAUNDRY | L20: Laundry Yook | M20: 0882007927333 | N20: 0882007927333 | O20: 46106 | P20: 46120 | Q20: 111 | R20: 1 | S20: CONTACTED | T20: DELIVERED | U20: VALID | V20: (0) Tidak Merespon
A21: =COUNTIF('Call & Chat-Lidya'!$I$4:$I$2433,I21) -> 2 | B21: 46185 | C21: 2026 | D21: Juni | E21: 22 | F21: 46176 | G21: AKun Baru | H21: 10886 | I21: 18155 | J21: Owner | K21: 24Laundry | L21: 24Laundry | M21: 081334428518 | N21: 085156239895 | O21: 46106 | P21: 46120 | Q21: 24 | R21: 1 | S21: CONTACTED | T21: DELIVERED | U21: VALID | V21: (0) Tidak Merespon
A22: =COUNTIF('Call & Chat-Lidya'!$I$4:$I$2433,I22) -> 2 | B22: 46185 | C22: 2026 | D22: Juni | E22: 23 | F22: 46176 | G22: AKun Baru | H22: 10890 | I22: 18163 | J22: Gusti Ayu Aris Widyantari | K22: Paradis Laundry | L22: Paradis Laundry | M22: 081239382543 | N22: 082266853437 | O22: 46107 | P22: 46121 | Q22: 0 | R22: 1 | S22: CONNECTED | T22: DELIVERED | U22: VALID | V22: (0) Tidak Merespon
A23: =COUNTIF('Call & Chat-Lidya'!$I$4:$I$2433,I23) -> 2 | B23: 46185 | C23: 2026 | D23: Juni | E23: 24 | F23: 46176 | G23: AKun Baru | H23: 10892 | I23: 18165 | J23: Nanda Aulia | K23: Ara Laundry | L23: Ara Laundry | M23: 085215899395 | N23: 085215899395 | O23: 46107 | P23: 46121 | Q23: 10 | R23: 1 | S23: CONTACTED | T23: DELIVERED | U23: VALID | V23: (0) Tidak Merespon
A24: =COUNTIF('Call & Chat-Lidya'!$I$4:$I$2433,I24) -> 1 | B24: 46176 | C24: 2026 | D24: Juni | E24: 25 | F24: 46176 | G24: AKun Baru | H24: 10900 | I24: 18176 | J24: Nurliah | K24: Agnifa Laundry | L24: Agnifa Laundry | M24: 081321973546 | N24: 08998975443 | O24: 46109 | P24: 46123 | Q24: 2 | R24: 1 | S24: ENGAGE | T24: DELIVERED | U24: VALID | V24: (0) Data Employee dan Trial | Z24: Konfirmasi penggunaan aplikasi dan call langsung dimatikan
A25: =COUNTIF('Call & Chat-Lidya'!$I$4:$I$2433,I25) -> 2 | B25: 46185 | C25: 2026 | D25: Juni | E25: 26 | F25: 46176 | G25: AKun Baru | H25: 10916 | I25: 18201 | J25: anindia | K25: Star Laundry 2 | L25: Star Laundry 2 | M25: 085820557960 | N25: 085820557960 | O25: 46112 | P25: 46126 | Q25: 0 | R25: 1 | S25: ENGAGE | T25: DELIVERED | U25: VALID | V25: (0) Data Employee dan Trial | Z25: Konfirmasi penggunaan aplikasi piposmart dan call langsung dimatikan
A26: =COUNTIF('Call & Chat-Lidya'!$I$4:$I$2433,I26) -> 2 | B26: 46185 | C26: 2026 | D26: Juni | E26: 27 | F26: 46176 | G26: AKun Baru | H26: 10920 | I26: 18214 | J26: Arkan laundry | K26: Arkan Laundry | L26: Arkan Laundry | M26: 083150654324 | N26: 083150654324 | O26: 46114 | P26: 46128 | Q26: 8 | R26: 1 | S26: ENGAGE | T26: DELIVERED | U26: VALID | V26: (0) Data Employee dan Trial | Z26: Konfirmasi penggunaan aplikasi piposmart dan call langsung dimatikan
A27: =COUNTIF('Call & Chat-Lidya'!$I$4:$I$2433,I27) -> 2 | B27: 46185 | C27: 2026 | D27: Juni | E27: 28 | F27: 46176 | G27: AKun Baru | H27: 10924 | I27: 18220 | J27: Kanza Aulia | K27: Jastrika | L27: Jastrika | M27: 0895342756135 | N27: 0895342756135 | O27: 46114 | P27: 46128 | Q27: 1 | R27: 1 | S27: CONNECTED | T27: DELIVERED | U27: VALID | V27: (0) Tidak Merespon
A28: =COUNTIF('Call & Chat-Lidya'!$I$4:$I$2433,I28) -> 2 | B28: 46185 | C28: 2026 | D28: Juni | E28: 29 | F28: 46176 | G28: AKun Baru | H28: 10932 | I28: 18235 | J28: Arwina | K28: Win Laundry | L28: Win Laundry | M28: 088245670913 | N28: 088245670913 | O28: 46116 | P28: 46130 | Q28: 0 | R28: 1 | S28: CONTACTED | T28: DELIVERED | U28: VALID | V28: (0) Tidak Merespon
A29: =COUNTIF('Call & Chat-Lidya'!$I$4:$I$2433,I29) -> 2 | B29: 46185 | C29: 2026 | D29: Juni | E29: 30 | F29: 46176 | G29: AKun Baru | H29: 10935 | I29: 18239 | J29: feny setiani | K29: Cleanwash Laundry | L29: Cleanwash Laundry | M29: 0895372027589 | O29: 46117 | P29: 46131 | Q29: 0 | R29: 1 | S29: CONNECTED | T29: DELIVERED | U29: VALID | V29: (0) Tidak Merespon
A30: =COUNTIF('Call & Chat-Lidya'!$I$4:$I$2433,I30) -> 2 | B30: 46185 | C30: 2026 | D30: Juni | E30: 31 | F30: 46176 | G30: AKun Baru | H30: 10959 | I30: 18286 | J30: Ariana | K30: Anah laundry | L30: Anah laundry | M30: 081220754792 | N30: 081220754792 | O30: 46120 | P30: 46134 | Q30: 1 | R30: 1 | S30: CONTACTED | T30: DELIVERED | U30: VALID | V30: (0) Tidak Merespon
A31: =COUNTIF('Call & Chat-Lidya'!$I$4:$I$2433,I31) -> 2 | B31: 46185 | C31: 2026 | D31: Juni | E31: 32 | F31: 46176 | G31: AKun Baru | H31: 10977 | I31: 18313 | J31: mamaJO | K31: mamaJO LAUNDRY | L31: mamaJO LAUNDRY | M31: 082374564878 | O31: 46123 | P31: 46137 | Q31: 5 | R31: 1 | S31: CONTACTED | T31: DELIVERED | U31: VALID | V31: (0) Tidak Merespon
A32: =COUNTIF('Call & Chat-Lidya'!$I$4:$I$2433,I32) -> 2 | B32: 46185 | C32: 2026 | D32: Juni | E32: 33 | F32: 46176 | G32: AKun Baru | H32: 10992 | I32: 18346 | J32: Mariana | K32: Sint Loundry | L32: Sint Loundry | M32: 082180157705 | N32: 082180157705 | O32: 46125 | P32: 46139 | Q32: 0 | R32: 1 | S32: CONTACTED | T32: DELIVERED | U32: VALID | V32: (0) Tidak Merespon
A33: =COUNTIF('Call & Chat-Lidya'!$I$4:$I$2433,I33) -> 2 | B33: 46185 | C33: 2026 | D33: Juni | E33: 34 | F33: 46176 | G33: AKun Baru | H33: 10996 | I33: 18351 | J33: zuria lidiana | K33: Myesha laundry | L33: Myesha laundry | M33: 081361415817 | N33: 085369967799 | O33: 46126 | P33: 46140 | Q33: 3 | R33: 1 | S33: ENGAGE | T33: DELIVERED | U33: VALID | V33: (0) Data Employee dan Trial | Z33: Konfirmasi penggunaan aplikasi piposmart dan call langsung dimatikan
A34: =COUNTIF('Call & Chat-Lidya'!$I$4:$I$2433,I34) -> 4 | B34: 46188 | C34: 2026 | D34: Juni | E34: 35 | F34: 46176 | G34: AKun Baru | H34: 11320 | I34: 18919 | J34: Risnul Syafrizal | K34: Skuyy Laundry | L34: Skuyy Laundry | M34: 082170927742 | N34: 5169170881 | O34: 46176 | P34: 46190 | Q34: 110 | R34: 3 | S34: PROSPECT | T34: DELIVERED | U34: VALID | V34: (3) Berlangganan | W34: Playstore | X34: Business | Y34: 118070 | Z34: Sejauh ini aplikasi piposmartnya belum ada kendala dan rencana berlangganan hari dengan paket 1 bulan bisnis dan akan dihubungi kembali
A35: =COUNTIF('Call & Chat-Lidya'!$I$4:$I$2433,I35) -> 2 | B35: 46185 | C35: 2026 | D35: Juni | E35: 36 | F35: 46178 | G35: AKun Baru | H35: 11001 | I35: 18359 | J35: Clink Mojokerto | K35: klemiz | L35: klemiz | M35: 085633335268 | N35: 085666326984 | O35: 46127 | P35: 46141 | Q35: 0 | R35: 1 | S35: CONTACTED | T35: NO CHAT | U35: INVALID | V35: (0) Tidak Merespon | Z35: Nomor tidak terhubung dengan wa
A36: =COUNTIF('Call & Chat-Lidya'!$I$4:$I$2433,I36) -> 2 | B36: 46185 | C36: 2026 | D36: Juni | E36: 37 | F36: 46178 | G36: AKun Baru | H36: 11007 | I36: 18373 | J36: dehazby dehazby | K36: CK Lona Laundry | L36: CK Lona Laundry | M36: 088216036140 | N36: 088216036140 | O36: 46128 | P36: 46142 | Q36: 2 | R36: 1 | S36: CONNECTED | T36: DELIVERED | U36: VALID | V36: (0) Tidak Merespon
A37: =COUNTIF('Call & Chat-Lidya'!$I$4:$I$2433,I37) -> 2 | B37: 46185 | C37: 2026 | D37: Juni | E37: 38 | F37: 46178 | G37: AKun Baru | H37: 11017 | I37: 18390 | J37: Wahyuni Ida ningsih | K37: Mawar | L37: Mawar | M37: 08991857388 | O37: 46129 | P37: 46143 | Q37: 6 | R37: 1 | S37: CONNECTED | T37: DELIVERED | U37: VALID | V37: (0) Tidak Merespon
A38: =COUNTIF('Call & Chat-Lidya'!$I$4:$I$2433,I38) -> 1 | B38: 46181 | C38: 2026 | D38: Juni | E38: 39 | F38: 46178 | G38: AKun Baru | H38: 11033 | I38: 18437 | J38: Dwi Wullan | K38: Omah Laundry | L38: Omah Laundry | M38: 087743123571 | N38: 087743123571 | O38: 46133 | P38: 46147 | Q38: 0 | R38: 1 | S38: ENGAGE | T38: DELIVERED | U38: VALID | V38: (0) Data Employee dan Trial | Z38: Konfirmasi penggunaan aplikasi piposmart dan call langsung dimatikan
A39: =COUNTIF('Call & Chat-Lidya'!$I$4:$I$2433,I39) -> 2 | B39: 46185 | C39: 2026 | D39: Juni | E39: 40 | F39: 46178 | G39: AKun Baru | H39: 11035 | I39: 18440 | J39: Ade Nandy Wirya | K39: Hoky Laundry Jambi | L39: Hoky Laundry Jambi | M39: 081272706900 | N39: 081272706900 | O39: 46133 | P39: 46147 | Q39: 0 | R39: 1 | S39: CONTACTED | T39: DELIVERED | U39: VALID | V39: (0) Tidak Merespon
A40: =COUNTIF('Call & Chat-Lidya'!$I$4:$I$2433,I40) -> 2 | B40: 46185 | C40: 2026 | D40: Juni | E40: 41 | F40: 46178 | G40: AKun Baru | H40: 11037 | I40: 18443 | J40: Dewi 5198 | K40: Rumah loundry | L40: Rumah loundry | N40: 085373405848 | O40: 46134 | P40: 46148 | Q40: 0 | R40: 1 | S40: CONTACTED | T40: DELIVERED | U40: VALID | V40: (0) Tidak Merespon
A41: =COUNTIF('Call & Chat-Lidya'!$I$4:$I$2433,I41) -> 2 | B41: 46185 | C41: 2026 | D41: Juni | E41: 42 | F41: 46178 | G41: AKun Baru | H41: 11045 | I41: 18453 | J41: Washoenday | K41: Washoenday | L41: Washoenday | M41: 085729199945 | N41: 085729199945 | O41: 46134 | P41: 46148 | Q41: 0 | R41: 1 | S41: CONTACTED | T41: DELIVERED | U41: VALID | V41: (0) Tidak Merespon
A42: =COUNTIF('Call & Chat-Lidya'!$I$4:$I$2433,I42) -> 1 | B42: 46181 | C42: 2026 | D42: Juni | E42: 43 | F42: 46178 | G42: AKun Baru | H42: 11051 | I42: 18465 | J42: dina napitupulu | K42: Jlaundry | L42: Jlaundry | M42: 087873419121 | N42: 084679 | O42: 46135 | P42: 46149 | Q42: 1 | R42: 1 | S42: CONNECTED | T42: DELIVERED | U42: VALID | V42: (0) Tidak Merespon
A43: =COUNTIF('Call & Chat-Lidya'!$I$4:$I$2433,I43) -> 1 | B43: 46181 | C43: 2026 | D43: Juni | E43: 44 | F43: 46178 | G43: AKun Baru | H43: 11052 | I43: 18467 | J43: Sani Wahyu nugroho | K43: toko | L43: toko | M43: 62895325406749 | N43: 62895325406749 | O43: 46135 | P43: 46149 | Q43: 0 | R43: 1 | S43: CONTACTED | T43: DELIVERED | U43: VALID | V43: (0) Tidak Merespon
A44: =COUNTIF('Call & Chat-Lidya'!$I$4:$I$2433,I44) -> 1 | B44: 46181 | C44: 2026 | D44: Juni | E44: 45 | F44: 46178 | G44: AKun Baru | H44: 11054 | I44: 18469 | J44: Apriliana putri | K44: ARULLIA LAUNDRY | L44: ARULLIA LAUNDRY | M44: 089510227711 | N44: 089510227711 | O44: 46135 | P44: 46149 | Q44: 2 | R44: 1 | S44: CONNECTED | T44: DELIVERED | U44: VALID | V44: (0) Tidak Merespon
A45: =COUNTIF('Call & Chat-Lidya'!$I$4:$I$2433,I45) -> 1 | B45: 46181 | C45: 2026 | D45: Juni | E45: 46 | F45: 46178 | G45: AKun Baru | H45: 11059 | I45: 18476 | J45: Asya Kamila | K45: KAMILA LAUNDRY | L45: KAMILA LAUNDRY | M45: 082314145522 | N45: 082314145522 | O45: 46136 | P45: 46150 | Q45: 2 | R45: 1 | S45: CONNECTED | T45: DELIVERED | U45: VALID | V45: (0) Tidak Merespon
A46: =COUNTIF('Call & Chat-Lidya'!$I$4:$I$2433,I46) -> 1 | B46: 46181 | C46: 2026 | D46: Juni | E46: 47 | F46: 46178 | G46: AKun Baru | H46: 11060 | I46: 18477 | J46: Deva Konaania | K46: Adewa | L46: Adewa | M46: 085339558912 | N46: 03617831748 | O46: 46136 | P46: 46150 | Q46: 3 | R46: 1 | S46: CONNECTED | T46: DELIVERED | U46: VALID | V46: (0) Tidak Merespon
A47: =COUNTIF('Call & Chat-Lidya'!$I$4:$I$2433,I47) -> 1 | B47: 46181 | C47: 2026 | D47: Juni | E47: 48 | F47: 46178 | G47: AKun Baru | H47: 11061 | I47: 18478 | J47: Nurani | K47: Setrikain | L47: Setrikain | M47: 085642006464 | N47: 085642006464 | O47: 46136 | P47: 46150 | Q47: 8 | R47: 1 | S47: CONNECTED | T47: DELIVERED | U47: VALID | V47: (0) Tidak Merespon
A48: =COUNTIF('Call & Chat-Lidya'!$I$4:$I$2433,I48) -> 1 | B48: 46181 | C48: 2026 | D48: Juni | E48: 49 | F48: 46178 | G48: AKun Baru | H48: 11062 | I48: 18479 | J48: Ninik | K48: BESTIE LAUNDRY | L48: BESTIE LAUNDRY | M48: 081994801008 | N48: 081994801008 | O48: 46136 | P48: 46150 | Q48: 2 | R48: 1 | S48: CONNECTED | T48: DELIVERED | U48: VALID | V48: (0) Tidak Merespon
A49: =COUNTIF('Call & Chat-Lidya'!$I$4:$I$2433,I49) -> 1 | B49: 46181 | C49: 2026 | D49: Juni | E49: 50 | F49: 46178 | G49: AKun Baru | H49: 11063 | I49: 18480 | J49: Emir Laundry | K49: Emir Laundry | L49: Emir Laundry | M49: 085156361726 | N49: 085156361726 | O49: 46137 | P49: 46151 | Q49: 0 | R49: 1 | S49: CONTACTED | T49: SENT | U49: VALID | V49: (0) Tidak Merespon
A50: =COUNTIF('Call & Chat-Lidya'!$I$4:$I$2433,I50) -> 1 | B50: 46181 | C50: 2026 | D50: Juni | E50: 51 | F50: 46178 | G50: AKun Baru | H50: 11064 | I50: 18481 | J50: mami babang | K50: Laundrykingkong | L50: Laundrykingkong | M50: 085348558783 | N50: 085245010585 | O50: 46137 | P50: 46151 | Q50: 1 | R50: 1 | S50: CONTACTED | T50: DELIVERED | U50: VALID | V50: (0) Tidak Merespon
A51: =COUNTIF('Call & Chat-Lidya'!$I$4:$I$2433,I51) -> 8 | B51: 46190 | C51: 2026 | D51: Juni | E51: 52 | F51: 46178 | G51: AKun Baru | H51: 11324 | I51: 18926 | J51: Tawakkal | K51: New Malomo Laundry | L51: New Malomo Laundry 01 | M51: 082333222543 | N51: 082333222543 | O51: 46177 | P51: 46191 | Q51: 6 | R51: 2 | S51: CONNECTED | T51: DELIVERED | U51: VALID | V51: (2) Trial, Demo, Interaktif | W51: Playstore
A52: =COUNTIF('Call & Chat-Lidya'!$I$4:$I$2433,I52) -> 2 | B52: 46190 | C52: 2026 | D52: Juni | E52: 53 | F52: 46178 | G52: AKun Baru | H52: 11326 | I52: 18930 | J52: rayyan | K52: rayyan laundry | L52: rayyan laundry | M52: 0895329286867 | N52: 082375740626 | O52: 46177 | P52: 46191 | Q52: 0 | R52: 1 | S52: ENGAGE | T52: DELIVERED | U52: VALID | V52: (0) Data Employee dan Trial | Z52: Konfirmasi penggunaan aplikasi piposmart dan call langsung dimatikan
A53: =COUNTIF('Call & Chat-Lidya'!$I$4:$I$2433,I53) -> 3 | B53: 46190 | C53: 2026 | D53: Juni | E53: 54 | F53: 46178 | G53: AKun Baru | H53: 11327 | I53: 18931 | J53: Dian Maulidini | K53: Yusuf Laundry | L53: Yusuf Laundry | M53: 081398606092 | N53: 081398606092 | O53: 46177 | P53: 46191 | Q53: 7 | R53: 2 | S53: INTEREST | T53: DELIVERED | U53: VALID | V53: (0) Data Karyawan dan Trial | W53: Facebook | Z53: Usaha laundry jalan 4 tahun dan masih menggunakan nota manual dan penjelasan sistem berlangganan dan paket promo berlangganan. Untuk berlangganan akan di diskusikan dulu dengan suaminya. Aplikasi tidak ada kendala dan mudah digunakan dan rencana penggunaan dia wal bulan juli dan reminder berlangganan tanggal 29 Juni
A54: =COUNTIF('Call & Chat-Lidya'!$I$4:$I$2433,I54) -> 8 | B54: 46190 | C54: 2026 | D54: Juni | E54: 52 | F54: 46178 | G54: AKun Baru | H54: 11324 | I54: 18926 | J54: Tawakkal | K54: New Malomo Laundry | L54: New Malomo Laundry | M54: 082333222543 | N54: 082333222543 | O54: 46177 | P54: 46191 | Q54: 6 | R54: 2 | S54: CONNECTED | T54: DELIVERED | U54: VALID | V54: (2) Trial, Demo, Interaktif | W54: Playstore
A55: =COUNTIF('Call & Chat-Lidya'!$I$4:$I$2433,I55) -> 4 | B55: 46190 | C55: 2026 | D55: Juni | E55: 56 | F55: 46178 | G55: AKun Baru | H55: 11331 | I55: 18938 | J55: Assalam Laundry | K55: Assalam Laundry | L55: Assalam Laundry | M55: 085602291180 | N55: 085602291180 | O55: 46178 | P55: 46192 | Q55: 0 | R55: 1 | S55: ENGAGE | T55: DELIVERED | U55: VALID | V55: (0) Data Employee dan Trial | Z55: Konfirmasi penggunaan aplikasi piposmart dan call langsung dimatikan
A56: =COUNTIF('Call & Chat-Lidya'!$I$4:$I$2433,I56) -> 1 | B56: 46182 | C56: 2026 | D56: Juni | E56: 57 | F56: 46179 | G56: Outlet Baru | H56: 2618 | I56: 3338 | J56: Pyen | K56: MY LAUNDRY | L56: MY LAUNDRY n DRY CLEANING | M56: 081287078508 | N56: 081389678957 | O56: 46178 | P56: 46209 | Q56: 25 | R56: 3 | S56: NO CALL | T56: DELIVERED | U56: VALID | V56: (3) Berlangganan
A57: =COUNTIF('Call & Chat-Lidya'!$I$4:$I$2433,I57) -> 4 | B57: 46190 | C57: 2026 | D57: Juni | E57: 58 | F57: 46179 | G57: AKun Baru | H57: 11334 | I57: 18946 | J57: moxie wash | K57: moxiewash | L57: moxiewash | M57: 0811868493 | N57: 08139999235 | O57: 46179 | P57: 46193 | Q57: 0 | R57: 0 | S57: NO CALL | T57: UNINTEREST | U57: VALID | V57: (0) Data Employee dan Trial | Z57: Aplikasi tidak digunakan dan tidak ada kendala karna kemarin hanya coba". Jika perlu nasabahnya yang akan menghubungi kembali
A58: =COUNTIF('Call & Chat-Lidya'!$I$4:$I$2433,I58) -> 3 | B58: 46188 | C58: 2026 | D58: Juni | E58: 59 | F58: 46180 | G58: AKun Baru | H58: 11336 | I58: 18952 | J58: Rizky Lia | K58: LaundryPedia | L58: LaundryPedia | M58: 0811198327 | N58: 0811198327 | O58: 46180 | P58: 46194 | Q58: 0 | R58: 0 | S58: PROSPECT | T58: ENGAGE | U58: VALID | V58: (0) Data Employee dan Trial | Z58: Rencana training hari ini namun di undur jadi besok pagi karna nasabahnya sedang padat jadwal di hari ini
A59: =COUNTIF('Call & Chat-Lidya'!$I$4:$I$2433,I59) -> 4 | B59: 46190 | C59: 2026 | D59: Juni | E59: 60 | F59: 46181 | G59: Outlet Baru | H59: 15536 | I59: 15510 | J59: Amanda | K59: cuciqu laundry | L59: CICERI DROP POINT | M59: 087798951222 | N59: 087798951222 | O59: 46181 | P59: 45822 | Q59: 0 | R59: 2 | S59: NO CALL | T59: DELIVERED | U59: VALID | V59: (2) Trial, Demo, Interaktif | W59: Playstore
A60: =COUNTIF('Call & Chat-Lidya'!$I$4:$I$2433,I60) -> 6 | B60: 46190 | C60: 2026 | D60: Juni | E60: 61 | F60: 46181 | G60: AKun Baru | H60: 11338 | I60: 18954 | J60: Dewi Anggraini | K60: We Laundry | L60: We Laundry | M60: 08161896392 | N60: 08161896392 | O60: 46181 | P60: 46195 | Q60: 3 | R60: 2 | S60: CONNECTED | T60: INTEREST | U60: VALID | V60: (2) Trial, Demo, Interaktif | W60: Playstore
A61: =COUNTIF('Call & Chat-Lidya'!$I$4:$I$2433,I61) -> 4 | B61: 46190 | C61: 2026 | D61: Juni | E61: 62 | F61: 46181 | G61: AKun Baru | H61: 11342 | I61: 18963 | J61: Cyclops Laundry | K61: Cyclops Laundry | L61: Cyclops Laundry | M61: 08218812277 | N61: 08218812277 | O61: 46181 | P61: 46195 | Q61: 2 | R61: 1 | S61: ENGAGE | T61: DELIVERED | U61: VALID | V61: (0) Data Employee dan Trial | Z61: Konfirmasi penggunaan aplikasi piposmart dan call langsung dimatikan
A62: =COUNTIF('Call & Chat-Lidya'!$I$4:$I$2433,I62) -> 4 | B62: 46190 | C62: 2026 | D62: Juni | E62: 63 | F62: 46181 | G62: Referral Mitra | H62: 11343 | I62: 18964 | J62: BRI Link Vania Loundry | K62: Vannessa Laundry | L62: Vannessa Laundry | M62: 085715609873 | N62: 085715609873 | O62: 46181 | P62: 46195 | Q62: 0 | R62: 2 | S62: CONNECTED | T62: DELIVERED | U62: VALID | V62: (2) Trial, Demo, Interaktif | W62: Mitra
A63: =COUNTIF('Call & Chat-Lidya'!$I$4:$I$2433,I63) -> 5 | B63: 46190 | C63: 2026 | D63: Juni | E63: 64 | F63: 46181 | G63: AKun Baru | H63: 11344 | I63: 18965 | J63: Hertati Simanjuntak | K63: miss resik laundry | L63: miss resik laundry | M63: 081280167784 | N63: 085813991103 | O63: 46181 | P63: 46195 | Q63: 1 | R63: 2 | S63: NO CALL | T63: DELIVERED | U63: VALID | V63: (2) Trial, Demo, Interaktif | W63: Mitra
A64: =COUNTIF('Call & Chat-Lidya'!$I$4:$I$2433,I64) -> 4 | B64: 46188 | C64: 2026 | D64: Juni | E64: 65 | F64: 46181 | G64: AKun Baru | H64: 11345 | I64: 18966 | J64: We Laundry | K64: We Laundry | L64: We Laundry | M64: 081292773006 | N64: 081292773006 | O64: 46181 | P64: 46195 | Q64: 0 | R64: 0 | S64: PROSPECT | T64: DELIVERED | U64: VALID | V64: (0) Data Karyawan dan Trial | Z64: Reminder kembali mengenai penyambungan printer thermal ke aplikasi, dan pagi ini ibunya belum ke laundry dan kemungkinan sore ke laundry dan jika sudah di laundry akan di hubungi kembali
A65: =COUNTIF('Call & Chat-Lidya'!$I$4:$I$2433,I65) -> 1 | B65: 46182 | C65: 2026 | D65: Juni | E65: 66 | F65: 46182 | G65: AKun Baru | H65: 11068 | I65: 18485 | J65: VK | K65: ZAHRA LAUNDRY | L65: ZAHRA LAUNDRY | M65: 085358912323 | N65: 085358912323 | O65: 46137 | P65: 46151 | Q65: 42 | R65: 1 | S65: CONNECTED | T65: DELIVERED | U65: VALID | V65: (0) Tidak Merespon
A66: =COUNTIF('Call & Chat-Lidya'!$I$4:$I$2433,I66) -> 1 | B66: 46182 | C66: 2026 | D66: Juni | E66: 67 | F66: 46182 | G66: AKun Baru | H66: 11078 | I66: 18509 | J66: NUR HAKIMIN | K66: RAFKA LAUNDRY | L66: RAFKA LAUNDRY | M66: 087846670412 | N66: 087846670412 | O66: 46139 | P66: 46153 | Q66: 0 | R66: 1 | S66: CONTACTED | T66: SENT | U66: INVALID | V66: (0) Tidak Merespon
A67: =COUNTIF('Call & Chat-Lidya'!$I$4:$I$2433,I67) -> 1 | B67: 46182 | C67: 2026 | D67: Juni | E67: 68 | F67: 46182 | G67: AKun Baru | H67: 11086 | I67: 18519 | J67: Siti Maesaroh | K67: Rumah Setrika | L67: Rumah Setrika | M67: 085363794875 | N67: 085762111795 | O67: 46140 | P67: 46154 | Q67: 4 | R67: 1 | S67: CONNECTED | T67: DELIVERED | U67: VALID | V67: (0) Tidak Merespon
A68: =COUNTIF('Call & Chat-Lidya'!$I$4:$I$2433,I68) -> 1 | B68: 46182 | C68: 2026 | D68: Juni | E68: 69 | F68: 46182 | G68: AKun Baru | H68: 11093 | I68: 18530 | J68: SUCI SUCIKA | K68: baju | L68: baju | M68: 08216030505 | N68: 08216030505 | O68: 46141 | P68: 46155 | Q68: 0 | R68: 1 | S68: CONNECTED | T68: DELIVERED | U68: VALID | V68: (0) Tidak Merespon
A69: =COUNTIF('Call & Chat-Lidya'!$I$4:$I$2433,I69) -> 1 | B69: 46182 | C69: 2026 | D69: Juni | E69: 70 | F69: 46182 | G69: AKun Baru | H69: 11097 | I69: 18534 | J69: Sifa Ajah | K69: barokah laundry | L69: barokah laundry | M69: 085601705836 | O69: 46141 | P69: 46155 | Q69: 0 | R69: 1 | S69: CONNECTED | T69: DELIVERED | U69: VALID | V69: (0) Tidak Merespon
A70: =COUNTIF('Call & Chat-Lidya'!$I$4:$I$2433,I70) -> 2 | B70: 46190 | C70: 2026 | D70: Juni | E70: 71 | F70: 46182 | G70: AKun Baru | H70: 11100 | I70: 18540 | J70: Hanin Laundry | K70: Hanin laundry | L70: Hanin laundry | M70: 081370907324 | N70: 085212096130 | O70: 46142 | P70: 46156 | Q70: 0 | R70: 2 | S70: PROSPECT | T70: DELIVERED | U70: VALID | V70: (2) Trial, Demo, Interaktif | Z70: Penjelasan biaya berlangganan dan rencana berlangganan 12 plus 6 bulan Pro, Reminder berlangganan besok tanggal 18 Juni 2026
A71: =COUNTIF('Call & Chat-Lidya'!$I$4:$I$2433,I71) -> 1 | B71: 46182 | C71: 2026 | D71: Juni | E71: 72 | F71: 46182 | G71: AKun Baru | H71: 11103 | I71: 18545 | J71: Hera Tristiana | K71: Maheza Laundry | L71: Maheza Laundry | M71: 081231313306 | N71: 081339935197 | O71: 46142 | P71: 46156 | Q71: 1 | R71: 0 | S71: UNINTEREST | T71: NO CHAT | U71: INVALID | V71: (0) Tidak jadi buka laundry | Z71: Tidak ada usaha laundry dan aplikasi tidak tau siapa yang download karna hp nya sudah hp jadul
A72: =COUNTIF('Call & Chat-Lidya'!$I$4:$I$2433,I72) -> 3 | B72: 46190 | C72: 2026 | D72: Juni | E72: 73 | F72: 46182 | G72: AKun Baru | H72: 11350 | I72: 18975 | J72: Wawan Hermawan | K72: emaluna laundry | L72: emaluna laundry | M72: 082147293334 | N72: 082147293334 | O72: 46182 | P72: 46196 | Q72: 0 | R72: 1 | S72: NO CALL | T72: DELIVERED | U72: VALID | V72: (0) Data Employee dan Trial | Z72: Nasabah sudah instal kembali dan daftar akun yang baru
A73: =COUNTIF('Call & Chat-Lidya'!$I$4:$I$2433,I73) -> 2 | B73: 46190 | C73: 2026 | D73: Juni | E73: 74 | F73: 46183 | G73: AKun Baru | H73: 11354 | I73: 18981 | J73: Rosmawatihadiarjo77 | K73: Alfian Laundry | L73: Alfian Laundry | M73: 088294365107 | N73: 088294365107 | O73: 46183 | P73: 46197 | Q73: 0 | R73: 1 | S73: CONTACTED | T73: DELIVERED | U73: VALID | V73: (0) Tidak Merespon
A74: =COUNTIF('Call & Chat-Lidya'!$I$4:$I$2433,I74) -> 3 | B74: 46190 | C74: 2026 | D74: Juni | E74: 75 | F74: 46184 | G74: Outlet Baru | H74: 8303 | I74: 12986 | J74: KEVIN SEVEN's | K74: SEVEN's LAUNDRY | L74: SEVEN's LAUNDRY 2 | M74: 085724591167 | N74: 085724591167 | O74: 46184 | P74: 45525 | Q74: 0 | R74: 1 | S74: CONNECTED | T74: DELIVERED | U74: VALID | V74: (0) Tidak Merespon | W74: Playstore
A75: =COUNTIF('Call & Chat-Lidya'!$I$4:$I$2433,I75) -> 1 | B75: 46184 | C75: 2026 | D75: Juni | E75: 76 | F75: 46184 | G75: AKun Baru | H75: 10709 | I75: 17894 | J75: Mariana imuadun | K75: Aliya Laundry Express Lopito | L75: Aliya Laundry Express Lopito | M75: 085159030523 | O75: 46071 | P75: 46085 | Q75: 10 | R75: 1 | S75: CONNECTED | T75: DELIVERED | U75: VALID | V75: (0) Tidak Merespon
A76: =COUNTIF('Call & Chat-Lidya'!$I$4:$I$2433,I76) -> 1 | B76: 46184 | C76: 2026 | D76: Juni | E76: 77 | F76: 46184 | G76: AKun Baru | H76: 10733 | I76: 17923 | J76: Amar Yuli | K76: Green house laundry | L76: Green house laundry | M76: 085865156156 | N76: 085643237336 | O76: 46074 | P76: 46088 | Q76: 1 | R76: 1 | S76: CONNECTED | T76: DELIVERED | U76: VALID | V76: (0) Tidak Merespon
A77: =COUNTIF('Call & Chat-Lidya'!$I$4:$I$2433,I77) -> 1 | B77: 46184 | C77: 2026 | D77: Juni | E77: 78 | F77: 46184 | G77: AKun Baru | H77: 10771 | I77: 17979 | J77: heni listyowati | K77: DAFFA LAUNDRY | L77: DAFFA LAUNDRY | M77: 089677757078 | N77: 089677757078 | O77: 46081 | P77: 46095 | Q77: 0 | R77: 1 | S77: CONNECTED | T77: DELIVERED | U77: VALID | V77: (0) Tidak Merespon
A78: =COUNTIF('Call & Chat-Lidya'!$I$4:$I$2433,I78) -> 1 | B78: 46184 | C78: 2026 | D78: Juni | E78: 79 | F78: 46184 | G78: AKun Baru | H78: 10857 | I78: 18111 | J78: richa wati | K78: Mira laundry | L78: Mira laundry | M78: 085855825771 | N78: 085855825771 | O78: 46098 | P78: 46112 | Q78: 0 | R78: 1 | S78: CONNECTED | T78: DELIVERED | U78: VALID | V78: (0) Tidak Merespon
A79: =COUNTIF('Call & Chat-Lidya'!$I$4:$I$2433,I79) -> 1 | B79: 46184 | C79: 2026 | D79: Juni | E79: 80 | F79: 46184 | G79: AKun Baru | H79: 10858 | I79: 18115 | J79: Salsa Bila | K79: kila laundry | L79: kila laundry | M79: 085921935406 | N79: 085921935406 | O79: 46098 | P79: 46112 | Q79: 0 | R79: 1 | S79: CONTACTED | T79: DELIVERED | U79: VALID | V79: (0) Tidak Merespon
A80: =COUNTIF('Call & Chat-Lidya'!$I$4:$I$2433,I80) -> 1 | B80: 46184 | C80: 2026 | D80: Juni | E80: 81 | F80: 46184 | G80: AKun Baru | H80: 10863 | I80: 18120 | J80: LAUNDRY RAYA | K80: laundry raya | L80: laundry raya | M80: 082310887532 | N80: 085217246881 | O80: 46099 | P80: 46113 | Q80: 1 | R80: 1 | S80: CONTACTED | T80: DELIVERED | U80: VALID | V80: (0) Tidak Merespon
A81: =COUNTIF('Call & Chat-Lidya'!$I$4:$I$2433,I81) -> 1 | B81: 46184 | C81: 2026 | D81: Juni | E81: 82 | F81: 46184 | G81: AKun Baru | H81: 10866 | I81: 18125 | J81: Winneto | K81: Winn Laundry | L81: Winn Laundry | M81: 087894714321 | N81: 087894714321 | O81: 46099 | P81: 46113 | Q81: 0 | R81: 1 | S81: CONTACTED | T81: DELIVERED | U81: VALID | V81: (0) Tidak Merespon
A82: =COUNTIF('Call & Chat-Lidya'!$I$4:$I$2433,I82) -> 1 | B82: 46184 | C82: 2026 | D82: Juni | E82: 83 | F82: 46184 | G82: AKun Baru | H82: 10869 | I82: 18130 | J82: Muhammad Fadli Syahputra | K82: Thahir Laundry | L82: Thahir Laundry | M82: 082312131219 | N82: 082312131219 | O82: 46101 | P82: 46115 | Q82: 0 | R82: 1 | S82: CONTACTED | T82: DELIVERED | U82: VALID | V82: (0) Tidak Merespon
A83: =COUNTIF('Call & Chat-Lidya'!$I$4:$I$2433,I83) -> 1 | B83: 46184 | C83: 2026 | D83: Juni | E83: 84 | F83: 46184 | G83: AKun Baru | H83: 10870 | I83: 18131 | J83: hadi setiawan | K83: Anugrah Laundry | L83: Anugrah Laundry | M83: 085158610056 | N83: 085158610056 | O83: 46101 | P83: 46115 | Q83: 1 | R83: 1 | S83: CONNECTED | T83: DELIVERED | U83: VALID | V83: (0) Tidak Merespon
A84: =COUNTIF('Call & Chat-Lidya'!$I$4:$I$2433,I84) -> 1 | B84: 46184 | C84: 2026 | D84: Juni | E84: 85 | F84: 46184 | G84: AKun Baru | H84: 10873 | I84: 18134 | J84: Lona G | K84: Laundry Mede29 | L84: Laundry Mede29 | M84: 085710252357 | N84: 085710252357 | O84: 46103 | P84: 46117 | Q84: 0 | R84: 1 | S84: ENGAGE | T84: DELIVERED | U84: VALID | V84: (0) Data Employee dan Trial | Z84: Aplikasi belum digunakan dan usaha laundry sudah berjalan, call langsung dimatikan
A85: =COUNTIF('Call & Chat-Lidya'!$I$4:$I$2433,I85) -> 1 | B85: 46184 | C85: 2026 | D85: Juni | E85: 86 | F85: 46184 | G85: AKun Baru | H85: 10874 | I85: 18136 | J85: widiana9 | K85: winner laundry | L85: winner laundry | N85: 081573875578 | O85: 46103 | P85: 46117 | Q85: 0 | R85: 1 | S85: CONTACTED | T85: DELIVERED | U85: VALID | V85: (0) Tidak Merespon
A86: =COUNTIF('Call & Chat-Lidya'!$I$4:$I$2433,I86) -> 1 | B86: 46184 | C86: 2026 | D86: Juni | E86: 87 | F86: 46184 | G86: AKun Baru | H86: 10877 | I86: 18141 | J86: jainal abidin | K86: Sik Asik Laundry | L86: Sik Asik Laundry | M86: 0882002491306 | O86: 46105 | P86: 46119 | Q86: 1 | R86: 1 | S86: CONTACTED | T86: DELIVERED | U86: VALID | V86: (0) Tidak Merespon
A87: =COUNTIF('Call & Chat-Lidya'!$I$4:$I$2433,I87) -> 3 | B87: 46190 | C87: 2026 | D87: Juni | E87: 88 | F87: 46184 | G87: AKun Baru | H87: 11359 | I87: 18993 | J87: Liviaaja Dede | K87: Ayu Laundry 1 | L87: Ayu Laundry 1 | M87: 081977525901 | N87: 081547468365 | O87: 46184 | P87: 46198 | Q87: 2 | R87: 1 | S87: CONNECTED | T87: DELIVERED | U87: VALID | V87: (0) Tidak Merespon
A88: =COUNTIF('Call & Chat-Lidya'!$I$4:$I$2433,I88) -> 10 | B88: 46190 | C88: 2026 | D88: Juni | E88: 89 | F88: 46184 | G88: Outlet Baru | H88: 10315 | I88: 17147 | J88: Aulia Laundry_PP | K88: Aulia Laundry | L88: Laundry Aulia II | M88: 085336166676 | N88: 085336166676 | O88: 46184 | P88: 46020 | Q88: 0 | R88: 1 | S88: CONNECTED | T88: DELIVERED | U88: VALID | V88: (0) Tidak Merespon | X88: Business | Y88: 118000
A89: =COUNTIF('Call & Chat-Lidya'!$I$4:$I$2433,I89) -> 2 | B89: 46190 | C89: 2026 | D89: Juni | E89: 90 | F89: 46184 | G89: AKun Baru | H89: 11360 | I89: 18998 | J89: Melly susanti | K89: Melly Laundry | L89: Melly Laundry | M89: 085760462638 | N89: 085760462638 | O89: 46184 | P89: 46198 | Q89: 0 | R89: 1 | S89: CONTACTED | T89: DELIVERED | U89: VALID | V89: (0) Tidak Merespon
A90: =COUNTIF('Call & Chat-Lidya'!$I$4:$I$2433,I90) -> 2 | B90: 46190 | C90: 2026 | D90: Juni | E90: 91 | F90: 46185 | G90: AKun Baru | H90: 11361 | I90: 19001 | J90: Putra Firdamansyah | K90: CEMARA LAUNDRY | L90: CEMARA LAUNDRY | M90: 082213883618 | N90: 082213883618 | O90: 46185 | P90: 46199 | Q90: 0 | R90: 0 | S90: CONNECTED | T90: ENGAGE | U90: VALID | V90: (0) Nomor Diblokir | Z90: Kenapa nelpon" terus gak sopan dan aplikasi tidak jadi digunakan
A91: =COUNTIF('Call & Chat-Lidya'!$I$4:$I$2433,I91) -> 2 | B91: 46190 | C91: 2026 | D91: Juni | E91: 92 | F91: 46186 | G91: AKun Baru | H91: 11364 | I91: 19009 | J91: septy | K91: Family Laundry | L91: Family Laundry | M91: 081584258949 | N91: 081584258949 | O91: 46186 | P91: 46200 | Q91: 0 | R91: 1 | S91: UNINTEREST | T91: DELIVERED | U91: VALID | V91: (0) Pakai Aplikasi Lain | Z91: Aplikasi piposmart tidak digunakan dan saat ini sudah menggunakan aplikasi lain dan call langsung dimatikan
A92: =COUNTIF('Call & Chat-Lidya'!$I$4:$I$2433,I92) -> 2 | B92: 46190 | C92: 2026 | D92: Juni | E92: 93 | F92: 46188 | G92: AKun Baru | H92: 11366 | I92: 19016 | J92: siti aisyah | K92: INONG LAUNDRY | L92: INONG LAUNDRY | M92: 081290050427 | N92: 081290050427 | O92: 46187 | P92: 46201 | Q92: 0 | R92: 1 | S92: ENGAGE | T92: DELIVERED | U92: VALID | V92: (0) Data Employee dan Trial | Z92: Konfirmasi penggunaan aplikasi piposmart dan call langsung dimatikan
A93: =COUNTIF('Call & Chat-Lidya'!$I$4:$I$2433,I93) -> 1 | B93: 46190 | C93: 2026 | D93: Juni | E93: 94 | F93: 46188 | G93: AKun Baru | H93: 11368 | I93: 19022 | J93: Yora | K93: Yora Loundry | L93: Yora Loundry | M93: 089504716938 | N93: 089504716938 | O93: 46188 | P93: 46202 | Q93: 0 | R93: 1 | S93: INTEREST | T93: DELIVERED | U93: VALID | V93: (0) Data Employee dan Trial | W93: Tiktok | Z93: Aplikasi piposmartnya suaminya yang instal dan registrasi akun dan memang ada rencana mau beralih ke sistem aplikasi namun masih mau menghabiskan nota manual nya dulu karna ada sisa. Usaha laundry jalan 1 bulan stengah dan penjelasan aplikasi dan sistem berlangganan. Jika ada waktu untuk training dan ada kendala akan dihubungi kembali
A94: =COUNTIF('Call & Chat-Lidya'!$I$4:$I$2433,I94) -> 1 | B94: 46190 | C94: 2026 | D94: Juni | E94: 95 | F94: 46189 | G94: AKun Baru | H94: 11371 | I94: 19029 | J94: mama dean sinta | K94: madesi laundry | L94: madesi laundry | M94: 082117314993 | N94: 082117314993 | O94: 46189 | P94: 46203 | Q94: 0 | R94: 1 | S94: INTEREST | T94: DELIVERED | U94: VALID | V94: (0) Data Employee dan Trial | Z94: Aplikasi belum digunakan karna masih menunggu anaknya yang masih kuliah. Usaha laundry jalan 2 bulan dan masih menggunakan nota manual, penjelasan aplikasi piposmart dan aplikasinya akan dicoba diskusikan dulu dengan anaknya dan jika ada kendala akan dihubungi kembai
A95: =COUNTIF('Call & Chat-Lidya'!$I$4:$I$2433,I95) -> 1 | B95: 46190 | C95: 2026 | D95: Juni | E95: 96 | F95: 46189 | G95: AKun Baru | H95: 11372 | I95: 19030 | J95: Bunda Kanefia | K95: Bunbun Laundry | L95: Bunbun Laundry | M95: 088901446926 | N95: 088901446926 | O95: 46189 | P95: 46203 | Q95: 0 | R95: 1 | S95: CONNECTED | T95: ENGAGE | U95: VALID | V95: (0) Data Employee dan Trial | Z95: Jika ada kendala dalam penggunaan piposmartnya akan dihubungi kembali
A96: =COUNTIF('Call & Chat-Lidya'!$I$4:$I$2433,I96) -> 1 | B96: 46190 | C96: 2026 | D96: Juni | E96: 97 | F96: 46190 | G96: AKun Baru | H96: 11373 | I96: 19031 | J96: karenamu jaya laundry | K96: karenamu jaya laundry | L96: karenamu jaya laundry | M96: 082144229754 | N96: 082144229754 | O96: 46189 | P96: 46203 | Q96: 0 | R96: 1 | S96: CONTACTED | T96: DELIVERED | U96: VALID | V96: (0) Tidak Merespon
A97: =COUNTIF('Call & Chat-Lidya'!$I$4:$I$2433,I97) -> 1 | B97: 46190 | C97: 2026 | D97: Juni | E97: 98 | F97: 46190 | G97: AKun Baru | H97: 11376 | I97: 19035 | J97: Novia Hutahaean | K97: Celine Laundry | L97: Celine Laundry | M97: 085276064292 | O97: 46190 | P97: 46204 | Q97: 1 | R97: 1 | S97: CONNECTED | T97: ENGAGE | U97: VALID | V97: (0) Data Employee dan Trial | Z97: Bantu penjelasan untuk penginputan jumlah item yang di cuci dalam cuci kiloan
A98: =COUNTIF('Call & Chat-Lidya'!$I$4:$I$2433,I98) -> 1 | B98: 46190 | C98: 2026 | D98: Juni | E98: 99 | F98: 46190 | G98: AKun Baru | H98: 9491 | I98: 15512 | J98: Beryan Zee | K98: Gen Z Laundry | L98: GEN Z 2 Laundry | M98: 085367135058 | N98: 082322452222 | O98: 46190 | P98: 45822 | Q98: 0 | R98: 2 | S98: INTEREST | T98: DELIVERED | U98: VALID | V98: (0) Data Employee dan Trial | W98: Playstore | Z98: Ada rencana buka outlet baru dengan sistem laundry self service, namun untuk menjalankan mesin menggunakan QRIS dan masih ditanyakan dengan perlengkapan laundry nya untuk sistem operasional mesin nya. dan jika ada kendala dan mau dibantu kembali dari sisi piposmartnya akan dihubungi kembali. Rencana pembukaan laundry 24 Juni 2026 dan saat ini masi dalam proses instalasi mesin
A99: =COUNTIF('Call & Chat-Lidya'!$I$4:$I$2433,I99) -> 1 | B99: 46190 | C99: 2026 | D99: Juni | E99: 100 | F99: 46190 | G99: Outlet Baru | H99: 9794 | I99: 16248 | J99: SHAVARA LAUNDRY | K99: SHAVARA LAUNDRY | L99: Shavara Laundry (MV) | M99: 087832009030 | N99: 087832009030 | O99: 46190 | P99: 45911 | Q99: 0 | R99: 1 | S99: CONNECTED | T99: DELIVERED | U99: VALID | V99: (0) Tidak Merespon | W99: Playstore
A100: =COUNTIF('Call & Chat-Lidya'!$I$4:$I$2433,I100) -> 10 | B100: 46177 | C100: 2026 | D100: Mei | E100: 447 | F100: 46160 | G100: AKun Baru | H100: 11219 | I100: 18745 | J100: jhoni ariyanto | K100: Fourkids laudry | L100: Fourkids laudry | M100: 089528002854 | O100: 46160 | P100: 46174 | Q100: 4 | R100: 0 | S100: UNINTEREST | T100: DELIVERED | U100: VALID | V100: (0) Data Employee dan Trial | Z100: Akun coba" dan nasabahnya sudah berlanganan dengan akun 18785 fourkids laundry paket 12 bulan basic
...

Sheet Call & Chat-Lidya
A1: PT PIPOSMART DIGITAL INDONESIA
A2: Data Kelolaan Nasabah
A3: Pengertian Scorsing = 0. (Tidak Tertarik) 1. (New Download) 2. (Potensial) 3. (Berlangganan)
A4: Total FU | B4: Tanggal FU | C4: Tahun | D4: Bulan | E4: No | F4: Tanggal Dibagikan (Data) | G4: Status Akun | H4: Kode Baris | I4: Kode Owner | J4: Nama Owner | K4: Project/Brand | L4: Outlet | M4: No. HP Owner | N4: No. HP Outlet | O4: Create Date Project | P4: Expired Date | Q4: Total Transaksi | R4: Scor | S4: Call | T4: Chat | U4: Validitas | V4: Remaks | W4: Sumber Nasabah | X4: Finalisasi (Closing) | Y4: Nominal | Z4: Noted | AA4: Audit
B5: 46098 | C5: 2026 | D5: Maret | E5: 1 | F5: 46097 | H5: 10853 | I5: 18107 | J5: rayakaundry | K5: laundry | L5: laundry | M5: 083895556893 | N5: 083895556893 | O5: 46097 | P5: 46111 | Q5: 0 | R5: 1 | S5: NO CALL | T5: DELIVERED | U5: VALID | V5: (0) Tidak Merespon
A6: =COUNTIF('Call & Chat-Lidya'!$I$4:$I$2391,I6) -> 5 | B6: 46190 | C6: 2026 | D6: Juni | E6: 17 | F6: 46175 | G6: AKun Baru | H6: 11315 | I6: 18911 | J6: sigit purnomo | K6: Laundry | L6: Mamas Laundry | M6: 081289304588 | O6: 46175 | P6: 46189 | Q6: 0 | R6: 1 | S6: CONNECTED | T6: DELIVERED | U6: VALID | V6: (0) Tidak Merespon
A7: =COUNTIF('Call & Chat-Lidya'!$I$4:$I$2391,I7) -> 3 | B7: 46190 | C7: 2026 | D7: Juni | E7: 18 | F7: 46175 | G7: AKun Baru | H7: 11316 | I7: 18912 | J7: Syariah Laundry | K7: Syariah Laundry | L7: Syariah Laundry | M7: 082181951816 | N7: 082181951816 | O7: 46175 | P7: 46189 | Q7: 0 | R7: 1 | S7: CONNECTED | T7: DELIVERED | U7: VALID | V7: (0) Data Employee dan Trial
A8: =COUNTIF('Call & Chat-Lidya'!$I$4:$I$2391,I8) -> 4 | B8: 46190 | C8: 2026 | D8: Juni | E8: 19 | F8: 46175 | G8: AKun Baru | H8: 11317 | I8: 18913 | J8: Elfira Yanti | K8: buk Yanti laundry | L8: buk Yanti laundry | M8: 082280298103 | N8: 082280298103 | O8: 46175 | P8: 46189 | Q8: 1 | R8: 1 | S8: CONNECTED | T8: UNINTEREST | U8: VALID | V8: (0) Data Employee dan Trial | Z8: Aplikasi piposmartnya tidak digunakan
A9: =COUNTIF('Call & Chat-Lidya'!$I$4:$I$2391,I9) -> 4 | B9: 46190 | C9: 2026 | D9: Juni | E9: 20 | F9: 46175 | G9: AKun Baru | H9: 11318 | I9: 18916 | J9: Yanti Fitria Sari | K9: JA londry | L9: JA londry | M9: 085283284078 | N9: 85283284078 | O9: 46175 | P9: 46189 | Q9: 0 | R9: 0 | S9: CONTACTED | T9: SENT | U9: INVALID | V9: (0) Nomor Diblokir
A10: =COUNTIF('Call & Chat-Lidya'!$I$4:$I$2391,I10) -> 8 | B10: 46190 | C10: 2026 | D10: Juni | E10: 52 | F10: 46178 | G10: AKun Baru | H10: 11324 | I10: 18926 | J10: Tawakkal | K10: New Malomo Laundry | L10: New Malomo Laundry 01 | M10: 082333222543 | N10: 082333222543 | O10: 46177 | P10: 46191 | Q10: 6 | R10: 2 | S10: CONNECTED | T10: DELIVERED | U10: VALID | V10: (2) Trial, Demo, Interaktif | W10: Playstore
A11: =COUNTIF('Call & Chat-Lidya'!$I$4:$I$2391,I11) -> 2 | B11: 46190 | C11: 2026 | D11: Juni | E11: 53 | F11: 46178 | G11: AKun Baru | H11: 11326 | I11: 18930 | J11: rayyan | K11: rayyan laundry | L11: rayyan laundry | M11: 0895329286867 | N11: 082375740626 | O11: 46177 | P11: 46191 | Q11: 0 | R11: 1 | S11: ENGAGE | T11: DELIVERED | U11: VALID | V11: (0) Data Employee dan Trial | Z11: Konfirmasi penggunaan aplikasi piposmart dan call langsung dimatikan
A12: hv | B12: 46190 | C12: 2026 | D12: Juni | E12: 54 | F12: 46178 | G12: AKun Baru | H12: 11327 | I12: 18931 | J12: Dian Maulidini | K12: Yusuf Laundry | L12: Yusuf Laundry | M12: 081398606092 | N12: 081398606092 | O12: 46177 | P12: 46191 | Q12: 7 | R12: 2 | S12: INTEREST | T12: DELIVERED | U12: VALID | V12: (0) Data Karyawan dan Trial | W12: Facebook | Z12: Usaha laundry jalan 4 tahun dan masih menggunakan nota manual dan penjelasan sistem berlangganan dan paket promo berlangganan. Untuk berlangganan akan di diskusikan dulu dengan suaminya. Aplikasi tidak ada kendala dan mudah digunakan dan rencana penggunaan dia wal bulan juli dan reminder berlangganan tanggal 29 Juni
A13: =COUNTIF('Call & Chat-Lidya'!$I$4:$I$2391,I13) -> 8 | B13: 46190 | C13: 2026 | D13: Juni | E13: 52 | F13: 46178 | G13: AKun Baru | H13: 11324 | I13: 18926 | J13: Tawakkal | K13: New Malomo Laundry | L13: New Malomo Laundry | M13: 082333222543 | N13: 082333222543 | O13: 46177 | P13: 46191 | Q13: 6 | R13: 2 | S13: CONNECTED | T13: DELIVERED | U13: VALID | V13: (2) Trial, Demo, Interaktif | W13: Playstore
A14: =COUNTIF('Call & Chat-Lidya'!$I$4:$I$2391,I14) -> 4 | B14: 46190 | C14: 2026 | D14: Juni | E14: 56 | F14: 46178 | G14: AKun Baru | H14: 11331 | I14: 18938 | J14: Assalam Laundry | K14: Assalam Laundry | L14: Assalam Laundry | M14: 085602291180 | N14: 085602291180 | O14: 46178 | P14: 46192 | Q14: 0 | R14: 1 | S14: ENGAGE | T14: DELIVERED | U14: VALID | V14: (0) Data Employee dan Trial | Z14: Konfirmasi penggunaan aplikasi piposmart dan call langsung dimatikan
A15: =COUNTIF('Call & Chat-Lidya'!$I$4:$I$2391,I15) -> 4 | B15: 46190 | C15: 2026 | D15: Juni | E15: 58 | F15: 46179 | G15: AKun Baru | H15: 11334 | I15: 18946 | J15: moxie wash | K15: moxiewash | L15: moxiewash | M15: 0811868493 | N15: 08139999235 | O15: 46179 | P15: 46193 | Q15: 0 | R15: 0 | S15: NO CALL | T15: UNINTEREST | U15: VALID | V15: (0) Data Employee dan Trial | Z15: Aplikasi tidak digunakan dan tidak ada kendala karna kemarin hanya coba". Jika perlu nasabahnya yang akan menghubungi kembali
A16: =COUNTIF('Call & Chat-Lidya'!$I$4:$I$2391,I16) -> 4 | B16: 46190 | C16: 2026 | D16: Juni | E16: 60 | F16: 46181 | G16: Outlet Baru | H16: 15536 | I16: 15510 | J16: Amanda | K16: cuciqu laundry | L16: CICERI DROP POINT | M16: 087798951222 | N16: 087798951222 | O16: 46181 | P16: 45822 | Q16: 0 | R16: 2 | S16: NO CALL | T16: DELIVERED | U16: VALID | V16: (2) Trial, Demo, Interaktif | W16: Playstore
A17: =COUNTIF('Call & Chat-Lidya'!$I$4:$I$2391,I17) -> 6 | B17: 46190 | C17: 2026 | D17: Juni | E17: 61 | F17: 46181 | G17: AKun Baru | H17: 11338 | I17: 18954 | J17: Dewi Anggraini | K17: We Laundry | L17: We Laundry | M17: 08161896392 | N17: 08161896392 | O17: 46181 | P17: 46195 | Q17: 3 | R17: 2 | S17: CONNECTED | T17: INTEREST | U17: VALID | V17: (2) Trial, Demo, Interaktif | W17: Playstore
A18: =COUNTIF('Call & Chat-Lidya'!$I$4:$I$2391,I18) -> 4 | B18: 46190 | C18: 2026 | D18: Juni | E18: 62 | F18: 46181 | G18: AKun Baru | H18: 11342 | I18: 18963 | J18: Cyclops Laundry | K18: Cyclops Laundry | L18: Cyclops Laundry | M18: 08218812277 | N18: 08218812277 | O18: 46181 | P18: 46195 | Q18: 2 | R18: 1 | S18: ENGAGE | T18: DELIVERED | U18: VALID | V18: (0) Data Employee dan Trial | Z18: Konfirmasi penggunaan aplikasi piposmart dan call langsung dimatikan
A19: =COUNTIF('Call & Chat-Lidya'!$I$4:$I$2391,I19) -> 4 | B19: 46190 | C19: 2026 | D19: Juni | E19: 63 | F19: 46181 | G19: Referral Mitra | H19: 11343 | I19: 18964 | J19: BRI Link Vania Loundry | K19: Vannessa Laundry | L19: Vannessa Laundry | M19: 085715609873 | N19: 085715609873 | O19: 46181 | P19: 46195 | Q19: 0 | R19: 2 | S19: CONNECTED | T19: DELIVERED | U19: VALID | V19: (2) Trial, Demo, Interaktif | W19: Mitra
A20: =COUNTIF('Call & Chat-Lidya'!$I$4:$I$2391,I20) -> 5 | B20: 46190 | C20: 2026 | D20: Juni | E20: 64 | F20: 46181 | G20: AKun Baru | H20: 11344 | I20: 18965 | J20: Hertati Simanjuntak | K20: miss resik laundry | L20: miss resik laundry | M20: 081280167784 | N20: 085813991103 | O20: 46181 | P20: 46195 | Q20: 1 | R20: 2 | S20: NO CALL | T20: DELIVERED | U20: VALID | V20: (2) Trial, Demo, Interaktif | W20: Mitra
A21: =COUNTIF('Call & Chat-Lidya'!$I$4:$I$2391,I21) -> 2 | B21: 46190 | C21: 2026 | D21: Juni | E21: 71 | F21: 46182 | G21: AKun Baru | H21: 11100 | I21: 18540 | J21: Hanin Laundry | K21: Hanin laundry | L21: Hanin laundry | M21: 081370907324 | N21: 085212096130 | O21: 46142 | P21: 46156 | Q21: 0 | R21: 2 | S21: PROSPECT | T21: DELIVERED | U21: VALID | V21: (2) Trial, Demo, Interaktif | Z21: Penjelasan biaya berlangganan dan rencana berlangganan 12 plus 6 bulan Pro, Reminder berlangganan besok tanggal 18 Juni 2026
A22: =COUNTIF('Call & Chat-Lidya'!$I$4:$I$2391,I22) -> 3 | B22: 46190 | C22: 2026 | D22: Juni | E22: 73 | F22: 46182 | G22: AKun Baru | H22: 11350 | I22: 18975 | J22: Wawan Hermawan | K22: emaluna laundry | L22: emaluna laundry | M22: 082147293334 | N22: 082147293334 | O22: 46182 | P22: 46196 | Q22: 0 | R22: 1 | S22: NO CALL | T22: DELIVERED | U22: VALID | V22: (0) Data Employee dan Trial | Z22: Nasabah sudah instal kembali dan daftar akun yang baru
A23: =COUNTIF('Call & Chat-Lidya'!$I$4:$I$2391,I23) -> 2 | B23: 46190 | C23: 2026 | D23: Juni | E23: 74 | F23: 46183 | G23: AKun Baru | H23: 11354 | I23: 18981 | J23: Rosmawatihadiarjo77 | K23: Alfian Laundry | L23: Alfian Laundry | M23: 088294365107 | N23: 088294365107 | O23: 46183 | P23: 46197 | Q23: 0 | R23: 1 | S23: CONTACTED | T23: DELIVERED | U23: VALID | V23: (0) Tidak Merespon
A24: =COUNTIF('Call & Chat-Lidya'!$I$4:$I$2391,I24) -> 3 | B24: 46190 | C24: 2026 | D24: Juni | E24: 75 | F24: 46184 | G24: Outlet Baru | H24: 8303 | I24: 12986 | J24: KEVIN SEVEN's | K24: SEVEN's LAUNDRY | L24: SEVEN's LAUNDRY 2 | M24: 085724591167 | N24: 085724591167 | O24: 46184 | P24: 45525 | Q24: 0 | R24: 1 | S24: CONNECTED | T24: DELIVERED | U24: VALID | V24: (0) Tidak Merespon | W24: Playstore
A25: =COUNTIF('Call & Chat-Lidya'!$I$4:$I$2391,I25) -> 3 | B25: 46190 | C25: 2026 | D25: Juni | E25: 88 | F25: 46184 | G25: AKun Baru | H25: 11359 | I25: 18993 | J25: Liviaaja Dede | K25: Ayu Laundry 1 | L25: Ayu Laundry 1 | M25: 081977525901 | N25: 081547468365 | O25: 46184 | P25: 46198 | Q25: 2 | R25: 1 | S25: CONNECTED | T25: DELIVERED | U25: VALID | V25: (0) Tidak Merespon
A26: =COUNTIF('Call & Chat-Lidya'!$I$4:$I$2391,I26) -> 10 | B26: 46190 | C26: 2026 | D26: Juni | E26: 89 | F26: 46184 | G26: Outlet Baru | H26: 10315 | I26: 17147 | J26: Aulia Laundry_PP | K26: Aulia Laundry | L26: Laundry Aulia II | M26: 085336166676 | N26: 085336166676 | O26: 46184 | P26: 46020 | Q26: 0 | R26: 1 | S26: CONNECTED | T26: DELIVERED | U26: VALID | V26: (0) Tidak Merespon | X26: Business | Y26: 118000
A27: =COUNTIF('Call & Chat-Lidya'!$I$4:$I$2391,I27) -> 2 | B27: 46190 | C27: 2026 | D27: Juni | E27: 90 | F27: 46184 | G27: AKun Baru | H27: 11360 | I27: 18998 | J27: Melly susanti | K27: Melly Laundry | L27: Melly Laundry | M27: 085760462638 | N27: 085760462638 | O27: 46184 | P27: 46198 | Q27: 0 | R27: 1 | S27: CONTACTED | T27: DELIVERED | U27: VALID | V27: (0) Tidak Merespon
A28: =COUNTIF('Call & Chat-Lidya'!$I$4:$I$2391,I28) -> 2 | B28: 46190 | C28: 2026 | D28: Juni | E28: 91 | F28: 46185 | G28: AKun Baru | H28: 11361 | I28: 19001 | J28: Putra Firdamansyah | K28: CEMARA LAUNDRY | L28: CEMARA LAUNDRY | M28: 082213883618 | N28: 082213883618 | O28: 46185 | P28: 46199 | Q28: 0 | R28: 0 | S28: CONNECTED | T28: ENGAGE | U28: VALID | V28: (0) Nomor Diblokir | Z28: Kenapa nelpon" terus gak sopan dan aplikasi tidak jadi digunakan
A29: =COUNTIF('Call & Chat-Lidya'!$I$4:$I$2391,I29) -> 2 | B29: 46190 | C29: 2026 | D29: Juni | E29: 92 | F29: 46186 | G29: AKun Baru | H29: 11364 | I29: 19009 | J29: septy | K29: Family Laundry | L29: Family Laundry | M29: 081584258949 | N29: 081584258949 | O29: 46186 | P29: 46200 | Q29: 0 | R29: 1 | S29: UNINTEREST | T29: DELIVERED | U29: VALID | V29: (0) Pakai Aplikasi Lain | Z29: Aplikasi piposmart tidak digunakan dan saat ini sudah menggunakan aplikasi lain dan call langsung dimatikan
A30: =COUNTIF('Call & Chat-Lidya'!$I$4:$I$2391,I30) -> 2 | B30: 46190 | C30: 2026 | D30: Juni | E30: 93 | F30: 46188 | G30: AKun Baru | H30: 11366 | I30: 19016 | J30: siti aisyah | K30: INONG LAUNDRY | L30: INONG LAUNDRY | M30: 081290050427 | N30: 081290050427 | O30: 46187 | P30: 46201 | Q30: 0 | R30: 1 | S30: ENGAGE | T30: DELIVERED | U30: VALID | V30: (0) Data Employee dan Trial | Z30: Konfirmasi penggunaan aplikasi piposmart dan call langsung dimatikan
A31: =COUNTIF('Call & Chat-Lidya'!$I$4:$I$2391,I31) -> 1 | B31: 46190 | C31: 2026 | D31: Juni | E31: 94 | F31: 46188 | G31: AKun Baru | H31: 11368 | I31: 19022 | J31: Yora | K31: Yora Loundry | L31: Yora Loundry | M31: 089504716938 | N31: 089504716938 | O31: 46188 | P31: 46202 | Q31: 0 | R31: 1 | S31: INTEREST | T31: DELIVERED | U31: VALID | V31: (0) Data Employee dan Trial | W31: Tiktok | Z31: Aplikasi piposmartnya suaminya yang instal dan registrasi akun dan memang ada rencana mau beralih ke sistem aplikasi namun masih mau menghabiskan nota manual nya dulu karna ada sisa. Usaha laundry jalan 1 bulan stengah dan penjelasan aplikasi dan sistem berlangganan. Jika ada waktu untuk training dan ada kendala akan dihubungi kembali
A32: =COUNTIF('Call & Chat-Lidya'!$I$4:$I$2391,I32) -> 1 | B32: 46190 | C32: 2026 | D32: Juni | E32: 95 | F32: 46189 | G32: AKun Baru | H32: 11371 | I32: 19029 | J32: mama dean sinta | K32: madesi laundry | L32: madesi laundry | M32: 082117314993 | N32: 082117314993 | O32: 46189 | P32: 46203 | Q32: 0 | R32: 1 | S32: INTEREST | T32: DELIVERED | U32: VALID | V32: (0) Data Employee dan Trial | Z32: Aplikasi belum digunakan karna masih menunggu anaknya yang masih kuliah. Usaha laundry jalan 2 bulan dan masih menggunakan nota manual, penjelasan aplikasi piposmart dan aplikasinya akan dicoba diskusikan dulu dengan anaknya dan jika ada kendala akan dihubungi kembai
A33: =COUNTIF('Call & Chat-Lidya'!$I$4:$I$2391,I33) -> 1 | B33: 46190 | C33: 2026 | D33: Juni | E33: 96 | F33: 46189 | G33: AKun Baru | H33: 11372 | I33: 19030 | J33: Bunda Kanefia | K33: Bunbun Laundry | L33: Bunbun Laundry | M33: 088901446926 | N33: 088901446926 | O33: 46189 | P33: 46203 | Q33: 0 | R33: 1 | S33: CONNECTED | T33: ENGAGE | U33: VALID | V33: (0) Data Employee dan Trial | Z33: Jika ada kendala dalam penggunaan piposmartnya akan dihubungi kembali
A34: =COUNTIF('Call & Chat-Lidya'!$I$4:$I$2391,I34) -> 1 | B34: 46190 | C34: 2026 | D34: Juni | E34: 97 | F34: 46190 | G34: AKun Baru | H34: 11373 | I34: 19031 | J34: karenamu jaya laundry | K34: karenamu jaya laundry | L34: karenamu jaya laundry | M34: 082144229754 | N34: 082144229754 | O34: 46189 | P34: 46203 | Q34: 0 | R34: 1 | S34: CONTACTED | T34: DELIVERED | U34: VALID | V34: (0) Tidak Merespon
A35: =COUNTIF('Call & Chat-Lidya'!$I$4:$I$2391,I35) -> 1 | B35: 46190 | C35: 2026 | D35: Juni | E35: 98 | F35: 46190 | G35: AKun Baru | H35: 11376 | I35: 19035 | J35: Novia Hutahaean | K35: Celine Laundry | L35: Celine Laundry | M35: 085276064292 | O35: 46190 | P35: 46204 | Q35: 1 | R35: 1 | S35: CONNECTED | T35: ENGAGE | U35: VALID | V35: (0) Data Employee dan Trial | Z35: Bantu penjelasan untuk penginputan jumlah item yang di cuci dalam cuci kiloan
A36: =COUNTIF('Call & Chat-Lidya'!$I$4:$I$2391,I36) -> 1 | B36: 46190 | C36: 2026 | D36: Juni | E36: 99 | F36: 46190 | G36: AKun Baru | H36: 9491 | I36: 15512 | J36: Beryan Zee | K36: Gen Z Laundry | L36: GEN Z 2 Laundry | M36: 085367135058 | N36: 082322452222 | O36: 46190 | P36: 45822 | Q36: 0 | R36: 2 | S36: INTEREST | T36: DELIVERED | U36: VALID | V36: (0) Data Employee dan Trial | W36: Playstore | Z36: Ada rencana buka outlet baru dengan sistem laundry self service, namun untuk menjalankan mesin menggunakan QRIS dan masih ditanyakan dengan perlengkapan laundry nya untuk sistem operasional mesin nya. dan jika ada kendala dan mau dibantu kembali dari sisi piposmartnya akan dihubungi kembali. Rencana pembukaan laundry 24 Juni 2026 dan saat ini masi dalam proses instalasi mesin
A37: =COUNTIF('Call & Chat-Lidya'!$I$4:$I$2391,I37) -> 1 | B37: 46190 | C37: 2026 | D37: Juni | E37: 100 | F37: 46190 | G37: Outlet Baru | H37: 9794 | I37: 16248 | J37: SHAVARA LAUNDRY | K37: SHAVARA LAUNDRY | L37: Shavara Laundry (MV) | M37: 087832009030 | N37: 087832009030 | O37: 46190 | P37: 45911 | Q37: 0 | R37: 1 | S37: CONNECTED | T37: DELIVERED | U37: VALID | V37: (0) Tidak Merespon | W37: Playstore
A38: =COUNTIF('Call & Chat-Lidya'!$I$4:$I$2391,I38) -> 13 | B38: 46190 | C38: 2026 | D38: Mei | E38: 339 | F38: 46134 | G38: AKun Baru | H38: 11027 | I38: 18420 | J38: Villy | K38: Resik Laundry | L38: Resik Laundry | M38: 085163036060 | N38: 085163036060 | O38: 46132 | P38: 46146 | Q38: 3 | R38: 2 | S38: CONNECTED | T38: DELIVERED | U38: VALID | V38: (2) Trial, Demo, Interaktif
A39: =COUNTIF('Call & Chat-Lidya'!$I$4:$I$2391,I39) -> 4 | B39: 46190 | C39: 2026 | D39: Juni | E39: 2 | F39: 46174 | G39: AKun Baru | H39: 11307 | I39: 18899 | J39: Renita Setianingsih | K39: Golden Laundry | L39: Golden Laundry | M39: 087829560267 | N39: 085725651447 | O39: 46174 | P39: 46188 | Q39: 0 | R39: 1 | S39: CONNECTED | T39: DELIVERED | U39: VALID | V39: (0) Tidak Merespon
A40: =COUNTIF('Call & Chat-Lidya'!$I$4:$I$2391,I40) -> 4 | B40: 46190 | C40: 2026 | D40: Juni | E40: 3 | F40: 46175 | G40: AKun Baru | H40: 11310 | I40: 18904 | J40: Nadiva Laundry | K40: Nadiva Laundry | L40: Nadiva Laundry | M40: 085608982002 | N40: 085608982002 | O40: 46174 | P40: 46188 | Q40: 0 | R40: 1 | S40: CONNECTED | T40: DELIVERED | U40: VALID | V40: (0) Tidak Merespon
A41: =COUNTIF('Call & Chat-Lidya'!$I$4:$I$2391,I41) -> 4 | B41: 46190 | C41: 2026 | D41: Juni | E41: 4 | F41: 46175 | G41: AKun Baru | H41: 11311 | I41: 18905 | J41: Indri Rafa | K41: Hana stasya laundry | L41: Hana stasya laundry | M41: 6289602895782 | N41: 089602895782 | O41: 46174 | P41: 46188 | Q41: 0 | R41: 1 | S41: CONNECTED | T41: DELIVERED | U41: VALID | V41: (0) Tidak Merespon
A42: =COUNTIF('Call & Chat-Lidya'!$I$4:$I$2391,I42) -> 4 | B42: 46190 | C42: 2026 | D42: Juni | E42: 5 | F42: 46175 | G42: AKun Baru | H42: 11312 | I42: 18906 | J42: sarni andri | K42: Derisa laundry | L42: Derisa laundry | M42: 0895378172793 | N42: 0895378172793 | O42: 46175 | P42: 46189 | Q42: 0 | R42: 1 | S42: CONTACTED | T42: DELIVERED | U42: VALID | V42: (0) Data Employee dan Trial
A43: =COUNTIF('Call & Chat-Lidya'!$I$4:$I$2391,I43) -> 3 | B43: 46190 | C43: 2026 | D43: Mei | E43: 446 | F43: 46173 | G43: AKun Baru | H43: 11301 | I43: 18890 | J43: yuliyanti | K43: Rizky laundry | L43: Rizky laundry | M43: 083820359958 | N43: 083820359958 | O43: 46173 | P43: 46187 | Q43: 0 | R43: 2 | S43: INTEREST | T43: ENGAGE | U43: VALID | V43: (2) Trial, Demo, Interaktif | Z43: Usaha laundry buka besok tanggal 18 Juni, bantu penyambungan printer ke aplikasi dan printernya masih terkendala tidak bisa ngeprint. Merk printer Putian Pos. Bnatu training cara penggunaan aplikasi piposmart
A44: =COUNTIF('Call & Chat-Lidya'!$I$4:$I$2391,I44) -> 5 | B44: 46188 | C44: 2026 | D44: Juni | E44: 6 | F44: 46175 | G44: AKun Baru | H44: 11313 | I44: 18907 | J44: Bubble's~2 | K44: Bubble 2 | L44: Bubble 2 | M44: 085240267611 | O44: 46175 | P44: 46189 | Q44: 4 | R44: 2 | S44: NO CALL | T44: ENGAGE | U44: VALID | V44: (0) Data Employee dan Trial | Z44: Sejauh ini aplikasi aman dan tidak ada kendala dan masih trial
A45: =COUNTIF('Call & Chat-Lidya'!$I$4:$I$2391,I45) -> 4 | B45: 46188 | C45: 2026 | D45: Juni | E45: 35 | F45: 46176 | G45: AKun Baru | H45: 11320 | I45: 18919 | J45: Risnul Syafrizal | K45: Skuyy Laundry | L45: Skuyy Laundry | M45: 082170927742 | N45: 5169170881 | O45: 46176 | P45: 46190 | Q45: 110 | R45: 2 | S45: PROSPECT | T45: DELIVERED | U45: VALID | V45: (2) Trial, Demo, Interaktif | W45: Playstore | Z45: Sejauh ini aplikasi piposmartnya belum ada kendala dan rencana berlangganan hari dengan paket 1 bulan bisnis dan akan dihubungi kembali
A46: =COUNTIF('Call & Chat-Lidya'!$I$4:$I$2391,I46) -> 8 | B46: 46188 | C46: 2026 | D46: Juni | E46: 52 | F46: 46178 | G46: AKun Baru | H46: 11324 | I46: 18926 | J46: Tawakkal | K46: New Malomo Laundry | L46: New Malomo Laundry 01 | M46: 082333222543 | N46: 082333222543 | O46: 46177 | P46: 46191 | Q46: 6 | R46: 2 | S46: PROSPECT | T46: DELIVERED | U46: VALID | V46: (2) Trial, Demo, Interaktif | W46: Playstore | Z46: Call diangkat dan konfirmasi kembali mengenai penggunaan aplikasi dan call langsung dimatikan
A47: =COUNTIF('Call & Chat-Lidya'!$I$4:$I$2391,I47) -> 3 | B47: 46188 | C47: 2026 | D47: Juni | E47: 54 | F47: 46178 | G47: AKun Baru | H47: 11327 | I47: 18931 | J47: Dian Maulidini | K47: Yusuf Laundry | L47: Yusuf Laundry | M47: 081398606092 | N47: 081398606092 | O47: 46177 | P47: 46191 | Q47: 7 | R47: 1 | S47: CONNECTED | T47: DELIVERED | U47: VALID | V47: (0) Tidak Merespon
A48: =COUNTIF('Call & Chat-Lidya'!$I$4:$I$2391,I48) -> 8 | B48: 46188 | C48: 2026 | D48: Juni | E48: 52 | F48: 46178 | G48: AKun Baru | H48: 11324 | I48: 18926 | J48: Tawakkal | K48: New Malomo Laundry | L48: New Malomo Laundry | M48: 082333222543 | N48: 082333222543 | O48: 46177 | P48: 46191 | Q48: 5 | R48: 2 | S48: PROSPECT | T48: DELIVERED | U48: VALID | V48: (2) Trial, Demo, Interaktif | W48: Playstore | Z48: Call diangkat dan konfirmasi kembali mengenai penggunaan aplikasi dan call langsung dimatikan
A49: =COUNTIF('Call & Chat-Lidya'!$I$4:$I$2391,I49) -> 4 | B49: 46188 | C49: 2026 | D49: Juni | E49: 56 | F49: 46178 | G49: AKun Baru | H49: 11331 | I49: 18938 | J49: Assalam Laundry | K49: Assalam Laundry | L49: Assalam Laundry | M49: 085602291180 | N49: 085602291180 | O49: 46178 | P49: 46192 | Q49: 0 | R49: 1 | S49: ENGAGE | T49: DELIVERED | U49: VALID | V49: (0) Data Employee dan Trial | Z49: Aplikasi piposmartnya belum digunakan
A50: =COUNTIF('Call & Chat-Lidya'!$I$4:$I$2391,I50) -> 4 | B50: 46188 | C50: 2026 | D50: Juni | E50: 58 | F50: 46179 | G50: AKun Baru | H50: 11334 | I50: 18946 | J50: moxie wash | K50: moxiewash | L50: moxiewash | M50: 0811868493 | N50: 08139999235 | O50: 46179 | P50: 46193 | Q50: 0 | R50: 1 | S50: CONNECTED | T50: UNINTEREST | U50: VALID | V50: (0) Data Employee dan Trial | Z50: Aplikasi tidak digunakan dan tidak ada kendala karna kemarin hanya coba". Jika perlu nasabahnya yang akan menghubungi kembali
A51: =COUNTIF('Call & Chat-Lidya'!$I$4:$I$2391,I51) -> 3 | B51: 46188 | C51: 2026 | D51: Juni | E51: 59 | F51: 46180 | G51: AKun Baru | H51: 11336 | I51: 18952 | J51: Rizky Lia | K51: LaundryPedia | L51: LaundryPedia | M51: 0811198327 | N51: 0811198327 | O51: 46180 | P51: 46194 | Q51: 0 | R51: 0 | S51: PROSPECT | T51: ENGAGE | U51: VALID | V51: (0) Data Employee dan Trial | Z51: Rencana training hari ini namun di undur jadi besok pagi karna nasabahnya sedang padat jadwal di hari ini
A52: =COUNTIF('Call & Chat-Lidya'!$I$4:$I$2391,I52) -> 4 | B52: 46188 | C52: 2026 | D52: Juni | E52: 60 | F52: 46181 | G52: Outlet Baru | H52: 15536 | I52: 15510 | J52: Amanda | K52: cuciqu laundry | L52: CICERI DROP POINT | M52: 087798951222 | N52: 087798951222 | O52: 46181 | P52: 45822 | Q52: 0 | R52: 2 | S52: NO CALL | T52: DELIVERED | U52: VALID | V52: (2) Trial, Demo, Interaktif | W52: Playstore
A53: =COUNTIF('Call & Chat-Lidya'!$I$4:$I$2391,I53) -> 6 | B53: 46188 | C53: 2026 | D53: Juni | E53: 61 | F53: 46181 | G53: AKun Baru | H53: 11338 | I53: 18954 | J53: Dewi Anggraini | K53: We Laundry | L53: We Laundry | M53: 08161896392 | N53: 08161896392 | O53: 46181 | P53: 46195 | Q53: 3 | R53: 2 | S53: CONNECTED | T53: INTEREST | U53: VALID | V53: (2) Trial, Demo, Interaktif | W53: Playstore | Z53: Reminder kembali mengenai penggunaan dan penginputan syarat dan ketentuan dan juga list harga layanan. Untuk aplikasi belum bisa digunakan karna karyawannya beum paham dan sudah konfirmasi ke owner untuk kirim kontak karyawannya supaya Lidya bantu kembali cara penggunaan piposmartnya. hari ini ibunya lagi sibuk ada meeting dan nanti akan di kabari kembali
A54: =COUNTIF('Call & Chat-Lidya'!$I$4:$I$2391,I54) -> 4 | B54: 46188 | C54: 2026 | D54: Juni | E54: 63 | F54: 46181 | G54: Referral Mitra | H54: 11343 | I54: 18964 | J54: BRI Link Vania Loundry | K54: Vannessa Laundry | L54: Vannessa Laundry | M54: 085715609873 | N54: 085715609873 | O54: 46181 | P54: 46195 | Q54: 0 | R54: 2 | S54: CONNECTED | T54: DELIVERED | U54: VALID | V54: (2) Trial, Demo, Interaktif | W54: Mitra
A55: =COUNTIF('Call & Chat-Lidya'!$I$4:$I$2391,I55) -> 5 | B55: 46188 | C55: 2026 | D55: Juni | E55: 64 | F55: 46181 | G55: AKun Baru | H55: 11344 | I55: 18965 | J55: Hertati Simanjuntak | K55: miss resik laundry | L55: miss resik laundry | M55: 081280167784 | N55: 085813991103 | O55: 46181 | P55: 46195 | Q55: 1 | R55: 2 | S55: CONNECTED | T55: INTEREST | U55: VALID | V55: (2) Trial, Demo, Interaktif | W55: Mitra | Z55: Reminder kembali mengenai penggunaan aplikasi piposmart dan untuk berlangganan nya nanti dikabari kembali
A56: =COUNTIF('Call & Chat-Lidya'!$I$4:$I$2391,I56) -> 4 | B56: 46188 | C56: 2026 | D56: Juni | E56: 65 | F56: 46181 | G56: AKun Baru | H56: 11345 | I56: 18966 | J56: We Laundry | K56: We Laundry | L56: We Laundry | M56: 081292773006 | N56: 081292773006 | O56: 46181 | P56: 46195 | Q56: 0 | R56: 0 | S56: PROSPECT | T56: DELIVERED | U56: VALID | V56: (0) Data Karyawan dan Trial | Z56: Reminder kembali mengenai penyambungan printer thermal ke aplikasi, dan pagi ini ibunya belum ke laundry dan kemungkinan sore ke laundry dan jika sudah di laundry akan di hubungi kembali
A57: =COUNTIF('Call & Chat-Lidya'!$I$4:$I$2391,I57) -> 3 | B57: 46188 | C57: 2026 | D57: Juni | E57: 75 | F57: 46184 | G57: Outlet Baru | H57: 8303 | I57: 12986 | J57: KEVIN SEVEN's | K57: SEVEN's LAUNDRY | L57: SEVEN's LAUNDRY 2 | M57: 085724591167 | N57: 085724591167 | O57: 46184 | P57: 45525 | Q57: 0 | R57: 1 | S57: CONNECTED | T57: DELIVERED | U57: VALID | V57: (0) Tidak Merespon | W57: Playstore
A58: =COUNTIF('Call & Chat-Lidya'!$I$4:$I$2391,I58) -> 3 | B58: 46188 | C58: 2026 | D58: Juni | E58: 88 | F58: 46184 | G58: AKun Baru | H58: 11359 | I58: 18993 | J58: Liviaaja Dede | K58: Ayu Laundry 1 | L58: Ayu Laundry 1 | M58: 081977525901 | N58: 081547468365 | O58: 46184 | P58: 46198 | Q58: 2 | R58: 1 | S58: CONNECTED | T58: DELIVERED | U58: VALID | V58: (0) Tidak Merespon
A59: =COUNTIF('Call & Chat-Lidya'!$I$4:$I$2391,I59) -> 2 | B59: 46188 | C59: 2026 | D59: Juni | E59: 91 | F59: 46185 | G59: AKun Baru | H59: 11361 | I59: 19001 | J59: Putra Firdamansyah | K59: CEMARA LAUNDRY | L59: CEMARA LAUNDRY | M59: 082213883618 | N59: 082213883618 | O59: 46185 | P59: 46199 | Q59: 0 | R59: 1 | S59: CONNECTED | T59: DELIVERED | U59: VALID | V59: (0) Tidak Merespon
A60: =COUNTIF('Call & Chat-Lidya'!$I$4:$I$2391,I60) -> 2 | B60: 46188 | C60: 2026 | D60: Juni | E60: 92 | F60: 46186 | G60: AKun Baru | H60: 11364 | I60: 19009 | J60: septy | K60: Family Laundry | L60: Family Laundry | M60: 081584258949 | N60: 081584258949 | O60: 46186 | P60: 46200 | Q60: 0 | R60: 1 | S60: CONTACTED | T60: DELIVERED | U60: VALID | V60: (0) Tidak Merespon
A61: =COUNTIF('Call & Chat-Lidya'!$I$4:$I$2391,I61) -> 2 | B61: 46188 | C61: 2026 | D61: Juni | E61: 93 | F61: 46188 | G61: AKun Baru | H61: 11366 | I61: 19016 | J61: siti aisyah | K61: INONG LAUNDRY | L61: INONG LAUNDRY | M61: 081290050427 | N61: 081290050427 | O61: 46187 | P61: 46201 | Q61: 0 | R61: 1 | S61: CONNECTED | T61: ENGAGE | U61: VALID | V61: (0) Data Employee dan Trial | Z61: Sejauh ini aplikasi piposmartnya belum ada kendala dan masih aman
A62: =COUNTIF('Call & Chat-Lidya'!$I$4:$I$2391,I62) -> 6 | B62: 46188 | C62: 2026 | D62: Mei | E62: 450 | F62: 46161 | G62: AKun Baru | H62: 11225 | I62: 18753 | J62: aceng ulumuddin | K62: Vara Laundry | L62: Vara Laundry | M62: 08122314544 | N62: 08122314544 | O62: 46161 | P62: 46175 | Q62: 5 | R62: 3 | S62: CONNECTED | T62: INTEREST | U62: VALID | V62: (3) Berlangganan | X62: Pro | Y62: 1688000 | Z62: Penjelasan mengenai laporan excel dan rekapan kinerja karyawan
A63: =COUNTIF('Call & Chat-Lidya'!$I$4:$I$2391,I63) -> 16 | B63: 46188 | C63: 2026 | D63: Mei | E63: 11 | F63: 46146 | G63: AKun Baru | H63: 11124 | I63: 18580 | J63: Osman Kadir | K63: BAMASS LAUNDRY | L63: BAMASS LAUNDRY | M63: 085251519797 | N63: 085251519797 | O63: 46146 | P63: 46160 | Q63: 0 | R63: 2 | S63: CONNECTED | T63: DELIVERED | U63: VALID | V63: (2) Trial, Demo, Interaktif | W63: Mitra | X63: Pro | Y63: 168.000
A64: =COUNTIF('Call & Chat-Lidya'!$I$4:$I$2391,I64) -> 13 | B64: 46188 | C64: 2026 | D64: Mei | E64: 38 | F64: 46148 | G64: AKun Baru | H64: 11137 | I64: 18604 | J64: Rizky Lia Febianty | K64: Laundrypedia | L64: Laundrypedia | M64: 081334611597 | N64: 081334611597 | O64: 05/05/26 | P64: 46161 | Q64: 0 | R64: 3 | S64: NO CALL | T64: DELIVERED | U64: VALID | V64: (3) Berlangganan | X64: Pro | Y64: 2.078.000
A65: =COUNTIF('Call & Chat-Lidya'!$I$4:$I$2391,I65) -> 8 | B65: 46188 | C65: 2026 | D65: Mei | E65: 311 | F65: 46131 | G65: AKun Baru | H65: 11026 | I65: 18411 | J65: Ivo | K65: Zeline Laundry | L65: Zeline Laundry | M65: 081225752657 | N65: 081225752657 | O65: 46131 | P65: 46145 | Q65: 0 | R65: 3 | S65: CONNECTED | T65: ENGAGE | U65: VALID | V65: (3) Berlangganan | W65: Playstore | X65: Pro | Y65: 1688000 | Z65: Bantu penghapusan transaksi
A66: =COUNTIF('Call & Chat-Lidya'!$I$4:$I$2391,I66) -> 15 | B66: 46188 | C66: 2026 | D66: Mei | E66: 6 | F66: 46144 | G66: AKun Baru | H66: 11116 | I66: 18567 | J66: Tawakkal | K66: Malomo Laundry | L66: Malomo Laundry | M66: 082347030333 | N66: 082347030333 | O66: 46144 | P66: 46158 | Q66: 1 | R66: 2 | S66: CONNECTED | T66: DELIVERED | U66: VALID | V66: (2) Trial, Demo, Interaktif | W66: Playstore
A67: =COUNTIF('Call & Chat-Lidya'!$I$4:$I$2391,I67) -> 13 | B67: 46188 | C67: 2026 | D67: Mei | E67: 339 | F67: 46134 | G67: AKun Baru | H67: 11027 | I67: 18420 | J67: Villy | K67: Resik Laundry | L67: Resik Laundry | M67: 085163036060 | N67: 085163036060 | O67: 46132 | P67: 46146 | Q67: 3 | R67: 2 | S67: CONNECTED | T67: DELIVERED | U67: VALID | V67: (2) Trial, Demo, Interaktif
A68: =COUNTIF('Call & Chat-Lidya'!$I$4:$I$2391,I68) -> 3 | B68: 46188 | C68: 2026 | D68: Mei | E68: 32 | F68: 46148 | G68: AKun Baru | H68: 10749 | I68: 17942 | J68: indah kristina | K68: saung laundry | L68: saung laundry | M68: 087882992022 | N68: 087893996550 | O68: 24/02/26 | P68: 46091 | Q68: 0 | R68: 1 | S68: CONNECTED | T68: DELIVERED | U68: VALID | V68: (0) Tidak Merespon
A69: =COUNTIF('Call & Chat-Lidya'!$I$4:$I$2391,I69) -> 3 | B69: 46188 | C69: 2026 | D69: Mei | E69: 33 | F69: 46148 | G69: AKun Baru | H69: 10756 | I69: 17951 | J69: Zazet Laundry | K69: Zazet Laundry | L69: Zazet Laundry | M69: 081513920744 | O69: 25/02/26 | P69: 46092 | Q69: 2 | R69: 1 | S69: CONTACTED | T69: DELIVERED | U69: VALID | V69: (0) Tidak Merespon
A70: =COUNTIF('Call & Chat-Lidya'!$I$4:$I$2391,I70) -> 14 | B70: 46188 | C70: 2026 | D70: Mei | E70: 124 | F70: 46118 | H70: 10936 | I70: 18245 | J70: Riska | K70: Fun Laundry | L70: Fun Laundry | M70: 081377700062 | N70: 081377700062 | O70: 46117 | P70: 46131 | Q70: 2 | R70: 2 | S70: CONNECTED | T70: DELIVERED | U70: VALID | V70: (2) Trial, Demo, Interaktif | W70: Tiktok
A71: =COUNTIF('Call & Chat-Lidya'!$I$4:$I$2391,I71) -> 6 | B71: 46188 | C71: 2026 | D71: Mei | E71: 295 | F71: 46084 | G71: AKun Baru | H71: 10679 | I71: 17843 | J71: Lusi qayyimah | K71: RUMAH LAUNDRY FRIZEL | L71: RUMAH LAUNDRY FRIZEL | M71: 082324386122 | N71: 082324386122 | O71: 46067 | P71: 46081 | Q71: 0 | R71: 1 | S71: CONTACTED | T71: DELIVERED | U71: VALID | V71: (0) Tidak Merespon | W71: Tiktok
A72: =COUNTIF('Call & Chat-Lidya'!$I$4:$I$2391,I72) -> 5 | B72: 46188 | C72: 2026 | D72: Mei | E72: 436 | F72: 46073 | G72: AKun Baru | H72: 10726 | I72: 17915 | J72: K.Jamila | K72: Syamiar Laundry | L72: Syamiar Laundry | M72: 082331159747 | N72: 082331159747 | O72: 46073 | P72: 46087 | Q72: 1 | R72: 1 | S72: CONNECTED | T72: DELIVERED | U72: VALID | V72: (0) Tidak Merespon | W72: Playstore | X72: Not yet
A73: =COUNTIF('Call & Chat-Lidya'!$I$4:$I$2391,I73) -> 6 | B73: 46188 | C73: 2026 | D73: Mei | E73: 475 | F73: 46062 | G73: AKun Baru | H73: 10635 | I73: 17775 | J73: Saleh arifin | K73: Amualfa Laundry | L73: Amualfa Laundry | M73: 081375201234 | N73: 081375201234 | O73: 46061 | P73: 46075 | Q73: 0 | R73: 1 | S73: ENGAGE | T73: DELIVERED | U73: VALID | V73: (1) Rencana buka laundry | W73: Tiktok | X73: Not yet | Z73: Aplikasi belum digunakan karna usaha laundrynya belum buka dan rencana pembukaan di bulan depan mungkin. Jika ada yang mau ditanyakan tentang piposmartnya akan dihubungi kembali
A74: =COUNTIF('Call & Chat-Lidya'!$I$4:$I$2391,I74) -> 3 | B74: 46188 | C74: 2026 | D74: Juni | E74: 1 | F74: 46174 | G74: AKun Baru | H74: 11304 | I74: 18894 | J74: family home loundrey | K74: family home loundrey | L74: family home loundrey | M74: 085738880205 | N74: 085738880205 | O74: 46173 | P74: 46187 | Q74: 0 | R74: 1 | S74: ENGAGE | T74: DELIVERED | U74: VALID | V74: (1) Incoming | W74: Tiktok
A75: =COUNTIF('Call & Chat-Lidya'!$I$4:$I$2391,I75) -> 4 | B75: 46188 | C75: 2026 | D75: Juni | E75: 2 | F75: 46174 | G75: AKun Baru | H75: 11307 | I75: 18899 | J75: Renita Setianingsih | K75: Golden Laundry | L75: Golden Laundry | M75: 087829560267 | N75: 085725651447 | O75: 46174 | P75: 46188 | Q75: 0 | R75: 1 | S75: CONTACTED | T75: DELIVERED | U75: VALID | V75: (0) Tidak Merespon
A76: =COUNTIF('Call & Chat-Lidya'!$I$4:$I$2391,I76) -> 4 | B76: 46188 | C76: 2026 | D76: Juni | E76: 3 | F76: 46175 | G76: AKun Baru | H76: 11310 | I76: 18904 | J76: Nadiva Laundry | K76: Nadiva Laundry | L76: Nadiva Laundry | M76: 085608982002 | N76: 085608982002 | O76: 46174 | P76: 46188 | Q76: 0 | R76: 1 | S76: CONNECTED | T76: DELIVERED | U76: VALID | V76: (0) Tidak Merespon
A77: =COUNTIF('Call & Chat-Lidya'!$I$4:$I$2391,I77) -> 4 | B77: 46188 | C77: 2026 | D77: Juni | E77: 4 | F77: 46175 | G77: AKun Baru | H77: 11311 | I77: 18905 | J77: Indri Rafa | K77: Hana stasya laundry | L77: Hana stasya laundry | M77: 6289602895782 | N77: 089602895782 | O77: 46174 | P77: 46188 | Q77: 0 | R77: 1 | S77: CONTACTED | T77: DELIVERED | U77: VALID | V77: (0) Tidak Merespon
A78: =COUNTIF('Call & Chat-Lidya'!$I$4:$I$2391,I78) -> 4 | B78: 46188 | C78: 2026 | D78: Juni | E78: 5 | F78: 46175 | G78: AKun Baru | H78: 11312 | I78: 18906 | J78: sarni andri | K78: Derisa laundry | L78: Derisa laundry | M78: 0895378172793 | N78: 0895378172793 | O78: 46175 | P78: 46189 | Q78: 0 | R78: 1 | S78: ENGAGE | T78: DELIVERED | U78: VALID | V78: (0) Data Employee dan Trial | Z78: Konfirmasi pengunaan aplikasi piposmart, call langsung dimatikan
A79: =COUNTIF('Call & Chat-Lidya'!$I$4:$I$2391,I79) -> 3 | B79: 46188 | C79: 2026 | D79: Mei | E79: 367 | F79: 46148 | G79: AKun Baru | H79: 10063 | I79: 16740 | J79: said lutfi manfalutie | K79: SMA LAUNDRY | L79: SMA LAUNDRY | N79: 085370700942 | O79: 02/11/25 | P79: 45977 | Q79: 0 | R79: 1 | S79: CONNECTED | T79: DELIVERED | U79: VALID | V79: (0) Tidak Merespon
A80: =COUNTIF('Call & Chat-Lidya'!$I$4:$I$2397,I80) -> 2 | B80: 46185 | C80: 2026 | D80: Juni | E80: 7 | F80: 46175 | G80: AKun Baru | H80: 10828 | I80: 18070 | J80: Ramlah 15 | K80: IRA LAUNDRY | L80: IRA LAUNDRY | M80: 085252472966 | N80: 082252472966 | O80: 46090 | P80: 46104 | Q80: 0 | R80: 0 | S80: CONTACTED | T80: NO CHAT | U80: INVALID | V80: (0) Tidak Merespon | Z80: Nomor tidak terhubung dengan wa
A81: =COUNTIF('Call & Chat-Lidya'!$I$4:$I$2397,I81) -> 2 | B81: 46185 | C81: 2026 | D81: Juni | E81: 8 | F81: 46175 | G81: AKun Baru | H81: 10850 | I81: 18104 | J81: Sofiah ichwani | K81: Azzahra laundry | L81: Azzahra laundry | M81: 081269923421 | N81: 081269923421 | O81: 46095 | P81: 46109 | Q81: 4 | R81: 1 | S81: CONTACTED | T81: DELIVERED | U81: VALID | V81: (0) Tidak Merespon
A82: =COUNTIF('Call & Chat-Lidya'!$I$4:$I$2397,I82) -> 2 | B82: 46185 | C82: 2026 | D82: Juni | E82: 10 | F82: 46175 | G82: AKun Baru | H82: 10860 | I82: 18117 | J82: Aswar Anas | K82: Laundry.KU | L82: Laundry.KU | M82: 082291364112 | N82: 082291364112 | O82: 46098 | P82: 46112 | Q82: 0 | R82: 1 | S82: CONTACTED | T82: DELIVERED | U82: VALID | V82: (0) Tidak Merespon
A83: =COUNTIF('Call & Chat-Lidya'!$I$4:$I$2397,I83) -> 2 | B83: 46185 | C83: 2026 | D83: Juni | E83: 11 | F83: 46175 | G83: AKun Baru | H83: 10865 | I83: 18124 | J83: Slastia | K83: LAUNDRY 99 KARAWANG | L83: LAUNDRY 99 KARAWANG | M83: 089630415505 | N83: 089630415505 | O83: 46099 | P83: 46113 | Q83: 0 | R83: 1 | S83: CONTACTED | T83: DELIVERED | U83: VALID | V83: (0) Tidak Merespon
A84: =COUNTIF('Call & Chat-Lidya'!$I$4:$I$2397,I84) -> 2 | B84: 46185 | C84: 2026 | D84: Juni | E84: 12 | F84: 46175 | G84: AKun Baru | H84: 10867 | I84: 18126 | J84: Ica Vera | K84: terima uang | L84: terima uang | M84: 082128887889 | N84: 082128887889 | O84: 46100 | P84: 46114 | Q84: 0 | R84: 0 | S84: CONTACTED | T84: SENT | U84: INVALID | V84: (0) Tidak Merespon
A85: =COUNTIF('Call & Chat-Lidya'!$I$4:$I$2397,I85) -> 2 | B85: 46185 | C85: 2026 | D85: Juni | E85: 13 | F85: 46175 | G85: AKun Baru | H85: 10871 | I85: 18132 | J85: ori zapp | K85: Geubrina londry | L85: Geubrina londry | M85: 085136305406 | N85: 085136305406 | O85: 46102 | P85: 46116 | Q85: 2 | R85: 1 | S85: CONTACTED | T85: DELIVERED | U85: VALID | V85: (0) Tidak Merespon
A86: =COUNTIF('Call & Chat-Lidya'!$I$4:$I$2397,I86) -> 2 | B86: 46185 | C86: 2026 | D86: Juni | E86: 14 | F86: 46175 | G86: AKun Baru | H86: 10876 | I86: 18140 | J86: Batapas Laundry Express | K86: Batapas Laundry Express | L86: Batapas Laundry Express | M86: 085960224716 | N86: 085960224716 | O86: 46104 | P86: 46118 | Q86: 1 | R86: 1 | S86: CONTACTED | T86: DELIVERED | U86: VALID | V86: (0) Tidak Merespon
A87: =COUNTIF('Call & Chat-Lidya'!$I$4:$I$2397,I87) -> 2 | B87: 46185 | C87: 2026 | D87: Juni | E87: 15 | F87: 46175 | G87: AKun Baru | H87: 10880 | I87: 18147 | J87: Moja Wash BSD | K87: mo | L87: mo | M87: 087887700094 | N87: 087887700094 | O87: 46106 | P87: 46120 | Q87: 0 | R87: 1 | S87: CONNECTED | T87: DELIVERED | U87: VALID | V87: (0) Tidak Merespon
A88: =COUNTIF('Call & Chat-Lidya'!$I$4:$I$2397,I88) -> 4 | B88: 46185 | C88: 2026 | D88: Juni | E88: 16 | F88: 46175 | G88: AKun Baru | H88: 10882 | I88: 18150 | J88: Abimanyu | K88: Laundry Yook | L88: Laundry Yook | M88: 0882007927333 | N88: 0882007927333 | O88: 46106 | P88: 46120 | Q88: 55 | R88: 1 | S88: CONTACTED | T88: DELIVERED | U88: VALID | V88: (0) Tidak Merespon
A89: =COUNTIF('Call & Chat-Lidya'!$I$4:$I$2397,I89) -> 4 | B89: 46185 | C89: 2026 | D89: Juni | E89: 19 | F89: 46175 | G89: AKun Baru | H89: 11317 | I89: 18913 | J89: Elfira Yanti | K89: buk Yanti laundry | L89: buk Yanti laundry | M89: 082280298103 | N89: 082280298103 | O89: 46175 | P89: 46189 | Q89: 1 | R89: 1 | S89: CONNECTED | T89: DELIVERED | U89: VALID | V89: (0) Tidak Merespon
A90: =COUNTIF('Call & Chat-Lidya'!$I$4:$I$2397,I90) -> 4 | B90: 46185 | C90: 2026 | D90: Juni | E90: 20 | F90: 46175 | G90: AKun Baru | H90: 11318 | I90: 18916 | J90: Yanti Fitria Sari | K90: JA londry | L90: JA londry | M90: 085283284078 | N90: 85283284078 | O90: 46175 | P90: 46189 | Q90: 0 | R90: 1 | S90: CONTACTED | T90: DELIVERED | U90: VALID | V90: (0) Tidak Merespon
A91: =COUNTIF('Call & Chat-Lidya'!$I$4:$I$2397,I91) -> 4 | B91: 46185 | C91: 2026 | D91: Juni | E91: 21 | F91: 46176 | G91: AKun Baru | H91: 10882 | I91: 18150 | J91: Abimanyu | K91: WOW LAUNDRY | L91: Laundry Yook | M91: 0882007927333 | N91: 0882007927333 | O91: 46106 | P91: 46120 | Q91: 111 | R91: 1 | S91: CONTACTED | T91: DELIVERED | U91: VALID | V91: (0) Tidak Merespon
A92: =COUNTIF('Call & Chat-Lidya'!$I$4:$I$2397,I92) -> 2 | B92: 46185 | C92: 2026 | D92: Juni | E92: 22 | F92: 46176 | G92: AKun Baru | H92: 10886 | I92: 18155 | J92: Owner | K92: 24Laundry | L92: 24Laundry | M92: 081334428518 | N92: 085156239895 | O92: 46106 | P92: 46120 | Q92: 24 | R92: 1 | S92: CONTACTED | T92: DELIVERED | U92: VALID | V92: (0) Tidak Merespon
... A94: =COUNTIF('Call & Chat-Lidya'!$I$4:$I$2397,I94) -> 2 | B94: 46185 | C94: 2026 | D94: Juni | E94: 24 | F94: 46176 | G94: AKun Baru | H94: 10892 | I94: 18165 | J94: Nanda Aulia | K94: Ara Laundry | L94: Ara Laundry | M94: 085215899395 | N94: 085215899395 | O94: 46107 | P94: 46121 | Q94: 10 | R94: 1 | S94: CONTACTED | T94: DELIVERED | U94: VALID | V94: (0) Tidak Merespon
A95: =COUNTIF('Call & Chat-Lidya'!$I$4:$I$2397,I95) -> 2 | B95: 46185 | C95: 2026 | D95: Juni | E95: 26 | F95: 46176 | G95: AKun Baru | H95: 10916 | I95: 18201 | J95: anindia | K95: Star Laundry 2 | L95: Star Laundry 2 | M95: 085820557960 | N95: 085820557960 | O95: 46112 | P95: 46126 | Q95: 0 | R95: 1 | S95: ENGAGE | T95: DELIVERED | U95: VALID | V95: (0) Data Employee dan Trial | Z95: Konfirmasi penggunaan aplikasi piposmart dan call langsung dimatikan
A96: =COUNTIF('Call & Chat-Lidya'!$I$4:$I$2397,I96) -> 2 | B96: 46185 | C96: 2026 | D96: Juni | E96: 27 | F96: 46176 | G96: AKun Baru | H96: 10920 | I96: 18214 | J96: Arkan laundry | K96: Arkan Laundry | L96: Arkan Laundry | M96: 083150654324 | N96: 083150654324 | O96: 46114 | P96: 46128 | Q96: 8 | R96: 1 | S96: ENGAGE | T96: DELIVERED | U96: VALID | V96: (0) Data Employee dan Trial | Z96: Konfirmasi penggunaan aplikasi piposmart dan call langsung dimatikan
A97: =COUNTIF('Call & Chat-Lidya'!$I$4:$I$2397,I97) -> 2 | B97: 46185 | C97: 2026 | D97: Juni | E97: 28 | F97: 46176 | G97: AKun Baru | H97: 10924 | I97: 18220 | J97: Kanza Aulia | K97: Jastrika | L97: Jastrika | M97: 0895342756135 | N97: 0895342756135 | O97: 46114 | P97: 46128 | Q97: 1 | R97: 1 | S97: CONNECTED | T97: DELIVERED | U97: VALID | V97: (0) Tidak Merespon
A98: =COUNTIF('Call & Chat-Lidya'!$I$4:$I$2397,I98) -> 2 | B98: 46185 | C98: 2026 | D98: Juni | E98: 29 | F98: 46176 | G98: AKun Baru | H98: 10932 | I98: 18235 | J98: Arwina | K98: Win Laundry | L98: Win Laundry | M98: 088245670913 | N98: 088245670913 | O98: 46116 | P98: 46130 | Q98: 0 | R98: 1 | S98: CONTACTED | T98: DELIVERED | U98: VALID | V98: (0) Tidak Merespon
A99: =COUNTIF('Call & Chat-Lidya'!$I$4:$I$2397,I99) -> 2 | B99: 46185 | C99: 2026 | D99: Juni | E99: 30 | F99: 46176 | G99: AKun Baru | H99: 10935 | I99: 18239 | J99: feny setiani | K99: Cleanwash Laundry | L99: Cleanwash Laundry | M99: 0895372027589 | O99: 46117 | P99: 46131 | Q99: 0 | R99: 1 | S99: CONNECTED | T99: DELIVERED | U99: VALID | V99: (0) Tidak Merespon
A100: =COUNTIF('Call & Chat-Lidya'!$I$4:$I$2397,I100) -> 2 | B100: 46185 | C100: 2026 | D100: Juni | E100: 31 | F100: 46176 | G100: AKun Baru | H100: 10959 | I100: 18286 | J100: Ariana | K100: Anah laundry | L100: Anah laundry | M100: 081220754792 | N100: 081220754792 | O100: 46120 | P100: 46134 | Q100: 1 | R100: 1 | S100: CONTACTED | T100: DELIVERED | U100: VALID | V100: (0) Tidak Merespon
A101: =COUNTIF('Call & Chat-Lidya'!$I$4:$I$2397,I101) -> 2 | B101: 46185 | C101: 2026 | D101: Juni | E101: 32 | F101: 46176 | G101: AKun Baru | H101: 10977 | I101: 18313 | J101: mamaJO | K101: mamaJO LAUNDRY | L101: mamaJO LAUNDRY | M101: 082374564878 | O101: 46123 | P101: 46137 | Q101: 5 | R101: 1 | S101: CONTACTED | T101: DELIVERED | U101: VALID | V101: (0) Tidak Merespon
...

Sheet Report - Lidya
A1: Kategori Nasabah | C1: Jan | D1: Feb | E1: Maret | F1: April | G1: Mei | H1: Juni | I1: Juli | J1: Agust | K1: Total
A2: Nasabah Baru | C2: =SUM(F97:F115) -> 169 | D2: =SUM(F74:F96) -> 268 | E2: =SUM(F66:F84) -> 208 | F2: =SUM(F46:F65) -> 115 | G2: =SUM(F30:F45) -> 100 | H2: =SUM(F19:F29) -> 66
A3: Nasabah Potensial | C3: =SUM(L97:L115) -> 35 | D3: =SUM(L74:L96) -> 41 | E3: =SUM(L66:L84) -> 26 | F3: =SUM(L46:L65) -> 34 | G3: =SUM(L30:L45) -> 72 | H3: =SUM(L19:L29) -> 44
A4: Nasabah Mitra | C4: =SUM(R97:R115) -> 2 | D4: =SUM(R74:R96) -> 7 | E4: =SUM(R66:R84) -> 4 | F4: =SUM(R46:R65) -> 2 | G4: =SUM(R30:R45) -> 2 | H4: =SUM(R19:R29) -> 1
A5: Total Nasabah No Respon | C5: =SUM(Z97:Z115) -> 346 | D5: =SUM(Z74:Z96) -> 583 | E5: =SUM(Z66:Z84) -> 566 | F5: =SUM(Z46:Z65) -> 434 | G5: =SUM(Z30:Z45) -> 588 | H5: =SUM(Z19:Z29) -> 303
A6: Total Nasabah Respon | C6: =SUM(C2:C4) -> 206 | D6: =SUM(D2:D4) -> 316 | E6: =SUM(Y66:Y84) -> 238 | F6: =SUM(F2:F4) -> 151 | G6: =SUM(G2:G4) -> 174 | H6: =SUM(Y19:Y29) -> 128 | I6: =SUM(I2:I4) -> 0 | J6: =SUM(J2:J4) -> 0 | K6: =SUM(K2:K4) -> 0
A8: Daily Report Activity | Y8: Total Respon (Nasabah Baru + Potensi + Mitra) | Z8: Total No Respon (Nasabah Baru + Potensi + Mitra) | AA8: Total
A9: Bulan | B9: Tanggal | C9: Nasabah Registrasi Akun | G9: Nasabah Potensi | M9: Mitra | S9: Nasabah Jatuh Tempo
C10: Respon | E10: No Respon | F10: Respon | G10: Respon | K10: No Respon | L10: Respon | M10: Respon | Q10: No Respon | R10: Respon | S10: Respon | W10: No Respon | X10: Respon
C11: Call | D11: Chat | G11: Call | H11: Chat | I11: Online Meeting | J11: Visit Laundry | M11: Call | N11: Chat | O11: Online Meeting | P11: Visit Laundry | S11: Call | T11: Chat | U11: Online Meeting | V11: Visit Laundry
A13: Juni
A14: Juni
A15: Juni
A16: Juni
A17: Juni
A18: Juni | B18: Kamis. 18
A19: Juni | B19: Rabu, 17 | C19: 7 | D19: 5 | E19: 14 | F19: =SUM(C19:D19) -> 12 | G19: 4 | H19: 0 | I19: 1 | J19: 0 | K19: 7 | L19: =SUM(G19:J19) -> 5 | M19: 0 | N19: 0 | O19: 0 | P19: 0 | Q19: 0 | R19: 0 | S19: 0 | T19: 1 | U19: 0 | V19: 0 | W19: 9 | X19: =SUM(S19:V19) -> 1 | Y19: =SUM(F19,L19,R19,X19) -> 18 | Z19: =SUM(E19,K19,Q19,W19) -> 30 | AA19: =SUM(Y19+Z19) -> 48
A20: Juni | B20: Senin, 15 | C20: 5 | D20: 2 | E20: 14 | F20: =SUM(C20:D20) -> 7 | G20: 3 | H20: 3 | I20: 1 | J20: 0 | K20: 6 | L20: =SUM(G20:J20) -> 7 | M20: 0 | N20: 0 | O20: 0 | P20: 0 | Q20: 0 | R20: 0 | S20: 0 | T20: 2 | U20: 0 | V20: 0 | W20: 24 | X20: =SUM(S20:V20) -> 2 | Y20: =SUM(F20,L20,R20,X20) -> 16 | Z20: =SUM(E20,K20,Q20,W20) -> 44 | AA20: =SUM(Y20+Z20) -> 60
A21: Juni | B21: Jumat. 12 | C21: 3 | D21: 0 | E21: 27 | F21: =SUM(C21:D21) -> 3 | G21: 0 | H21: 0 | I21: 1 | J21: 0 | K21: 0 | L21: =SUM(G21:J21) -> 1 | M21: 0 | N21: 0 | O21: 0 | P21: 0 | Q21: 0 | R21: 0 | S21: 1 | T21: 0 | U21: 0 | V21: 0 | W21: 8 | X21: =SUM(S21:V21) -> 1 | Y21: =SUM(F21,L21,R21,X21) -> 5 | Z21: =SUM(E21,K21,Q21,W21) -> 35 | AA21: =SUM(Y21+Z21) -> 40
A22: Juni | B22: Kamis, 11 | C22: 9 | D22: 2 | E22: 24 | F22: =SUM(C22:D22) -> 11 | G22: 1 | H22: 2 | I22: 1 | J22: 0 | K22: 5 | L22: =SUM(G22:K22) -> 9 | M22: 0 | N22: 0 | O22: 0 | P22: 0 | Q22: 0 | R22: 0 | S22: 0 | T22: 1 | U22: 0 | V22: 0 | W22: 9 | X22: =SUM(S22:V22) -> 1 | Y22: =SUM(F22,L22,R22,X22) -> 21 | Z22: =SUM(E22,K22,Q22,W22) -> 38 | AA22: =SUM(Y22+Z22) -> 59
A23: Juni | B23: Rabu, 10 | C23: 5 | D23: 2 | E23: 12 | F23: =SUM(C23:D23) -> 7 | G23: 5 | H23: 2 | I23: 1 | J23: 0 | K23: 5 | L23: =SUM(G23:J23) -> 8 | M23: 0 | N23: 0 | O23: 0 | P23: 0 | Q23: 0 | R23: 0 | S23: 1 | T23: 0 | U23: 0 | V23: 0 | W23: 0 | X23: =SUM(S23:V23) -> 1 | Y23: =SUM(F23,L23,R23,X23) -> 16 | Z23: =SUM(E23,K23,Q23,W23) -> 17 | AA23: =SUM(Y23+Z23) -> 33
A24: Juni | B24: Selasa. 09 | C24: 6 | D24: 2 | E24: 16 | F24: =SUM(C24:D24) -> 8 | G24: 1 | H24: 2 | I24: 2 | J24: 0 | K24: 2 | L24: =SUM(G24:J24) -> 5 | M24: 0 | N24: 0 | O24: 0 | P24: 0 | Q24: 0 | R24: 0 | S24: 0 | T24: 1 | U24: 0 | V24: 0 | W24: 15 | X24: =SUM(S24:V24) -> 1 | Y24: =SUM(F24,L24,R24,X24) -> 14 | Z24: =SUM(E24,K24,Q24,W24) -> 33 | AA24: =SUM(Y24+Z24) -> 47
A25: Juni | B25: Senin, 08 | C25: 1 | D25: 1 | E25: 17 | F25: =SUM(C25:D25) -> 2 | G25: 4 | H25: 1 | I25: 3 | J25: 0 | K25: 4 | L25: =SUM(G25:J25) -> 8 | M25: 0 | N25: 1 | O25: 0 | P25: 0 | Q25: 0 | R25: =SUM(M25:P25) -> 1 | S25: 2 | T25: 3 | U25: 0 | V25: 0 | W25: 4 | X25: =SUM(S25:V25) -> 5 | Y25: =SUM(F25,L25,R25,X25) -> 16 | Z25: =SUM(E25,K25,Q25,W25) -> 25 | AA25: =SUM(Y25+Z25) -> 41
A26: Juni | B26: Jumat, 05 | C26: Test Bug Ayocuci dan bantu special case dan kendala beberapa nasabah
A27: Juni | B27: Kamis, 04 | C27: 8 | D27: 6 | E27: 24 | F27: =SUM(C27:D27) -> 14 | G27: 0 | H27: 1 | I27: 0 | J27: 0 | K27: 3 | L27: =SUM(G27:J27) -> 1 | M27: 0 | N27: 0 | O27: 0 | P27: 0 | Q27: 0 | R27: 0 | S27: 0 | T27: 0 | U27: 0 | V27: 0 | W27: 0 | X27: 0 | Y27: =SUM(F27,L27,R27,X27) -> 15 | Z27: =SUM(E27,K27,Q27,W27) -> 27 | AA27: =SUM(Y27+Z27) -> 42
A28: Juni | B28: Rabu,03 | C28: 1 | D28: 1 | E28: 21 | F28: =SUM(C28:D28) -> 2 | G28: 0 | H28: 0 | I28: 0 | J28: 0 | K28: 6 | L28: 0 | M28: 0 | N28: 0 | O28: 0 | P28: 0 | Q28: 2 | R28: 0 | S28: 0 | T28: 5 | U28: 0 | V28: 0 | W28: 25 | X28: =SUM(S28:V28) -> 5 | Y28: =SUM(F28,L28,R28,X28) -> 7 | Z28: =SUM(E28,K28,Q28,W28) -> 54 | AA28: =SUM(Y28+Z28) -> 61
A29: Juni | B29: Selasa. 02 | C29: Melengkapi data kelolaan Mei
A30: Mei | B30: Jumat, 29 | C30: 6 | D30: 1 | E30: 21 | F30: =SUM(C30:D30) -> 7 | G30: 5 | H30: 1 | I30: 0 | J30: 0 | K30: 6 | L30: =SUM(G30:J30) -> 6 | M30: 0 | N30: 0 | O30: 0 | P30: 0 | Q30: 0 | R30: 0 | S30: 2 | T30: 2 | U30: 0 | V30: 0 | W30: 14 | X30: =SUM(S30:V30) -> 4 | Y30: =SUM(F30,L30,R30,X30) -> 17 | Z30: =SUM(E30,K30,Q30,W30) -> 41 | AA30: =SUM(Y30+Z30) -> 58
A31: Mei | B31: Kamis,28 | C31: 1 | D31: 0 | E31: 4 | F31: =SUM(C31:D31) -> 1 | G31: 6 | H31: 1 | I31: 1 | J31: 0 | K31: 24 | L31: =SUM(G31:J31) -> 8 | M31: 0 | N31: 0 | O31: 0 | P31: 0 | Q31: 0 | R31: 0 | S31: 0 | T31: 2 | U31: 0 | V31: 0 | W31: 28 | X31: =SUM(S31:V31) -> 2 | Y31: =SUM(F31,L31,R31,X31) -> 11 | Z31: =SUM(E31,K31,Q31,W31) -> 56 | AA31: =SUM(Y31+Z31) -> 67
A32: Mei | B32: Selasa, 26 | C32: 6 | D32: 4 | E32: 42 | F32: =SUM(C32:D32) -> 10 | G32: 0 | H32: 0 | I32: 2 | J32: 0 | K32: 2 | L32: =SUM(G32:J32) -> 2 | M32: 0 | N32: 0 | O32: 0 | P32: 0 | Q32: 0 | R32: 0 | S32: 1 | T32: 0 | U32: 0 | V32: 0 | W32: 8 | X32: =SUM(S32:V32) -> 1 | Y32: =SUM(F32,L32,R32,X32) -> 13 | Z32: =SUM(E32,K32,Q32,W32) -> 52 | AA32: =SUM(Y32+Z32) -> 65
A33: Mei | B33: Senin, 25 | C33: 4 | D33: 3 | E33: 14 | F33: =SUM(C33:D33) -> 7 | G33: 2 | H33: 0 | I33: 1 | J33: 0 | K33: 6 | L33: =SUM(G33:J33) -> 3 | M33: 0 | N33: 0 | O33: 0 | P33: 0 | Q33: 0 | R33: 0 | S33: 0 | T33: 0 | U33: 0 | V33: 0 | W33: 0 | X33: =SUM(S33:V33) -> 0 | Y33: =SUM(F33,L33,R33,X33) -> 10 | Z33: =SUM(E33,K33,Q33,W33) -> 20 | AA33: =SUM(Y33+Z33) -> 30
A34: Mei | B34: Jumat, 22 | C34: 2 | D34: 5 | E34: 16 | F34: =SUM(C34:D34) -> 7 | G34: 0 | H34: 2 | I34: 1 | J34: 0 | K34: 7 | L34: =SUM(G34:J34) -> 3 | M34: 0 | N34: 0 | O34: 0 | P34: 0 | Q34: 0 | R34: 0 | S34: 1 | T34: 0 | U34: 0 | V34: 0 | W34: 20 | X34: =SUM(S34:V34) -> 1 | Y34: =SUM(F34,L34,R34,X34) -> 11 | Z34: =SUM(E34,K34,Q34,W34) -> 43 | AA34: =SUM(Y34+Z34) -> 54
A35: Mei | B35: Kamis, 21 | C35: 5 | D35: 3 | E35: 13 | F35: =SUM(C35:D35) -> 8 | G35: 5 | H35: 0 | I35: 0 | J35: 0 | K35: 13 | L35: =SUM(G35:J35) -> 5 | M35: 0 | N35: 0 | O35: 0 | P35: 0 | Q35: 0 | R35: 0 | S35: 2 | T35: 0 | U35: 0 | V35: 0 | W35: 0 | X35: =SUM(S35:V35) -> 2 | Y35: =SUM(F35,L35,R35,X35) -> 15 | Z35: =SUM(E35,K35,Q35,W35) -> 26 | AA35: =SUM(Y35+Z35) -> 41
A36: Mei | B36: Rabu, 20 | C36: 2 | D36: 0 | E36: 5 | F36: =SUM(C36:D36) -> 2 | G36: 3 | H36: 4 | I36: 1 | J36: 0 | K36: 12 | L36: =SUM(G36:J36) -> 8 | M36: 0 | N36: 0 | O36: 0 | P36: 0 | Q36: 0 | R36: 0 | S36: 1 | T36: 0 | U36: 0 | V36: 0 | W36: 0 | X36: =SUM(S36:V36) -> 1 | Y36: =SUM(F36,L36,R36,X36) -> 11 | Z36: =SUM(E36,K36,Q36,W36) -> 17 | AA36: =SUM(Y36+Z36) -> 28
A37: Mei | B37: Selasa, 19 | C37: 5 | D37: 1 | E37: 23 | F37: =SUM(C37:D37) -> 6 | G37: 1 | H37: 3 | I37: 0 | J37: 0 | K37: 2 | L37: =SUM(G37:J37) -> 4 | M37: 0 | N37: 0 | O37: 0 | P37: 0 | Q37: 0 | R37: 0 | S37: 0 | T37: 3 | U37: 0 | V37: 0 | W37: 16 | X37: =SUM(S37:V37) -> 3 | Y37: =SUM(F37,L37,R37,X37) -> 13 | Z37: =SUM(E37,K37,Q37,W37) -> 41 | AA37: =SUM(Y37+Z37) -> 54
A38: Mei | B38: Senin, 18 | C38: 7 | D38: 7 | E38: 26 | F38: =SUM(C38:D38) -> 14 | G38: 1 | H38: 2 | I38: 3 | J38: 0 | K38: 6 | L38: =SUM(G38:J38) -> 6 | M38: 0 | N38: 0 | O38: 0 | P38: 0 | Q38: 0 | R38: 0 | S38: 0 | T38: 2 | U38: 0 | V38: 0 | W38: 13 | X38: =SUM(S38:V38) -> 2 | Y38: =SUM(F38,L38,R38,X38) -> 22 | Z38: =SUM(E38,K38,Q38,W38) -> 45 | AA38: =SUM(Y38+Z38) -> 67
A39: Mei | B39: Jumat, 15 | C39: 4 | D39: 1 | E39: 18 | F39: =SUM(C39:D39) -> 5 | G39: 3 | H39: 4 | I39: 0 | J39: 0 | K39: 6 | L39: =SUM(G39:J39) -> 7 | M39: 0 | N39: 0 | O39: 0 | P39: 0 | Q39: 0 | R39: 0 | S39: 0 | T39: 2 | U39: 0 | V39: 0 | W39: 12 | X39: =SUM(S39:V39) -> 2 | Y39: =SUM(F39,L39,R39,X39) -> 14 | Z39: =SUM(E39,K39,Q39,W39) -> 36 | AA39: =SUM(Y39+Z39) -> 50
A40: Mei | B40: Rabu, 13 | C40: 4 | D40: 2 | E40: 20 | F40: =SUM(C40:D40) -> 6 | G40: 0 | H40: 2 | I40: 0 | J40: 0 | K40: 2 | L40: =SUM(G40:J40) -> 2 | M40: 0 | N40: 0 | O40: 0 | P40: 0 | Q40: 0 | R40: 0 | S40: 0 | T40: 4 | U40: 0 | V40: 0 | W40: 18 | X40: =SUM(S40:V40) -> 4 | Y40: =SUM(F40,L40,R40,X40) -> 12 | Z40: =SUM(E40,K40,Q40,W40) -> 40 | AA40: =SUM(Y40+Z40) -> 52
A41: Mei | B41: Jumat, 08 | C41: 4 | D41: 2 | E41: 32 | F41: =SUM(C41:D41) -> 6 | G41: 2 | H41: 1 | I41: 0 | J41: 0 | K41: 12 | L41: =SUM(G41:J41) -> 3 | M41: 0 | N41: 0 | O41: 0 | P41: 0 | Q41: 0 | R41: 0 | S41: 0 | T41: 3 | U41: 0 | V41: 0 | W41: 14 | X41: =SUM(S41:V41) -> 3 | Y41: =SUM(F41,L41,R41,X41) -> 12 | Z41: =SUM(E41,K41,Q41,W41) -> 58 | AA41: =SUM(Y41+Z41) -> 70
A42: Mei | B42: Kamis, 07 | C42: 8 | D42: 2 | E42: 30 | F42: =SUM(C42:D42) -> 10 | G42: 1 | H42: 1 | I42: 0 | J42: 0 | K42: 1 | L42: =SUM(G42:J42) -> 2 | M42: 0 | N42: 0 | O42: 0 | P42: 0 | Q42: 0 | R42: 0 | S42: 0 | T42: 2 | U42: 0 | V42: 0 | W42: 6 | X42: =SUM(S42:W42) -> 8 | Y42: =SUM(F42,L42,R42,X42) -> 20 | Z42: =SUM(E42,K42,Q42,W42) -> 37 | AA42: =SUM(Y42+Z42) -> 57
A43: Mei | B43: Rabu, 06 | C43: 5 | D43: 0 | E43: 10 | F43: =SUM(C43:D43) -> 5 | G43: 3 | H43: 0 | I43: 0 | J43: 0 | K43: 2 | L43: =SUM(G43:J43) -> 3 | M43: 0 | N43: 0 | O43: 0 | P43: 0 | Q43: 0 | R43: 0 | S43: 0 | T43: 1 | U43: 0 | V43: 0 | W43: 10 | X43: =SUM(S43:V43) -> 1 | Y43: =SUM(F43,L43,R43,X43) -> 9 | Z43: =SUM(E43,K43,Q43,W43) -> 22 | AA43: =SUM(Y43+Z43) -> 31
A44: Mei | B44: Sel, 05 | C44: 3 | D44: 1 | E44: 21 | F44: =SUM(C44:D44) -> 4 | G44: 1 | H44: 5 | I44: 0 | J44: 0 | K44: 5 | L44: =SUM(G44:J44) -> 6 | M44: 0 | N44: 1 | O44: 0 | P44: 0 | Q44: 0 | R44: =SUM(M44:P44) -> 1 | S44: 1 | T44: 5 | U44: 0 | V44: 1 | W44: 15 | X44: =SUM(S44:V44) -> 7 | Y44: =SUM(F44,L44,R44,X44) -> 18 | Z44: =SUM(E44,K44,Q44,W44) -> 41 | AA44: =SUM(Y44+Z44) -> 59
A45: Mei | B45: Sen, 04 | C45: 1 | D45: 1 | E45: 9 | F45: =SUM(C45:D45) -> 2 | G45: 1 | H45: 2 | I45: 0 | J45: 1 | K45: 2 | L45: =SUM(G45:J45) -> 4 | M45: 0 | N45: 1 | O45: 0 | P45: 0 | Q45: 0 | R45: =SUM(M45:P45) -> 1 | S45: 1 | T45: 2 | U45: 0 | V45: 0 | W45: 2 | X45: =SUM(S45:V45) -> 3 | Y45: =SUM(F45,L45,R45,X45) -> 10 | Z45: =SUM(E45,K45,Q45,W45) -> 13 | AA45: =SUM(Y45+Z45) -> 23
A46: April | B46: Kamis, 30 | C46: 8 | D46: 6 | E46: 21 | F46: =SUM(C46:D46) -> 14 | G46: 3 | H46: 1 | I46: 0 | J46: 0 | K46: 5 | L46: =SUM(G46:J46) -> 4 | M46: 0 | N46: 0 | O46: 0 | P46: 0 | Q46: 0 | R46: 0 | S46: 1 | T46: 4 | U46: 0 | V46: 0 | W46: 8 | X46: =SUM(S46:V46) -> 5 | Y46: =SUM(F46,L46,R46,X46) -> 23 | Z46: =SUM(E46,K46,Q46,W46) -> 34 | AA46: =SUM(Y46+Z46) -> 57
A47: April | B47: Rabu, 29 | C47: 12 | D47: 5 | E47: 31 | F47: =SUM(C47:D47) -> 17 | G47: 3 | H47: 1 | I47: 0 | J47: 0 | K47: 1 | L47: =SUM(G47:K47) -> 5 | M47: 0 | N47: 0 | O47: 0 | P47: 0 | Q47: 0 | R47: 0 | S47: 1 | T47: 3 | U47: 0 | V47: 0 | W47: 12 | X47: =SUM(S47:V47) -> 4 | Y47: =SUM(F47,L47,R47,X47) -> 26 | Z47: =SUM(E47,K47,Q47,W47) -> 44 | AA47: =SUM(Y47+Z47) -> 70
A48: April | B48: Selasa, 28 | C48: 8 | D48: 3 | E48: 20 | F48: =SUM(C48:D48) -> 11 | G48: 2 | H48: 1 | I48: 0 | J48: 0 | K48: 5 | L48: =SUM(G48:K48) -> 8 | M48: 0 | N48: 0 | O48: 0 | P48: 0 | Q48: 0 | R48: 0 | S48: 2 | T48: 2 | U48: 0 | V48: 0 | W48: 14 | X48: =SUM(S48:V48) -> 4 | Y48: =SUM(F48,L48,R48,X48) -> 23 | Z48: =SUM(E48,K48,Q48,W48) -> 39 | AA48: =SUM(Y48+Z48) -> 62
A49: April | B49: Senin, 27 | C49: Pemindahan akun WA Business ke Device Baru dan pemulihan Data, Join webinar | M49: 0 | N49: 0 | O49: 0 | P49: 0 | Q49: 0 | R49: 0 | S49: 0 | T49: 0 | U49: 0 | V49: 0 | W49: 0 | X49: 0 | Y49: 0 | Z49: =SUM(E49,K49,Q49,W49) -> 0 | AA49: =SUM(Y49+Z49) -> 0
A50: April | B50: Jumat, 24 | C50: Akun WA Busines belum pulih | M50: 0 | N50: 0 | O50: 0 | P50: 0 | Q50: 0 | R50: 0 | S50: 0 | T50: 0 | U50: 0 | V50: 0 | W50: 0 | X50: 0 | Y50: 0 | Z50: =SUM(E50,K50,Q50,W50) -> 0 | AA50: =SUM(Y50+Z50) -> 0
A51: April | B51: Kamis, 23 | C51: Akun WA Busines belum pulih | M51: 0 | N51: 0 | O51: 0 | P51: 0 | Q51: 0 | R51: 0 | S51: 0 | T51: 0 | U51: 0 | V51: 0 | W51: 0 | X51: 0 | Y51: 0 | Z51: =SUM(E51,K51,Q51,W51) -> 0 | AA51: =SUM(Y51+Z51) -> 0
A52: April | B52: Rabu, 22 | C52: Akun WA Busines dan Biasa di blokir dan bantu follow up user temp, bantu tim cs untuk follow nasabah, Training nasabah (G-meets) | M52: 0 | N52: 0 | O52: 0 | P52: 0 | Q52: 0 | R52: 0 | S52: 0 | T52: 0 | U52: 0 | V52: 0 | W52: 0 | X52: 0 | Y52: 0 | Z52: =SUM(E52,K52,Q52,W52) -> 0 | AA52: =SUM(Y52+Z52) -> 0
A53: April | B53: Selasa, 21 | C53: Akun WA Busines dan Biasa di blokir dan bantu follow up user temp, bantu tim cs untuk follow nasabah, Training nasabah (G-meets) | M53: 0 | N53: 0 | O53: 0 | P53: 0 | Q53: 9 | R53: 0 | S53: 0 | T53: 0 | U53: 0 | V53: 0 | W53: 0 | X53: 0 | Y53: 0 | Z53: =SUM(E53,K53,Q53,W53) -> 9 | AA53: =SUM(Y53+Z53) -> 9
A54: April | B54: Senin, 20 | C54: Akun WA Busines dan Biasa di blokir dan bantu follow up user temp, bantu tim cs untuk follow nasabah, Cara nasabah mitra dari Dm tiktok | M54: 0 | N54: 0 | O54: 0 | P54: 0 | Q54: 0 | R54: 0 | S54: 0 | T54: 0 | U54: 0 | V54: 0 | W54: 0 | X54: 0 | Y54: 0 | Z54: =SUM(E54,K54,Q54,W54) -> 0 | AA54: =SUM(Y54+Z54) -> 0
A55: April | B55: Jumat, 17 | C55: 3 | D55: 1 | E55: 27 | F55: =SUM(C55:D55) -> 4 | G55: 1 | H55: 0 | I55: 0 | J55: 0 | K55: 10 | L55: =SUM(G55:K55) -> 11 | M55: 0 | N55: 0 | O55: 0 | P55: 0 | Q55: 0 | R55: 0 | S55: 0 | T55: 0 | U55: 0 | V55: 0 | W55: 0 | X55: 0 | Y55: =SUM(F55,L55,R55,X55) -> 15 | Z55: =SUM(E55,K55,Q55,W55) -> 37 | AA55: =SUM(Y55+Z55) -> 52
A56: April | B56: Kamis, 16 | C56: 8 | D56: 0 | E56: 43 | F56: =SUM(C56:D56) -> 8 | G56: 2 | H56: 1 | I56: 0 | J56: 0 | K56: 5 | L56: =SUM(G56:J56) -> 3 | M56: 0 | N56: 1 | O56: 0 | P56: 0 | Q56: 0 | R56: =SUM(M56:Q56) -> 1 | S56: 0 | T56: 7 | U56: 0 | V56: 0 | W56: 5 | X56: =SUM(S56:V56) -> 7 | Y56: =SUM(F56,L56,R56,X56) -> 19 | Z56: =SUM(E56,K56,Q56,W56) -> 53 | AA56: =SUM(Y56+Z56) -> 72
A57: April | B57: Rabu, 15 | C57: 3 | D57: 3 | E57: 28 | F57: =SUM(C57:D57) -> 6 | G57: Training karyawan baru | I57: 0 | J57: 0 | K57: 0 | L57: =SUM(G57:J57) -> 0 | M57: 0 | N57: 0 | O57: 0 | P57: 0 | Q57: 1 | R57: =SUM(M57:P57) -> 0 | S57: 0 | T57: 1 | U57: 0 | V57: 0 | W57: 1 | X57: =SUM(S57:V57) -> 1 | Y57: =SUM(F57,L57,R57,X57) -> 7 | Z57: =SUM(E57,K57,Q57,W57) -> 30 | AA57: =SUM(Y57+Z57) -> 37
A58: April | B58: Selasa, 14 | C58: 2 | D58: 5 | E58: 12 | F58: =SUM(C58:D58) -> 7 | G58: 0 | H58: 1 | I58: 0 | J58: 0 | K58: 1 | L58: =SUM(G58:J58) -> 1 | M58: 0 | N58: 1 | O58: 0 | P58: 0 | Q58: 0 | R58: =SUM(M58:P58) -> 1 | S58: 3 | T58: 2 | U58: 0 | V58: 0 | W58: 4 | X58: =SUM(S58:V58) -> 5 | Y58: =SUM(F58,L58,R58,X58) -> 14 | Z58: =SUM(E58,K58,Q58,W58) -> 17 | AA58: =SUM(Y58+Z58) -> 31
A59: April | B59: Jumat, 10 | C59: 4 | D59: 4 | E59: 23 | F59: =SUM(C59:D59) -> 8 | G59: 0 | H59: 0 | I59: 0 | J59: 0 | K59: 5 | L59: =SUM(G59:J59) -> 0 | M59: 0 | N59: 0 | O59: 0 | P59: 0 | Q59: 1 | R59: =SUM(M59:P59) -> 0 | S59: 0 | T59: 0 | U59: 0 | V59: 0 | W59: 0 | X59: 0 | Y59: =SUM(F59,L59,R59) -> 8 | Z59: =SUM(E59,K59,Q59) -> 29 | AA59: =SUM(Y59+Z59) -> 37
A60: April | B60: Kamis, 09 | C60: 6 | D60: 1 | E60: 41 | F60: =SUM(C60:D60) -> 7 | G60: 0 | H60: 1 | I60: 0 | J60: 0 | K60: 1 | L60: =SUM(G60:J60) -> 1 | M60: 0 | N60: 0 | O60: 0 | P60: 0 | Q60: 1 | R60: =SUM(M60:P60) -> 0 | S60: 0 | T60: 0 | U60: 0 | V60: 0 | W60: 0 | X60: 0 | Y60: =SUM(F60,L60,R60) -> 8 | Z60: =SUM(E60,K60,Q60) -> 43 | AA60: =SUM(Y60+Z60) -> 51
A61: April | B61: Rabu, 08 | C61: Training karyawan baru dan bantu case nasabah dan follow up nasabah tahunan | I61: 0 | J61: 0 | K61: 0 | L61: 0 | M61: 0 | N61: 0 | O61: 0 | P61: 0 | Q61: 0 | R61: 0 | S61: 0 | T61: 0 | U61: 0 | V61: 0 | W61: 0 | X61: 0 | Y61: =SUM(F61,L61,R61) -> 0 | Z61: =SUM(E61,K61,Q61) -> 0 | AA61: =SUM(Y61+Z61) -> 0
A62: April | B62: Selasa, 07 | C62: Training karyawan baru dan bantu case nasabah pic dan nasabah call center | I62: 0 | J62: 0 | K62: 0 | L62: 0 | M62: 0 | N62: 0 | O62: 0 | P62: 0 | Q62: 0 | R62: 0 | S62: 0 | T62: 0 | U62: 0 | V62: 0 | W62: 0 | X62: 0 | Y62: =SUM(F62,L62,R62) -> 0 | Z62: =SUM(E62,K62,Q62) -> 0 | AA62: =SUM(Y62+Z62) -> 0
A63: April | B63: Senin, 06 | C63: 13 | D63: 2 | E63: 41 | F63: =SUM(C63:D63) -> 15 | G63: 0 | H63: 0 | I63: 0 | J63: 0 | K63: 0 | L63: =SUM(G63:J63) -> 0 | M63: 0 | N63: 0 | O63: 0 | P63: 0 | Q63: 0 | R63: =SUM(M63:P63) -> 0 | S63: 0 | T63: 0 | U63: 0 | V63: 0 | W63: 0 | X63: 0 | Y63: =SUM(F63,L63,R63) -> 15 | Z63: =SUM(E63,K63,Q63) -> 41 | AA63: =SUM(Y63+Z63) -> 56
A64: April | B64: Kamis,02 | C64: 10 | D64: 0 | E64: 43 | F64: =SUM(C64:D64) -> 10 | G64: 0 | H64: 0 | I64: 0 | J64: 0 | K64: 0 | L64: =SUM(G64:J64) -> 0 | M64: 0 | N64: 0 | O64: 0 | P64: 0 | Q64: 0 | R64: =SUM(M64:P64) -> 0 | S64: 0 | T64: 0 | U64: 0 | V64: 0 | W64: 0 | X64: 0 | Y64: =SUM(F64,L64,R64) -> 10 | Z64: =SUM(E64,K64,Q64) -> 43 | AA64: =SUM(Y64+Z64) -> 53
A65: April | B65: Rabu, 01 | C65: 4 | D65: 4 | E65: 14 | F65: =SUM(C65:D65) -> 8 | G65: 1 | H65: 0 | I65: 0 | J65: 0 | K65: 1 | L65: =SUM(G65:J65) -> 1 | M65: 0 | N65: 0 | O65: 0 | P65: 0 | Q65: 0 | R65: =SUM(M65:P65) -> 0 | S65: 0 | T65: 0 | U65: 0 | V65: 0 | W65: 0 | X65: 0 | Y65: =SUM(F65,L65,R65) -> 9 | Z65: =SUM(E65,K65,Q65) -> 15 | AA65: =SUM(Y65+Z65) -> 24
A66: Maret | B66: Selasa, 31 | C66: 10 | D66: 0 | E66: 23 | F66: =SUM(C66:D66) -> 10 | G66: 2 | H66: 0 | I66: 0 | J66: 0 | K66: 10 | L66: =SUM(G66:J66) -> 2 | M66: 0 | N66: 0 | O66: 0 | P66: 0 | Q66: 0 | R66: =SUM(M66:P66) -> 0 | S66: 0 | T66: 0 | U66: 0 | V66: 0 | W66: 0 | X66: 0 | Y66: =SUM(F66,L66,R66) -> 12 | Z66: =SUM(E66,K66,Q66) -> 33 | AA66: =SUM(Y66+Z66) -> 45
A67: Maret | B67: Senin, 30 | C67: 7 | D67: 4 | E67: 45 | F67: =SUM(C67:D67) -> 11 | G67: 3 | H67: 0 | I67: 0 | J67: 0 | K67: 5 | L67: =SUM(G67:J67) -> 3 | M67: 1 | N67: 0 | O67: 0 | P67: 0 | Q67: 0 | R67: =SUM(M67:P67) -> 1 | S67: 0 | T67: 0 | U67: 0 | V67: 0 | W67: 0 | X67: 0 | Y67: =SUM(F67,L67,R67) -> 15 | Z67: =SUM(E67,K67,Q67) -> 50 | AA67: =SUM(Y67+Z67) -> 65
A68: Maret | B68: Jumat, 27 | C68: 5 | D68: 1 | E68: 45 | F68: =SUM(C68:D68) -> 6 | G68: 1 | H68: 1 | I68: 0 | J68: 0 | K68: 1 | L68: =SUM(G68:J68) -> 2 | M68: 0 | N68: 2 | O68: 0 | P68: 0 | Q68: 1 | R68: =SUM(M68:P68) -> 2 | S68: 0 | T68: 0 | U68: 0 | V68: 0 | W68: 0 | X68: 0 | Y68: =SUM(F68,L68,R68) -> 10 | Z68: =SUM(E68,K68,Q68) -> 47 | AA68: =SUM(Y68+Z68) -> 57
A69: Maret | B69: Kamis, 26 | C69: Akun WA ke Blokir dan Training Karyawan Baru | H69: 0 | I69: 0 | J69: 0 | K69: 0 | L69: 0 | M69: 0 | N69: 0 | O69: 0 | P69: 0 | Q69: 0 | R69: 0 | S69: 0 | T69: 0 | U69: 0 | V69: 0 | W69: 0 | X69: 0 | Y69: =SUM(D69,J69,P69) -> 0 | Z69: =SUM(E69,K69,Q69) -> 0 | AA69: =SUM(Y69+Z69) -> 0
A70: Maret | B70: Rabu, 25 | C70: Akun WA ke Blokir dan Training Karyawan Baru | H70: 0 | I70: 0 | J70: 0 | K70: 0 | L70: 0 | M70: 0 | N70: 0 | O70: 0 | P70: 0 | Q70: 0 | R70: 0 | S70: 0 | T70: 0 | U70: 0 | V70: 0 | W70: 0 | X70: 0 | Y70: =SUM(D70,J70,P70) -> 0 | Z70: =SUM(E70,K70,Q70) -> 0 | AA70: =SUM(Y70+Z70) -> 0
A71: Maret | B71: Selasa, 24 | C71: 4 | D71: 2 | E71: 48 | F71: =SUM(C71:D71) -> 6 | G71: 1 | H71: 0 | I71: 0 | J71: 0 | K71: 0 | L71: =SUM(G71:J71) -> 1 | M71: 0 | N71: 0 | O71: 0 | P71: 0 | Q71: 0 | R71: =SUM(M71:P71) -> 0 | S71: 0 | T71: 0 | U71: 0 | V71: 0 | W71: 0 | X71: 0 | Y71: =SUM(F71,L71,R71) -> 7 | Z71: =SUM(E71,K71,Q71) -> 48 | AA71: =SUM(Y71+Z71) -> 55
A72: Maret | B72: Senin, 23 | C72: 1 | D72: 3 | E72: 27 | F72: =SUM(C72:D72) -> 4 | G72: 1 | H72: 0 | I72: 0 | J72: 0 | K72: 3 | L72: =SUM(G72:J72) -> 1 | M72: 0 | N72: 0 | O72: 0 | P72: 0 | Q72: 0 | R72: =SUM(M72:P72) -> 0 | S72: 0 | T72: 0 | U72: 0 | V72: 0 | W72: 0 | X72: 0 | Y72: =SUM(F72,L72,R72) -> 5 | Z72: =SUM(E72,K72,Q72) -> 30 | AA72: =SUM(Y72+Z72) -> 35
A73: Maret | B73: Rabu, 18 | C73: 9 | D73: 2 | E73: 27 | F73: =SUM(C73:D73) -> 11 | G73: 2 | H73: 0 | I73: 0 | J73: 0 | K73: 1 | L73: =SUM(G73:J73) -> 2 | M73: 0 | N73: 0 | O73: 0 | P73: 0 | Q73: 0 | R73: =SUM(M73:P73) -> 0 | S73: 0 | T73: 0 | U73: 0 | V73: 0 | W73: 0 | X73: 0 | Y73: =SUM(F73,L73,R73) -> 13 | Z73: =SUM(E73,K73,Q73) -> 28 | AA73: =SUM(Y73+Z73) -> 41
A74: Maret | B74: Selasa, 17 | C74: 9 | D74: 8 | E74: 25 | F74: =SUM(C74:D74) -> 17 | G74: 1 | H74: 0 | I74: 0 | J74: 0 | K74: 3 | L74: =SUM(G74:J74) -> 1 | M74: 0 | N74: 0 | O74: 0 | P74: 0 | Q74: 0 | R74: =SUM(M74:P74) -> 0 | S74: 0 | T74: 0 | U74: 0 | V74: 0 | W74: 0 | X74: 0 | Y74: =SUM(F74,L74,R74) -> 18 | Z74: =SUM(E74,K74,Q74) -> 28 | AA74: =SUM(Y74+Z74) -> 46
A75: Maret | B75: Jumat, 13 | C75: 6 | D75: 2 | E75: 4 | F75: =SUM(C75:D75) -> 8 | G75: 1 | H75: 2 | I75: 0 | J75: 0 | K75: 0 | L75: =SUM(G75:J75) -> 3 | M75: 1 | N75: 0 | O75: 0 | P75: 0 | Q75: 0 | R75: =SUM(M75:P75) -> 1 | S75: 0 | T75: 0 | U75: 0 | V75: 0 | W75: 0 | X75: 0 | Y75: =SUM(F75,L75,R75) -> 12 | Z75: =SUM(E75,K75,Q75) -> 4 | AA75: =SUM(Y75+Z75) -> 16
A76: Maret | B76: Kamis, 12 | C76: 3 | D76: 2 | E76: 38 | F76: =SUM(C76:D76) -> 5 | G76: 0 | H76: 0 | I76: 0 | J76: 0 | K76: 0 | L76: 0 | M76: 0 | N76: 0 | O76: 0 | P76: 0 | Q76: 0 | R76: 0 | S76: 0 | T76: 0 | U76: 0 | V76: 0 | W76: 0 | X76: 0 | Y76: =SUM(F76,L76,R76) -> 5 | Z76: =SUM(E76,K76,Q76) -> 38 | AA76: =SUM(Y76+Z76) -> 43
A77: Maret | B77: Rabu, 11 | C77: 4 | D77: 4 | E77: 13 | F77: =SUM(C77:D77) -> 8 | G77: 0 | H77: 1 | I77: 0 | J77: 0 | K77: 0 | L77: =SUM(G77:J77) -> 1 | M77: 0 | N77: 0 | O77: 0 | P77: 0 | Q77: 0 | R77: 0 | S77: 0 | T77: 0 | U77: 0 | V77: 0 | W77: 0 | X77: 0 | Y77: =SUM(F77,L77,R77) -> 9 | Z77: =SUM(E77,K77,Q77) -> 13 | AA77: =SUM(Y77+Z77) -> 22
A78: Maret | B78: Selasa, 10 | C78: 8 | D78: 2 | E78: 63 | F78: =SUM(C78:D78) -> 10 | G78: 1 | H78: 0 | I78: 0 | J78: 0 | K78: 0 | L78: =SUM(G78:J78) -> 1 | M78: 0 | N78: 0 | O78: 0 | P78: 0 | Q78: 0 | R78: 0 | S78: 0 | T78: 0 | U78: 0 | V78: 0 | W78: 0 | X78: 0 | Y78: =SUM(F78,L78,R78) -> 11 | Z78: =SUM(E78,K78,Q78) -> 63 | AA78: =SUM(Y78+Z78) -> 74
A79: Maret | B79: Selasa, 09 | C79: 8 | D79: 2 | E79: 25 | F79: =SUM(C79:D79) -> 10 | G79: 1 | H79: 0 | I79: 0 | J79: 0 | K79: 0 | L79: =SUM(G79:J79) -> 1 | M79: 0 | N79: 0 | O79: 0 | P79: 0 | Q79: 0 | R79: =SUM(M79:P79) -> 0 | S79: 0 | T79: 0 | U79: 0 | V79: 0 | W79: 0 | X79: 0 | Y79: =SUM(F79,L79,R79) -> 11 | Z79: =SUM(E79,K79,Q79) -> 25 | AA79: =SUM(Y79+Z79) -> 36
A80: Maret | B80: Jumat, 06 | C80: 10 | D80: 1 | E80: 22 | F80: =SUM(C80:D80) -> 11 | G80: 0 | H80: 1 | I80: 0 | J80: 0 | K80: 0 | L80: =SUM(G80:J80) -> 1 | M80: 0 | N80: 0 | O80: 0 | P80: 0 | Q80: 0 | R80: =SUM(M80:P80) -> 0 | S80: 0 | T80: 0 | U80: 0 | V80: 0 | W80: 0 | X80: 0 | Y80: =SUM(F80,L80,R80) -> 12 | Z80: =SUM(E80,K80,Q80) -> 22 | AA80: =SUM(Y80+Z80) -> 34
A81: Maret | B81: Kamis, 05 | C81: 9 | D81: 1 | E81: 27 | F81: =SUM(C81:D81) -> 10 | G81: 1 | H81: 1 | I81: 0 | J81: 0 | K81: 6 | L81: =SUM(G81:J81) -> 2 | M81: 0 | N81: 0 | O81: 0 | P81: 0 | Q81: 0 | R81: =SUM(M81:P81) -> 0 | S81: 0 | T81: 0 | U81: 0 | V81: 0 | W81: 0 | X81: 0 | Y81: =SUM(F81,L81,R81) -> 12 | Z81: =SUM(E81,K81,Q81) -> 33 | AA81: =SUM(Y81+Z81) -> 45
A82: Maret | B82: Rabu. 04 | C82: 8 | D82: 2 | E82: 29 | F82: =SUM(C82:E82) -> 39 | G82: 0 | H82: 0 | I82: 0 | J82: 0 | K82: 4 | L82: =SUM(G82:J82) -> 0 | M82: 0 | N82: 0 | O82: 0 | P82: 0 | Q82: 0 | R82: =SUM(M82:P82) -> 0 | S82: 0 | T82: 0 | U82: 0 | V82: 0 | W82: 0 | X82: 0 | Y82: =SUM(F82,L82,R82) -> 39 | Z82: =SUM(E82,K82,Q82) -> 33 | AA82: =SUM(Y82+Z82) -> 72
A83: Maret | B83: Selasa,02 | C83: 10 | D83: 4 | E83: 42 | F83: =SUM(C83:D83) -> 14 | G83: 0 | H83: 1 | J83: 0 | K83: 3 | L83: =SUM(G83:J83) -> 1 | M83: 0 | N83: 0 | O83: 0 | P83: 0 | Q83: 0 | R83: =SUM(M83:P83) -> 0 | S83: 0 | T83: 0 | U83: 0 | V83: 0 | W83: 0 | X83: 0 | Y83: =SUM(F83,L83,R83) -> 15 | Z83: =SUM(E83,K83,Q83) -> 45 | AA83: =SUM(Y83+Z83) -> 60
A84: Maret | B84: Senin, 01 | C84: 1 | D84: 4 | E84: 23 | F84: =SUM(C84:E84) -> 28 | G84: 2 | H84: 2 | J84: 0 | K84: 3 | L84: =SUM(G84:J84) -> 4 | M84: 0 | N84: 0 | O84: 0 | P84: 0 | Q84: 0 | R84: =SUM(M84:P84) -> 0 | S84: 0 | T84: 0 | U84: 0 | V84: 0 | W84: 0 | X84: 0 | Y84: =SUM(F84,L84,R84) -> 32 | Z84: =SUM(E84,K84,Q84) -> 26 | AA84: =SUM(Y84+Z84) -> 58
A85: Februari | B85: 46072 | C85: 9 | D85: 3 | E85: 28 | F85: =SUM(C85:D85) -> 12 | G85: 1 | H85: 1 | I85: 0 | J85: 0 | K85: 6 | L85: =SUM(G85:J85) -> 2 | M85: 0 | N85: 0 | O85: 0 | P85: 0 | Q85: 0 | R85: =SUM(M85:P85) -> 0 | S85: 0 | T85: 0 | U85: 0 | V85: 0 | W85: 0 | X85: 0 | Y85: =SUM(F85,L85,R85) -> 14 | Z85: =SUM(E85,K85,Q85) -> 34 | AA85: =SUM(Y85+Z85) -> 48
A86: Februari | B86: 46071 | C86: 4 | D86: 5 | E86: 5 | F86: =SUM(C86:D86) -> 9 | G86: 1 | H86: 1 | I86: 0 | J86: 1 | K86: 0 | L86: =SUM(G86:K86) -> 3 | M86: 1 | N86: 0 | O86: 0 | P86: 0 | Q86: 0 | R86: =SUM(M86:P86) -> 1 | S86: 0 | T86: 0 | U86: 0 | V86: 0 | W86: 0 | X86: 0 | Y86: =SUM(F86,L86,R86) -> 13 | Z86: =SUM(E86,K86,Q86) -> 5 | AA86: =SUM(Y86+Z86) -> 18
A87: Februari | B87: 46066 | C87: 4 | D87: 4 | E87: 17 | F87: =SUM(C87:D87) -> 8 | G87: 1 | H87: 2 | I87: 0 | J87: 0 | K87: 7 | L87: =SUM(G87:J87) -> 3 | M87: 0 | N87: 0 | O87: 0 | P87: 0 | Q87: 0 | R87: =SUM(M87:P87) -> 0 | S87: 0 | T87: 0 | U87: 0 | V87: 0 | W87: 0 | X87: 0 | Y87: =SUM(F87,L87,R87) -> 11 | Z87: =SUM(E87,K87,Q87) -> 24 | AA87: =SUM(Y87+Z87) -> 35
A88: Februari | B88: 46065 | C88: 0 | D88: 5 | E88: 23 | F88: =SUM(C88:D88) -> 5 | G88: 0 | H88: 2 | I88: 0 | J88: 1 | K88: 0 | L88: =SUM(G88:J88) -> 3 | M88: 0 | N88: 1 | O88: 0 | P88: 0 | Q88: 0 | R88: =SUM(M88:P88) -> 1 | S88: 0 | T88: 0 | U88: 0 | V88: 0 | W88: 0 | X88: 0 | Y88: =SUM(F88,L88,R88) -> 9 | Z88: =SUM(E88,K88,Q88) -> 23 | AA88: =SUM(Y88+Z88) -> 32
A89: Februari | B89: 46064 | C89: 4 | D89: 4 | E89: 28 | F89: =SUM(C89:D89) -> 8 | G89: 2 | H89: 0 | I89: 0 | J89: 0 | K89: 8 | L89: =SUM(G89:J89) -> 2 | M89: 0 | N89: 0 | O89: 0 | P89: 0 | Q89: 0 | R89: =SUM(M89:P89) -> 0 | S89: 0 | T89: 0 | U89: 0 | V89: 0 | W89: 0 | X89: 0 | Y89: =SUM(F89,L89,R89) -> 10 | Z89: =SUM(E89,K89,Q89) -> 36 | AA89: =SUM(Y89+Z89) -> 46
A90: Februari | B90: 46063 | C90: 7 | D90: 5 | E90: 14 | F90: =SUM(C90:D90) -> 12 | G90: 0 | H90: 0 | I90: 0 | J90: 0 | K90: 10 | L90: =SUM(G90:J90) -> 0 | M90: 0 | N90: 1 | O90: 0 | P90: 0 | Q90: 0 | R90: =SUM(M90:P90) -> 1 | S90: 0 | T90: 0 | U90: 0 | V90: 0 | W90: 0 | X90: 0 | Y90: =SUM(F90,L90,R90) -> 13 | Z90: =SUM(E90,K90,Q90) -> 24 | AA90: =SUM(Y90+Z90) -> 37
A91: Februari | B91: 46062 | C91: 3 | D91: 3 | E91: 4 | F91: =SUM(C91:D91) -> 6 | G91: 1 | H91: 1 | I91: 0 | J91: 0 | K91: 11 | L91: =SUM(G91:J91) -> 2 | M91: 0 | N91: 0 | O91: 0 | P91: 0 | Q91: 0 | R91: =SUM(M91:P91) -> 0 | S91: 0 | T91: 0 | U91: 0 | V91: 0 | W91: 0 | X91: 0 | Y91: =SUM(F91,L91,R91) -> 8 | Z91: =SUM(E91,K91,Q91) -> 15 | AA91: =SUM(Y91+Z91) -> 23
A92: Februari | B92: 46059 | C92: 2 | D92: 7 | E92: 12 | F92: =SUM(C92:D92) -> 9 | G92: 1 | H92: 1 | I92: 0 | J92: 0 | K92: 1 | L92: =SUM(G92:K92) -> 3 | M92: 0 | N92: 0 | O92: 0 | P92: 0 | Q92: 0 | R92: =SUM(M92:P92) -> 0 | S92: 0 | T92: 0 | U92: 0 | V92: 0 | W92: 0 | X92: 0 | Y92: =SUM(F92,L92,R92) -> 12 | Z92: =SUM(E92,K92,Q92) -> 13 | AA92: =SUM(Y92+Z92) -> 25
A93: Februari | B93: 46058 | C93: 4 | D93: 10 | E93: 9 | F93: =SUM(C93:D93) -> 14 | G93: 2 | H93: 2 | I93: 0 | J93: 0 | K93: 15 | L93: =SUM(G93:J93) -> 4 | M93: 0 | N93: 0 | O93: 0 | P93: 0 | Q93: 0 | R93: =SUM(M93:P93) -> 0 | S93: 0 | T93: 0 | U93: 0 | V93: 0 | W93: 0 | X93: 0 | Y93: =SUM(F93,L93,R93) -> 18 | Z93: =SUM(E93,K93,Q93) -> 24 | AA93: =SUM(Y93+Z93) -> 42
A94: Februari | B94: 46057 | C94: 4 | D94: 8 | E94: 0 | F94: =SUM(C94:E94) -> 12 | G94: 2 | H94: 1 | I94: 0 | J94: 0 | K94: 7 | L94: =SUM(G94:J94) -> 3 | M94: 0 | N94: 1 | O94: 0 | P94: 0 | Q94: 0 | R94: =SUM(M94:P94) -> 1 | S94: 0 | T94: 0 | U94: 0 | V94: 0 | W94: 0 | X94: 0 | Y94: =SUM(F94,L94,R94) -> 16 | Z94: =SUM(E94,K94,Q94) -> 7 | AA94: =SUM(Y94+Z94) -> 23
A95: Februari | B95: 46056 | C95: 7 | D95: 3 | E95: 28 | F95: =SUM(C95:D95) -> 10 | G95: 0 | H95: 1 | I95: 0 | J95: 0 | K95: 7 | L95: =SUM(G95:J95) -> 1 | M95: 1 | N95: 0 | O95: 0 | P95: 0 | Q95: 1 | R95: =SUM(M95:P95) -> 1 | S95: 0 | T95: 0 | U95: 0 | V95: 0 | W95: 0 | X95: 0 | Y95: =SUM(F95,L95,R95) -> 12 | Z95: =SUM(E95,K95,Q95) -> 36 | AA95: =SUM(Y95+Z95) -> 48
A96: Februari | B96: 46055 | C96: 3 | D96: 0 | E96: 12 | F96: =SUM(C96:D96) -> 3 | G96: 0 | H96: 0 | I96: 0 | J96: 0 | K96: 0 | L96: =SUM(G96:J96) -> 0 | M96: 1 | N96: 0 | O96: 0 | P96: 0 | Q96: 0 | R96: =SUM(M96:P96) -> 1 | S96: 0 | T96: 0 | U96: 0 | V96: 0 | W96: 0 | X96: 0 | Y96: =SUM(F96,L96,R96) -> 4 | Z96: =SUM(E96,K96,Q96) -> 12 | AA96: =SUM(Y96+Z96) -> 16
A97: Januari | B97: 46024 | C97: Bantu kendala dan komplain nasabah mengenai aplikasi versi terbaru | S97: 0 | T97: 0 | U97: 0 | V97: 0 | W97: 0 | X97: 0 | AA97: =SUM(Y97+Z97) -> 0
A98: Januari | B98: 46027 | C98: Bantu kendala dan komplain nasabah mengenai aplikasi versi terbaru | S98: 0 | T98: 0 | U98: 0 | V98: 0 | W98: 0 | X98: 0 | AA98: =SUM(Y98+Z98) -> 0
A99: Januari | B99: 46028 | C99: 6 | D99: 0 | E99: 9 | F99: =SUM(C99:D99) -> 6 | G99: 1 | H99: 0 | I99: 0 | J99: 0 | K99: 0 | L99: =SUM(G99:J99) -> 1 | M99: 0 | N99: 0 | O99: 0 | P99: 0 | Q99: 0 | R99: =SUM(M99:P99) -> 0 | S99: 0 | T99: 0 | U99: 0 | V99: 0 | W99: 0 | X99: 0 | Y99: =SUM(F99,L99,R99) -> 7 | Z99: =SUM(E99,K99,Q99) -> 9 | AA99: =SUM(Y99+Z99) -> 16
A100: Januari | B100: 46029 | C100: 9 | D100: 2 | E100: 10 | F100: =SUM(C100:D100) -> 11 | G100: 0 | H100: 1 | I100: 0 | J100: 1 | K100: 3 | L100: =SUM(G100:J100) -> 2 | M100: 0 | N100: 1 | O100: 0 | P100: 0 | Q100: 0 | R100: =SUM(M100:P100) -> 1 | S100: 0 | T100: 0 | U100: 0 | V100: 0 | W100: 0 | X100: 0 | Y100: =SUM(F100,L100,R100) -> 14 | Z100: =SUM(E100,K100,Q100) -> 13 | AA100: =SUM(Y100+Z100) -> 27
A101: Januari | B101: 46030 | C101: 5 | D101: 2 | E101: 17 | F101: =SUM(C101:D101) -> 7 | G101: 0 | H101: 0 | I101: 0 | J101: 0 | K101: 0 | L101: =SUM(G101:J101) -> 0 | M101: 0 | N101: 0 | O101: 0 | P101: 0 | Q101: 0 | R101: o | S101: 0 | T101: 0 | U101: 0 | V101: 0 | W101: 0 | X101: 0 | Y101: =SUM(F101,L101,R101) -> 7 | Z101: =SUM(E101,K101,Q101) -> 17 | AA101: =SUM(Y101+Z101) -> 24
A102: Januari | B102: 46031 | C102: 1 | D102: 1 | E102: 13 | F102: =SUM(C102:D102) -> 2 | G102: 0 | H102: 0 | I102: 0 | J102: 0 | K102: 0 | L102: =SUM(G102:J102) -> 0 | M102: 0 | N102: 0 | O102: 0 | P102: 0 | Q102: 0 | R102: =SUM(M102:P102) -> 0 | S102: 0 | T102: 0 | U102: 0 | V102: 0 | W102: 0 | X102: 0 | Y102: =SUM(F102,L102,R102) -> 2 | Z102: =SUM(E102,K102,Q102) -> 13 | AA102: =SUM(Y102+Z102) -> 15
...

Sheet List Mitra
A1: PT. PIPOSMART DIGITAL INDONESIA
A2: DATA LIST MITRA PIPOSMART INDONESIA
A3: Kategori Mitra | B3: PIC Nasabah | C3: Bulan Terdaftar | D3: Tahun | E3: Kode Owner | F3: Owner Mitra | G3: Nama Brand / Nama Badan Usaha | H3: No. Telp | I3: Email Mitra | J3: No Rekening | K3: Bank | L3: Kategori Mitra | M3: Kota/Provinsi | N3: Alamat | O3: Total Akuisisi Referal | P3: Total Referral | Q3: Jan | R3: Feb | S3: Mar | T3: Apr | U3: Mei | V3: Jun | W3: Jul | X3: Aug | Y3: Sep | Z3: Okt | AA3: Nov | AB3: Des
A4: AFILIASI (Perlengkapan Ex. Mesin, Rak, Dll) | B4: PBGC 1 - Lidya | C4: Januari | D4: 2025 | F4: KG TEKNIK BATAM | G4: KG TEKNIK BATAM | H4: 081364050429 | I4: amiraizati01@gmail.com | J4: 1090019010180 | K4: Mandiri | L4: Mitra Corporated | M4: Kota Batam/Kepulauan Riau | N4: Ruko Puri Legenda Blok C2 No 02-03 Batam Centre | O4: ='Kelolaan Mitra'!H180 -> 3 | P4: =SUM(Q4:AB4) -> 7 | Q4: 3 | R4: 3 | S4: 0 | T4: 0 | U4: 1
A5: AFILIASI (Perlengkapan Ex. Mesin, Rak, Dll) | B5: PBGC 1 - Lidya | C5: Nihil | D5: 2024 | F5: Asep Taufik Hidayat | G5: mesincucilaundry.com | H5: 081213970585 | I5: chisa.qb@gmail.com | J5: 6880445471 | K5: BCA | L5: Mitra Referral | M5: Jawa Barat | N5: Perumahan Cibarusah Indah Blok e23 No.4 Cibarusah Kota Kab. Bekasi Patokan sebelum masuk perumahan ada gapura dekat dengan mesjid perahu, Kec. Cibarusah, Jawa Barat 17340 | O5: ='Kelolaan Mitra'!H169 -> 87 | P5: =SUM(Q5:AB5) -> 13 | Q5: 2 | R5: 4 | S5: 2 | T5: 1 | U5: 2 | V5: 2
A6: FRANCHISE (Jual Brand Usaha) | B6: PBGC 1 - Lidya | C6: November | D6: 2024 | E6: 11165 | F6: Ayu Widyasari primanda | G6: HAWP LAUNDRY | H6: 082197946038 | L6: Mitra Corporated | M6: Depok | N6: jln kemang swatama, gg H Tarin no 28, Kel/Kec Sukmajaya Depok | O6: ='Kelolaan Mitra'!H9 -> 1 | P6: =SUM(Q6:AB6) -> 0 | Q6: =SUM(R6:AC6) -> 0 | R6: =SUM(S6:AD6) -> 0 | S6: =SUM(T6:AE6) -> 0 | T6: =SUM(U6:AF6) -> 0 | U6: =SUM(V6:AG6) -> 0
A7: AFILIASI (Perlengkapan Ex. Mesin, Rak, Dll) | B7: PBGC 1 - Lidya | C7: Nihil | D7: 2024 | F7: Nurul Fathiyaturrohmah | G7: PT. Alfatih Tech Utama | H7: 089662321780 | I7: hi.fathiya12@gmail.com | J7: 4212659928 | K7: BCA | L7: Mitra Referral | M7: Jakarta Selatan | N7: Jl. Komp. Desa Putera No.1, RT.7/RW.5, Srengseng Sawah, Kec. Jagakarsa, Kota Jakarta Selatan, DKI Jakarta | O7: ='Kelolaan Mitra'!H58 -> 3 | P7: =SUM(Q7:AB7) -> 0 | Q7: =SUM(R7:AC7) -> 0 | R7: =SUM(S7:AD7) -> 0 | S7: =SUM(T7:AE7) -> 0 | T7: =SUM(U7:AF7) -> 0 | U7: =SUM(V7:AG7) -> 0
A8: AFILIASI (Perlengkapan Ex. Mesin, Rak, Dll) | B8: PBGC 1 - Lidya | C8: Nihil | D8: 2024 | F8: nurlasmiatun | G8: MIKAIL ELECTRONIK | H8: 081211542249 | I8: nur131087@gmail.com | J8: 708501008072539 | K8: BRI | L8: Mitra Referral | M8: Jakarta Selatan | N8: Jl. Persatuan Amal Mulia No. 25b, RT.5/RW.13, Grogol Sel., Jakarta, Kota Jakarta Selatan | O8: ='Kelolaan Mitra'!H65 -> 6 | P8: =SUM(Q8:AB8) -> 0 | Q8: =SUM(R8:AC8) -> 0 | R8: =SUM(S8:AD8) -> 0 | S8: =SUM(T8:AE8) -> 0 | T8: =SUM(U8:AF8) -> 0 | U8: =SUM(V8:AG8) -> 0
A9: FRANCHISE (Jual Brand Usaha) | B9: PBGC 1 - Lidya | C9: Nihil | D9: 2024 | E9: 6926 | F9: Leny | G9: Get Laundry RMJ | H9: 087777139459 | L9: Mitra Referral | M9: Serpong | N9: Jl. Ciater Rt 004 / Rw 022 Kel. Rawabuntu Kec. Serpong | O9: ='Kelolaan Mitra'!H7 -> 2 | P9: =SUM(Q9:AB9) -> 0 | Q9: =SUM(R9:AC9) -> 0 | R9: =SUM(S9:AD9) -> 0 | S9: =SUM(T9:AE9) -> 0 | T9: =SUM(U9:AF9) -> 0 | U9: =SUM(V9:AG9) -> 0
A10: REFERAL (Berlangganan) | B10: PBGC 1 - Lidya | C10: Nihil | D10: 2024 | E10: 4181 | F10: DIGNITY SINAGA | G10: DIGNITY LAUNDRY | H10: 0811620080 | L10: Mitra Referral | M10: Tangerang | N10: Tanggerang, Cikokol, Tangerang, Banten | O10: ='Kelolaan Mitra'!H31 -> 6 | P10: =SUM(Q10:AB10) -> 0 | Q10: =SUM(R10:AC10) -> 0 | R10: =SUM(S10:AD10) -> 0 | S10: =SUM(T10:AE10) -> 0 | T10: =SUM(U10:AF10) -> 0 | U10: =SUM(V10:AG10) -> 0
A11: REFERAL (Berlangganan) | B11: PBGC 1 - Lidya | C11: Nihil | D11: 2024 | E11: 4723 | F11: Budi Santo | G11: Sahabat Laundry | H11: 082174637062 | L11: Mitra Referral | M11: Jawa Barat | N11: jln pertokoan stasiun cikampek nmr 2, Kab. Karawang, Jawa Barat | O11: ='Kelolaan Mitra'!H22 -> 6 | P11: =SUM(Q11:AB11) -> 0 | Q11: =SUM(R11:AC11) -> 0 | R11: =SUM(S11:AD11) -> 0 | S11: =SUM(T11:AE11) -> 0 | T11: =SUM(U11:AF11) -> 0 | U11: =SUM(V11:AG11) -> 0
A12: REFERAL (Berlangganan) | B12: PBGC 1 - Lidya | C12: Nihil | D12: 2024 | E12: 7479 | F12: Farhan Alfatan | G12: juragan laundry | H12: 082125008245 | L12: Mitra Referral | M12: Jawa Barat | N12: kp.krajan1 ds.jayamukti kec.banyusari kab.karawang | O12: ='Kelolaan Mitra'!H15 -> 1 | P12: =SUM(Q12:AB12) -> 0 | Q12: =SUM(R12:AC12) -> 0 | R12: =SUM(S12:AD12) -> 0 | S12: =SUM(T12:AE12) -> 0 | T12: =SUM(U12:AF12) -> 0 | U12: =SUM(V12:AG12) -> 0
A13: REFERAL (Berlangganan) | B13: PBGC 1 - Lidya | C13: Nihil | D13: 2024 | E13: 7801 | F13: Anita Yulianti Asgar | G13: Aroma Palopo / NETTO LAUNDRY | H13: 08114220487 | L13: Mitra Referral | M13: Palopo | N13: Kota Palopo, Sulawesi Selatan | O13: ='Kelolaan Mitra'!H38 -> 2 | P13: =SUM(Q13:AB13) -> 0 | Q13: =SUM(R13:AC13) -> 0 | R13: =SUM(S13:AD13) -> 0 | S13: =SUM(T13:AE13) -> 0 | T13: =SUM(U13:AF13) -> 0 | U13: =SUM(V13:AG13) -> 0
A14: REFERAL (Berlangganan) | B14: PBGC 1 - Lidya | C14: Nihil | D14: 2024 | E14: 11515 | F14: APRILIA RAHMAWATI | G14: SHARENA LAUNDRY | H14: 085210108123 | L14: Mitra Referral | M14: Jakarta Timur | N14: JL H.R ISMAIL RT 08 RW 03 JATINEGARA CAKUNG JAKARTA TIMUR | O14: ='Kelolaan Mitra'!H40 -> 1 | P14: =SUM(Q14:AB14) -> 0 | Q14: =SUM(R14:AC14) -> 0 | R14: =SUM(S14:AD14) -> 0 | S14: =SUM(T14:AE14) -> 0 | T14: =SUM(U14:AF14) -> 0 | U14: =SUM(V14:AG14) -> 0
A15: REFERAL (Berlangganan) | B15: PBGC 1 - Lidya | C15: Nihil | D15: 2024 | E15: 1522 | F15: Sugiana | G15: Indah Express Laundry | H15: 082147446756 | L15: Mitra Referral | M15: Denpasar Selatan | N15: Danau tempe no.35 sanur kecamatan Denpasar Selatan | O15: ='Kelolaan Mitra'!H11 -> 1 | P15: =SUM(Q15:AB15) -> 0 | Q15: =SUM(R15:AC15) -> 0 | R15: =SUM(S15:AD15) -> 0 | S15: =SUM(T15:AE15) -> 0 | T15: =SUM(U15:AF15) -> 0 | U15: =SUM(V15:AG15) -> 0
A16: REFERAL (Berlangganan) | B16: PBGC 1 - Lidya | C16: Nihil | D16: 2024 | E16: 6058 | F16: Citra Halim | G16: Citra Laundry | H16: 08174885266 | L16: Mitra Referral | M16: Jakarta Barat | N16: jl. tanjung duren timur raya gang mandalika, kota Jakarta Barat, Dki Jakarta | O16: ='Kelolaan Mitra'!H13 -> 1 | P16: =SUM(Q16:AB16) -> 0 | Q16: =SUM(R16:AC16) -> 0 | R16: =SUM(S16:AD16) -> 0 | S16: =SUM(T16:AE16) -> 0 | T16: =SUM(U16:AF16) -> 0 | U16: =SUM(V16:AG16) -> 0
A17: REFERAL (Berlangganan) | B17: PBGC 1 - Lidya | C17: Nihil | D17: 2024 | E17: 7251 | F17: Yogi Lumban Tobing | G17: BAR Laundry | H17: 081264114427 | L17: Mitra Referral | M17: Pematang siantar | N17: Jl. Sisingamangaraja No.250, Siantar Utara, Kota Pematang Siantar, Sumatera Utara | O17: ='Kelolaan Mitra'!H24 -> 1 | P17: =SUM(Q17:AB17) -> 0 | Q17: =SUM(R17:AC17) -> 0 | R17: =SUM(S17:AD17) -> 0 | S17: =SUM(T17:AE17) -> 0 | T17: =SUM(U17:AF17) -> 0 | U17: =SUM(V17:AG17) -> 0
A18: REFERAL (Berlangganan) | B18: PBGC 1 - Lidya | C18: November | D18: 2024 | E18: 9441 | F18: Kasih Laundry Siantar | G18: Kasih Laundry | H18: 0859106762310 | L18: Mitra Referral | M18: Pematang Siantar | N18: Jl.Sisingamangaraja, No.15, Bukit Sofa, Siantar Sitalasari | O18: ='Kelolaan Mitra'!H33 -> 1 | P18: =SUM(Q18:AB18) -> 0 | Q18: =SUM(R18:AC18) -> 0 | R18: =SUM(S18:AD18) -> 0 | S18: =SUM(T18:AE18) -> 0 | T18: =SUM(U18:AF18) -> 0 | U18: =SUM(V18:AG18) -> 0
A19: REFERAL (Berlangganan) | B19: PBGC 1 - Lidya | C19: Januari | D19: 2025 | E19: 13944 | F19: Orlando Manalu | G19: LAUNDRY KITA | H19: 085163695628 | L19: Mitra Referral | M19: Simalungun | N19: Jl. Asahan,KM 3,5. Pematang Simalungun, Kec. Siantar, Kabupaten Simalungun, Sumatera Utara 21151(Komplek Graha Asahan Gold) | O19: ='Kelolaan Mitra'!H42 -> 1 | P19: =SUM(Q19:AB19) -> 0 | Q19: =SUM(R19:AC19) -> 0 | R19: =SUM(S19:AD19) -> 0 | S19: =SUM(T19:AE19) -> 0 | T19: =SUM(U19:AF19) -> 0 | U19: =SUM(V19:AG19) -> 0
A20: REFERAL (Berlangganan) | B20: PBGC 1 - Lidya | C20: Januari | D20: 2025 | E20: 10563 | F20: Abi Hafidz | G20: AZZAHRO LAUNDRY ٣٨ CIKANDE | H20: 085217955565 | L20: Mitra Referral | M20: Banten | N20: kp.Gegong burung Rt 02/02 Desa situterate Kec. Cikande Kabupaten SERANG BANTEN kode pos 42186 | O20: ='Kelolaan Mitra'!H44 -> 1 | P20: =SUM(Q20:AB20) -> 0 | Q20: =SUM(R20:AC20) -> 0 | R20: =SUM(S20:AD20) -> 0 | S20: =SUM(T20:AE20) -> 0 | T20: =SUM(U20:AF20) -> 0 | U20: =SUM(V20:AG20) -> 0
A21: REFERAL (Berlangganan) | B21: PBGC 1 - Lidya | C21: Januari | D21: 2025 | E21: 8381 | F21: Moko purnomo | G21: laundry bloosom | H21: 082168508148 | L21: Mitra Referral | M21: DI Yogyakarta | N21: Jl. Mancasan indah III no.2 samping bobobop (belakang parkiran motor FE UII | O21: ='Kelolaan Mitra'!H46 -> 1 | P21: =SUM(Q21:AB21) -> 0 | Q21: =SUM(R21:AC21) -> 0 | R21: =SUM(S21:AD21) -> 0 | S21: =SUM(T21:AE21) -> 0 | T21: =SUM(U21:AF21) -> 0 | U21: =SUM(V21:AG21) -> 0
A22: REFERAL (Berlangganan) | B22: PBGC 1 - Lidya | C22: Februari | D22: 2025 | E22: 14464 | F22: Kilo Laundry | G22: Kilo Laundry Singosari | H22: 087866932707 | L22: Mitra Referral | M22: Jawa TImur | N22: Jl raya mondoroko, mondoroko, singosari, kec. singosari, kabupaten malang, jawa timur 65153 | O22: ='Kelolaan Mitra'!H35 -> 1 | P22: =SUM(Q22:AB22) -> 0 | Q22: =SUM(R22:AC22) -> 0 | R22: =SUM(S22:AD22) -> 0 | S22: =SUM(T22:AE22) -> 0 | T22: =SUM(U22:AF22) -> 0 | U22: =SUM(V22:AG22) -> 0
A23: REFERAL (Berlangganan) | B23: PBGC 1 - Lidya | C23: Februari | D23: 2025 | E23: 1431 | F23: Muksin Mujih | G23: TiaNova Laundry | H23: 085888567858 | L23: Mitra Referral | M23: Banten | N23: Jl.Japos Raya,kp.Pondok Jati Utama RT4/3 Jurang Mangu Barat,Pondok Aren,Tangsel | O23: 1 | P23: =SUM(Q23:AB23) -> 0 | Q23: =SUM(R23:AC23) -> 0 | R23: =SUM(S23:AD23) -> 0 | S23: =SUM(T23:AE23) -> 0 | T23: =SUM(U23:AF23) -> 0 | U23: =SUM(V23:AG23) -> 0
A24: REFERAL (Berlangganan) | B24: PBGC 1 - Lidya | C24: Mei | D24: 2025 | E24: 5942 | F24: Agung Gunawan | G24: guns laundry | H24: =6283899290378 -> 6283899290378 | L24: Mitra Referral | M24: Jawa Barat | N24: Jl. MT Haryono 005/008 Ciledug, Bekasi | O24: 1 | P24: =SUM(Q24:AB24) -> 0 | Q24: =SUM(R24:AC24) -> 0 | R24: =SUM(S24:AD24) -> 0 | S24: =SUM(T24:AE24) -> 0 | T24: =SUM(U24:AF24) -> 0 | U24: =SUM(V24:AG24) -> 0
A25: REFERAL (Berlangganan) | B25: PBGC 1 - Lidya | C25: Mei | D25: 2025 | E25: 10409 | F25: Ahmad Kamal Dahlan | G25: Zona Laundry Mamuju | H25: 085213159125 | L25: Mitra Referral | M25: Sulawesi Barat | N25: Jl. Martadinata Mamuju, Kab. Mamuju | O25: ='Kelolaan Mitra'!H184 -> 1 | P25: =SUM(Q25:AB25) -> 0 | Q25: =SUM(R25:AC25) -> 0 | R25: =SUM(S25:AD25) -> 0 | S25: =SUM(T25:AE25) -> 0 | T25: =SUM(U25:AF25) -> 0 | U25: =SUM(V25:AG25) -> 0
A26: REFERAL (Berlangganan) | B26: PBGC 1 - Lidya | C26: Mei | D26: 2025 | E26: 4323 | F26: Atik Nurbayati | G26: Delisha Laundry | H26: 081259819220 | L26: Mitra Referral | M26: Jawa TImur | N26: Jl.H.Syukur No.75 Sedati Sidoarjo | O26: ='Kelolaan Mitra'!H186 -> 1 | P26: =SUM(Q26:AB26) -> 0 | Q26: =SUM(R26:AC26) -> 0 | R26: =SUM(S26:AD26) -> 0 | S26: =SUM(T26:AE26) -> 0 | T26: =SUM(U26:AF26) -> 0 | U26: =SUM(V26:AG26) -> 0
A27: REFERAL (Berlangganan) | B27: PBGC 1 - Lidya | C27: Juni | D27: 2025 | F27: Selly | H27: 082297051345 | J27: 6250379160 | K27: BCA | L27: Mitra Referral | M27: Banten | N27: Perumahan taman cibodas jl. Duta Raya Blok H1 No. 2, Tanggerang | O27: 2 | P27: =SUM(Q27:AB27) -> 0 | Q27: =SUM(R27:AC27) -> 0 | R27: =SUM(S27:AD27) -> 0 | S27: =SUM(T27:AE27) -> 0 | T27: =SUM(U27:AF27) -> 0 | U27: =SUM(V27:AG27) -> 0
A28: REFERAL (Berlangganan) | B28: PBGC 1 - Lidya | C28: Agustus | D28: 2025 | G28: Fast Laundry | L28: Mitra Referral | M28: Jawa Barat | N28: perumahan Lippo Cikarang jalan Surya kencana 2 no 6 | O28: 0 | P28: 0 | Q28: =SUM(R28:AC28) -> 0 | R28: =SUM(S28:AD28) -> 0 | S28: =SUM(T28:AE28) -> 0 | T28: =SUM(U28:AF28) -> 0 | U28: =SUM(V28:AG28) -> 0
A29: REFERAL (Berlangganan) | B29: PBGC 1 - Lidya | C29: Agustus | D29: 2025 | E29: 15292 | F29: Rika Yulia | G29: Kmm | H29: 085343850662 | L29: Mitra Referral | M29: Jawa Barat | N29: perumahan Lippo Cikarang jalan Surya kencana 2 no 60 | O29: 0 | P29: 0 | Q29: =SUM(R29:AC29) -> 0 | R29: =SUM(S29:AD29) -> 0 | S29: =SUM(T29:AE29) -> 0 | T29: =SUM(U29:AF29) -> 0 | U29: =SUM(V29:AG29) -> 0
A30: REFERAL (Berlangganan) | B30: PBGC 1 - Lidya | C30: September | D30: 2025 | E30: 8177 | F30: Tengku ariani | G30: Mame Laundry | H30: 081275566111 | L30: Mitra Referral | M30: Sumatera Utara | N30: Jalan Tani Asli gang Samin sebelah kolam renang Wira kel.purwodadi kec.sunggal kab.deli Serdang Sumatera Utara | O30: 0 | P30: 0 | Q30: =SUM(R30:AC30) -> 0 | R30: =SUM(S30:AD30) -> 0 | S30: =SUM(T30:AE30) -> 0 | T30: =SUM(U30:AF30) -> 0 | U30: =SUM(V30:AG30) -> 0

Sheet PotensiDemo 
A1: Data Potensi & Demo
A2: 1 - 30 Juni 2026
A3: Urutan Nasabah : 1. Sudah diclosing, 2. Sudah Di Training, 3. Belum Ditraining
A4: No | B4: Tanggal input | C4: Sumber Data | D4: PIC Nasabah | E4: Kode Owner | F4: Nama Owner | G4: Project & Brand | H4: No. HP Owner | I4: Status | J4: Membership | K4: Target Paket Langganan | L4: Target Nominal Langganan | M4: Paket Aktual | N4: Nominal Aktual | O4: Tanggal Training | P4: Status Training | Q4: Timeline Training | R4: Rating Play Store
A5: 1 | B5: 46174 | C5: Mitra Taufik | D5: PBGC 1 - Lidya | E5: 18739 | F5: Andini Pratiwi | G5: Ratu Laundry | H5: 081211778498 | I5: Closing | J5: Aktivasi | K5: Pro 1 Bulan | L5: 168000 | M5: Basic 9 Bulan | N5: 702031 | O5: 46160 | P5: Training Bulan Sebelumnya | Q5: 18739 - Andini Pratiwi - Ratu Laundry - 18/05/26
A6: 2 | B6: 46174 | C6: Kelolaan | D6: PBGC 1 - Lidya | E6: 18753 | F6: aceng ulumuddin | G6: Vara Laundry | H6: 08122314544 | I6: Closing | J6: Aktivasi | K6: Pro 12 Bulan | L6: 1688000 | M6: Pro 12 Bulan | N6: 1688000 | O6: 46162 | P6: Training Bulan Sebelumnya | Q6: 18753 - Vara Laubdry - aceng ulumuddin - 20 Mei 2026
A7: 3 | B7: 46174 | C7: Kelolaan | D7: PBGC 1 - Lidya | E7: 18785 | F7: Owner revajhoni | G7: fourkids laundry | H7: 089528002854 | I7: Closing | J7: Aktivasi | K7: Basic 12 Bulan | L7: 858000 | M7: Basic 12 Bulan | N7: 858017 | O7: 46160 | P7: Training Bulan Sebelumnya | Q7: 18745 - jhoni ariyanto - Fourkids laudry - 18/05/26
A8: 4 | B8: 46174 | C8: Kelolaan | D8: PBGC 1 - Lidya | E8: 18604 | F8: Rizky Lia Febianty | G8: Laundrypedia | H8: 081334611597 | I8: Closing | J8: Aktivasi | K8: Pro 12 Bulan | L8: 1688000 | M8: Jagoan Pro | N8: 2078000 | O8: 46184 | P8: Training Bulan ini
A9: 5 | B9: 46174 | C9: Referal Perusahaan | D9: PBGC 1 - Lidya | E9: 17147 | F9: Aulia Laundry_PP | G9: Aulia Laundry | H9: 0811400996 | I9: Closing | J9: Aktivasi | K9: Bisnis 1 Bulan | L9: 118000 | M9: Bisnis 1 Bulan | N9: 118000
A10: 6 | B10: 46181 | C10: Kelolaan | D10: PBGC 1 - Lidya | E10: 18893 | F10: Mentari Group | G10: Mentari Laundry | H10: 082163055555 | I10: Closing | J10: Aktivasi | K10: Pro 1 Bulan | L10: 168000 | M10: Basic 12 Bulan | N10: 858000 | O10: 46181 | P10: Training Bulan ini
A11: 7 | B11: 46188 | C11: Kelolaan | D11: PBGC 1 - Lidya | E11: 18907 | F11: Bubble's~2 | G11: Bubble 2 | H11: 085240267611 | I11: Closing | J11: Aktivasi | K11: Basic 1 Bulan | L11: 78000 | M11: Basic 12 Bulan | N11: 858000
A12: 8 | B12: 46188 | C12: Kelolaan | D12: PBGC 1 - Lidya | E12: 18919 | F12: Risnul Syafrizal | G12: Skuyy Laundry | H12: 082170927742 | I12: Closing | J12: Aktivasi | K12: Bisnis 1 Bulan | L12: 118000 | M12: Bisnis 1 Bulan | N12: 118070
A13: 9 | B13: 46181 | C13: Kelolaan | D13: PBGC 1 - Lidya | E13: 18954 | F13: Dewi Anggraini | G13: We Laundry | H13: 08161896392 | I13: Potensi | J13: No Package | K13: Basic 12 Bulan | L13: 858000 | O13: 46181 | P13: Training Bulan ini
A14: 10 | B14: 46181 | C14: Kelolaan | D14: PBGC 1 - Lidya | E14: 15510 | F14: Amanda | G14: cuciqu laundry / CICERI DROP POINT | H14: 087798951222 | I14: Potensi | J14: No Package | K14: Basic 1 Bulan | L14: 78000
A15: 11 | B15: 46207 | C15: Kelolaan | D15: PBGC 1 - Lidya | E15: 18420 | F15: villy | G15: Resik Laundry | H15: 085163036060 | I15: Potensi | J15: No Package | K15: Pro 12 Bulan | L15: 1688000 | O15: 46181 | P15: Training Bulan ini
A16: 12 | B16: 46181 | C16: Mitra Taufik | D16: PBGC 1 - Lidya | E16: 18965 | F16: Hertati Simanjuntak | G16: miss resik laundry | H16: 081280167784 | I16: Potensi | J16: No Package | K16: Pro 1 Bulan | L16: 168000 | O16: 46183 | P16: Training Bulan ini
A17: 13 | B17: 46181 | C17: Mitra Taufik | D17: PBGC 1 - Lidya | E17: 18964 | F17: BRI Link Vania Loundry | G17: Vannessa Laundry | H17: 085715609873 | I17: Potensi | J17: No Package
A18: 14 | B18: 46190 | C18: Kelolaan | D18: PBGC 1 - Lidya | E18: 18890 | F18: yuliyanti | G18: Rizky laundry | H18: 083820359958 | I18: Potensi | J18: No Package | O18: 46190 | P18: Training Bulan ini | Q18: https://drive.google.com/file/d/1YhWdSLP3uHQRcwvz2KWYFtAWQttNVwrC/view?usp=drive_link
A19: 15 | B19: 46190 | C19: Kelolaan | D19: PBGC 1 - Lidya | E19: 18540 | F19: Hanin Laundry | G19: Hanin laundry | H19: 081370907324 | I19: Potensi | J19: No Package | K19: Pro 12 Bulan | L19: 1688000 | P19: Belum di Training
A20: 16 | B20: 46190 | C20: Kelolaan | D20: PBGC 1 - Lidya | E20: 10703 | F20: Owner Mama laundry | G20: mama laundry / 88 Laundry | H20: 081717175658 | I20: Potensi | J20: No Package
A21: Total Pencapaian | K21: =sum(L5:L17) -> 7676000 | M21: =sum(N5:N17) -> 7278118
A23: Data Potensi & Demo
A24: 1 - 31 Mei 2026
A25: Urutan Nasabah : 1. Sudah diclosing, 2. Sudah Di Training, 3. Belum Ditraining
A26: No | B26: Tanggal input | C26: Sumber Data | D26: PIC Nasabah | E26: Kode Owner | F26: Nama Owner | G26: Project & Brand | H26: No. HP Owner | I26: Status | J26: Membership | K26: Target Paket Langganan | L26: Target Nominal Langganan | M26: Paket Aktual | N26: Nominal Aktual | O26: Tanggal Training | P26: Status Training | Q26: Timeline Training | R26: Rating Play Store
A27: 1 | B27: 46146 | C27: Mitra KG TEKNIK BATAM | D27: PBGC 1 - Lidya | E27: 18587 | F27: Anderson Laundry | G27: Anderson Laundry | H27: 085363292222 | I27: Closing | J27: Aktivasi | K27: Pro 12 Bulan | L27: 1688000 | M27: Pro 12 Bulan | N27: 1688000 | O27: 46146 | P27: Training Bulan ini | Q27: 18587 - Anderson Laundry - Anderson Laundry - 04/05/26 | R27: 18587 - Anderson Laundry - Anderson Laundry
A28: 2 | B28: 46147 | C28: Referal Perusahaan | D28: PBGC 1 - Lidya | E28: 17980 | F28: Delta Plus Laundry | G28: Delta+ Laundry | H28: 082344337583 | I28: Closing | J28: Aktivasi | K28: Basic 12 Bulan | L28: 858000 | M28: Pro 12 Bulan | N28: 1718020 | R28: 17980 - Delta Plus Laundry - Delta+ Laundry
A29: 3 | B29: 46149 | C29: Kelolaan | D29: PBGC 1 - Lidya | E29: 14115 | F29: Nuranura | G29: Laundry / Ruang Laundry 2 | H29: 082320655655 | I29: Closing | J29: Aktivasi | K29: Pro 12 Bulan | L29: 1688000 | M29: Pro 12 Bulan | N29: 1688000
A30: 4 | B30: 46162 | C30: Referal Perusahaan | D30: PBGC 1 - Lidya | E30: 18763 | F30: Irma | G30: Fast Laundry 2 | H30: 08999999308 | I30: Closing | J30: Pending | K30: Pro 12 Bulan | L30: 1688000 | M30: Pro 12 Bulan | N30: 1688000 | O30: 46163 | P30: Training Bulan ini
A31: 5 | B31: 46132 | C31: Kelolaan | D31: PBGC 1 - Lidya | E31: 18411 | F31: Ivo | G31: Zeline Laundry | H31: 081225752657 | I31: Closing | J31: Aktivasi | K31: Pro 12 Bulan | L31: 1688000 | M31: Pro 12 Bulan | N31: 1688000 | P31: Training Bulan ini
A32: 6 | B32: 46160 | C32: Kelolaan | D32: PBGC 1 - Lidya | E32: 18676 | F32: DGN Wash & Clean Laundry | G32: laundry | H32: 081319462926 | I32: Closing | J32: Aktivasi | K32: Pro 1 Bulan | L32: 168000 | M32: Pro 12 Bulan | N32: 1688000 | O32: 46160 | P32: Training Bulan ini | Q32: 18676 - DGN Wash & Clean Laundry - laundry - 18/05/26
A33: 7 | B33: 46159 | C33: Referal Perusahaan | D33: PBGC 1 - Lidya | E33: 18728 | F33: Kin's Laundry | G33: Kin's Laundry | H33: 081931735165 | I33: Closing | J33: Aktivasi | K33: Pro 12 Bulan | L33: 1688000 | M33: Pro 12 Bulan | N33: 1688000 | O33: 46159 | P33: Training Bulan ini | Q33: 18728 - Kin's Laundry - Kin's Laundry - 17/05/26 | R33: 18728 - Kin's Laundry - Kin's Laundry
A34: 15 | B34: 46148 | C34: Kelolaan | D34: PBGC 1 - Lidya | E34: 13063 | F34: Fajar Lazuardiana | G34: SABI LAUNDRY / SABI LAUNDRY 2 | H34: 081318560911 | I34: Closing | J34: Aktivasi | K34: Pro 12 Bulan | L34: 1688000 | M34: Pro 12 Bulan | N34: 1688000
A35: 8 | B35: 46170 | C35: Referal Perusahaan | D35: PBGC 1 - Lidya | E35: 4156 | F35: Admin 1 | G35: Red Laundry Bethesda / Red Laundry Tomohon | H35: 081356709000 | I35: Closing | J35: Aktivasi | K35: Basic 12 Bulan | L35: 858000 | M35: Basic 12 Bulan | N35: 858002 | O35: 46170 | P35: Training Bulan ini | Q35: 4156 - Red Laundry Tomohon - Admin 1 - 28/05/26 | R35: 4156 - Red Laundry Tomohon - Admin 1
A36: 9 | B36: 46156 | C36: Kelolaan | D36: PBGC 1 - Lidya | E36: 14529 | F36: ulfa | G36: bintang laundry / bintang laundry badas | H36: 085853958526 | I36: Closing | J36: Aktivasi | K36: Bisnis 6 Bulan | L36: 708000 | M36: Bisnis 6 Bulan | N36: 708000 | O36: 46164 | P36: Training Bulan ini | Q36: 14529 - bintang laundry badas - ulfa - 22/05/26
A37: 10 | B37: 46141 | C37: Kelolaan | D37: PBGC 1 - Lidya | E37: 18470 | F37: DENNY | G37: CUCIKU LAUNDRY | H37: 085784106339 | I37: Closing | J37: Aktivasi | K37: Pro 1 Bulan | L37: 168000 | M37: Pro 1 Bulan | N37: 168000 | R37: 18470 - DENNY - CUCIKU LAUNDRY
A38: 11 | B38: 46154 | C38: Mitra Taufik | D38: PBGC 1 - Lidya | E38: 18666 | F38: Mulia jaya solusindo | G38: FAST Laundry | H38: 085977599002 | I38: Closing | J38: Pending | K38: Pro 1 Bulan | L38: 168000 | M38: Pro 1 Bulan | N38: 168000 | O38: 46154 | P38: Training Bulan ini | Q38: 18666 - Mulia jaya solusindo - FAST Laundry - 12/05/26
A39: 12 | B39: 46156 | C39: Kelolaan | D39: PBGC 1 - Lidya | E39: 14529 | F39: ulfa | G39: bintang laundry | H39: 085853958526 | I39: Closing | J39: On Progrees | K39: Printer Thermal | L39: 399000 | M39: Printer Thermal | N39: 399000
A40: 13 | B40: 46156 | C40: Kelolaan | D40: PBGC 1 - Lidya | E40: 14529 | F40: ulfa | G40: bintang laundry | H40: 085853958526 | I40: Closing | J40: On Progrees | K40: Kertas Thermal | L40: 54000 | M40: Kertas Thermal | N40: 54000
A41: 14 | B41: 46146 | C41: Kelolaan | D41: PBGC 1 - Lidya | E41: 18580 | F41: Osman Kadir | G41: BAMASS LAUNDRY | H41: 6285251519797 | I41: Negoisasi | J41: No Package | K41: Pro 12 Bulan | L41: 1688000
A42: 16 | B42: 46146 | C42: Kelolaan | D42: PBGC 1 - Lidya | E42: 18567 | F42: Tawakkal | G42: Malomo Laundry | H42: 082347030333 | I42: Potensi | J42: No Package
A43: 17 | B43: 46134 | C43: Referal Perusahaan | D43: PBGC 1 - Lidya | E43: 18447 | F43: Barossie Laundry | G43: Barossie | H43: 085711779968 | I43: Potensi | J43: No Package | O43: 46134 | P43: Training Bulan Sebelumnya | Q43: 18447 - Barossie - Barossie Laundry - 22/04/2026
A44: 18 | B44: 46149 | C44: Kelolaan | D44: PBGC 1 - Lidya | E44: 18420 | F44: villy | G44: Resik Laundry | H44: 085163036060 | I44: Potensi | J44: No Package
A45: 19 | B45: 46160 | C45: Mitra Taufik | D45: PBGC 1 - Lidya | E45: 18739 | F45: Andini Pratiwi | G45: Ratu Laundry | H45: 081211778498 | I45: Potensi | J45: No Package | K45: Pro 1 Bulan | L45: 168000 | O45: 46160 | P45: Training Bulan ini | Q45: 18739 - Andini Pratiwi - Ratu Laundry - 18/05/26
A46: 20 | B46: 46160 | C46: Kelolaan | D46: PBGC 1 - Lidya | E46: 18742 | F46: Nana Kasterin | G46: Laundryku Bali | H46: 0818356761 | I46: Potensi | J46: No Package
A47: 21 | B47: 46160 | C47: Kelolaan | D47: PBGC 1 - Lidya | E47: 18745 | F47: jhoni ariyanto | G47: Fourkids laudry | H47: 089528002854 | I47: Potensi | J47: No Package | O47: 46160 | P47: Training Bulan ini | Q47: 18745 - jhoni ariyanto - Fourkids laudry - 18/05/26
A48: 22 | B48: 46162 | C48: Kelolaan | D48: PBGC 1 - Lidya | E48: 18753 | F48: aceng ulumuddin | G48: Vara Laundry | H48: 08122314544 | I48: Potensi | J48: No Package | O48: 46162 | P48: Training Bulan ini | Q48: 18753 - Vara Laubdry - aceng ulumuddin - 20 Mei 2026
A49: 23 | B49: 46160 | C49: Referal Perusahaan | D49: PBGC 1 - Lidya | E49: 17147 | F49: Aulia Laundry | G49: Aulia Laundry | H49: 0811400996 | I49: Potensi | J49: No Package
A50: 24 | B50: 46162 | C50: Kelolaan | D50: PBGC 1 - Lidya | E50: 18604 | F50: Rizky Lia Febianty | G50: Laundrypedia | H50: 081334611597 | I50: Potensi | J50: No Package
A51: Total Pencapaian | K51: =sum(L27:L50) -> 15365000 | M51: =sum(N27:N50) -> 15889022
A53: Data Potensi & Demo
A54: 1 - 30 April 2026
A55: Urutan Nasabah : 1. Sudah diclosing, 2. Sudah Di Training, 3. Belum Ditraining
A56: No | B56: Tanggal input | C56: Sumber Data | D56: PIC Nasabah | E56: Kode Owner | F56: Nama Owner | G56: Project & Brand | H56: No. HP Owner | I56: Status | J56: Membership | K56: Target Paket Langganan | L56: Target Nominal Langganan | M56: Paket Aktual | N56: Nominal Aktual | O56: Tanggal Training | P56: Status Training | Q56: Timeline Training | R56: Rating Play Store
A57: 1 | B57: 46113 | C57: Kelolaan | D57: PBGC 1 - Lidya | E57: 18051 | F57: Ingewati Puguh | G57: Happy Laundry | H57: 08123450292 | I57: Closing | J57: Aktivasi | K57: Pro 12 Bulan | L57: 1688000 | M57: Pro 12 Bulan | N57: 1688000 | O57: 46113 | P57: Follow up Call&Chat | R57: 18051 - Happy Laundry - ingewati Puguh - 18/04/2026
A58: 2 | B58: 46139 | C58: Referal Perusahaan | D58: PBGC 1 - Lidya | E58: 10659 | F58: Owner Defly | G58: Defly Laundry Express | H58: 082398922244 | I58: Closing | J58: Aktivasi | K58: Basic 12 Bulan | L58: 858000 | M58: Basic 12 Bulan | N58: 858081
A59: 3 | B59: 46118 | C59: Kelolaan | D59: PBGC 1 - Lidya | E59: 17863 | F59: Frischella Tuty Martini | G59: Supeer Laundry | H59: 082385500575 | I59: Closing | J59: Aktivasi | K59: Pro 1 Bulan | L59: 168000 | M59: Pro 1 Bulan | N59: 436086
A60: 4 | B60: 46119 | C60: Kelolaan | D60: PBGC 1 - Lidya | E60: 10406 | F60: Sania kartika | G60: Fast Laundry/Fast Laundry | H60: 082252788533 | I60: Closing | J60: On Progrees | K60: Printer Thermal | L60: 399000 | M60: Printer Thermal | N60: 399000
A61: 5 | B61: 46133 | C61: Kelolaan | D61: PBGC 1 - Lidya | E61: 16306 | F61: Vicky loundry 2 | G61: loundry | H61: 081262537788 | I61: Closing | J61: Aktivasi | K61: Basic 6 Bulan | L61: 468000 | M61: Basic 6 Bulan | N61: 468000
A62: 6 | B62: 46139 | C62: Kelolaan | D62: PBGC 1 - Lidya | E62: 18512 | F62: Tiur Uli | G62: V Four Laundry | H62: 081280277383 | I62: Negoisasi | J62: No Package | K62: Bisnis 12 Bulan | L62: 1298000 | O62: 46142 | P62: Training Bulan ini | Q62: 18512 - V Four Laundry - Tiur Uli - 30/04/2026
A63: 7 | B63: 46125 | C63: Referal Perusahaan | D63: PBGC 1 - Lidya | E63: No Name | F63: Pak Adhi Muhammad Daryono | G63: Pak Adhi Muhammad Daryono | H63: No Name | I63: Potensi | J63: No Package
A64: 8 | B64: 46126 | C64: Kelolaan | D64: PBGC 1 - Lidya | E64: 18352 | F64: Daniel Bakara | G64: KaJe Laundry | H64: 089696447448 | I64: Potensi | J64: No Package
A65: 9 | B65: 46128 | C65: Kelolaan | D65: PBGC 1 - Lidya | E65: 18168 | F65: Hana Laundry | G65: Hana Laundry | H65: 081389300953 | I65: Potensi | J65: No Package | K65: Pro 1 Bulan | L65: 168000
A66: 10 | B66: 46132 | C66: Kelolaan | D66: PBGC 1 - Lidya | E66: 18411 | F66: Ivo | G66: Zeline Laundry | H66: 081225752657 | I66: Potensi | J66: No Package
A67: 11 | B67: 46134 | C67: Referal Perusahaan | D67: PBGC 1 - Lidya | E67: 18447 | F67: Barossie Laundry | G67: Barossie | H67: 085711779968 | I67: Potensi | J67: No Package | O67: 46134 | P67: Training Bulan ini | Q67: 18447 - Barossie - Barossie Laundry - 22/04/2026
A68: 12 | B68: 46141 | C68: Kelolaan | D68: PBGC 1 - Lidya | E68: 18470 | F68: DENNY | G68: CUCIKU LAUNDRY | H68: 085784106339 | I68: Potensi | J68: No Package
A69: 13 | B69: 46119 | C69: Kelolaan | D69: PBGC 4 - Laura | E69: 18173 | F69: Zahra laundry | G69: Zahra laundry | H69: 081320584171 | I69: Closing | J69: Aktivasi | K69: Basic 12 Bulan | L69: 858000 | M69: Basic 12 Bulan | N69: 858000 | O69: 46119 | P69: Training Bulan ini | Q69: 18173 - Zahra laundry - Zahra laundry - 07/04/26.jpg | R69: 18173 - Zahra laundry - Zahra laundry - 07/04/26.jpg
A70: 14 | B70: 46114 | C70: Kelolaan | D70: PBGC 4 - Laura | E70: 17227 | F70: Rom Doni | G70: go laundry | H70: 087792981424 | I70: Potensi | J70: No Package | K70: Basic 1 Bulan | O70: 46114 | P70: Follow up Call&Chat
A71: 15 | B71: 46121 | C71: Kelolaan | D71: PBGC 4 - Laura | E71: 18293 | F71: Intan Fitria sari | G71: JASA LAUNDRY KILOAN SATUAN INTAN SINTA | H71: 085730847511 | I71: Potensi | J71: No Package | O71: 46121 | P71: Training Bulan ini | Q71: 18293 - Intan Fitria sari - JASA LAUNDRY KILOAN SATUAN INTAN SINTA - 09/04/2026.jpg
A72: 16 | B72: 46121 | C72: Kelolaan | D72: PBGC 4 - Laura | E72: 16838 | F72: Untung Fridiono | G72: Gosok-in | H72: 085755272991 | I72: Potensi | J72: No Package | O72: 46121 | P72: Follow up Call&Chat
A73: 17 | B73: 46125 | C73: Kelolaan | D73: PBGC 4 - Laura | E73: 18341 | F73: Nur Hayati | G73: Jihan laundry | H73: 089507260156 | I73: Potensi | J73: No Package | O73: 46125 | P73: Training Bulan ini | Q73: 18341 - Nur Hayati - Jihan laundry - 13/04/26.jpg
A74: 18 | B74: 46127 | C74: Kelolaan | D74: PBGC 4 - Laura | E74: 18357 | F74: denita khairunnissa | G74: freshclean.expresss | H74: 08211883676 | I74: Potensi | J74: No Package | O74: 46127 | P74: Training Bulan ini | Q74: 18357 - denita khairunnissa - freshclean.expresss - 15/04/26.jpg
A75: 19 | B75: 46129 | C75: Kelolaan | D75: PBGC 4 - Laura | E75: 18383 | F75: Christian Yossy Anggola | G75: Cuci'In Laundry | H75: 085755551287 | I75: Negoisasi | J75: No Package | K75: Pro 1 Bulan | L75: 168000 | O75: 46129 | P75: Follow up Call&Chat
A76: Total Pencapaian | K76: =sum(L57:L75) -> 6073000 | M76: =sum(N57:N75) -> 4707167
A78: Data Potensi & Demo
A79: 1 - 31 Maret 2026
A80: Urutan Nasabah : 1. Sudah diclosing, 2. Sudah Di Training, 3. Belum Ditraining
A81: No | B81: Tanggal input | C81: Sumber Data | D81: PIC Nasabah | E81: Kode Owner | F81: Nama Owner | G81: Project & Brand | H81: No. HP Owner | I81: Status | J81: Membership | K81: Target Paket Langganan | L81: Target Nominal Langganan | M81: Paket Aktual | N81: Nominal Aktual | O81: Tanggal Training | P81: Status Training | Q81: Timeline Training | R81: Rating Play Store
A82: 1 | B82: 46083 | C82: Kelolaan | D82: PBGC 1 - Lidya | E82: 17838 | F82: Hi Sary Laundry | G82: Hi Sary Laundry | H82: 081517071000 | I82: Closing | J82: Aktivasi | K82: Bisnis 12 Bulan | L82: 1298000 | M82: Bisnis 12 Bulan | N82: 1298000 | P82: Follow up Call&Chat | R82: 17838 - Hi Sary Laundry - Hi Sary Laundry - 02/03/2026
A83: 2 | B83: 46083 | C83: Kelolaan | D83: PBGC 1 - Lidya | E83: 4181 | F83: DIGNITY SINAGA | G83: DIGNITY LAUNDRY / DIGNITY LAUNDRY PUSAT (Jln Jawa) | H83: 082370098185 | I83: Closing | J83: Aktivasi | K83: Bisnis 12 Bulan | L83: 1298000 | M83: Bisnis 12 Bulan | N83: 1200000
A84: 3 | B84: 46083 | C84: Mitra Taufik | D84: PBGC 1 - Lidya | E84: 17522 | F84: Cendy Rachmat Umasangaji | G84: Clean & Co Laundry Semarang | H84: 081239081763 | I84: Closing | J84: Aktivasi | K84: Pro 12 Bulan | L84: 1688000 | M84: Pro 12 Bulan | N84: 1658000
A85: 4 | B85: 46086 | C85: Mitra Taufik | D85: PBGC 1 - Lidya | E85: 18052 | F85: IWAN MUCHAMMAD HIDAYATULLAH S, S.T. | G85: ONEDAY LAUNDRY | H85: 081318957067 | I85: Closing | J85: Aktivasi | K85: Basic 12 Bulan | L85: 858000 | M85: Basic 12 Bulan | N85: 858000 | R85: 18052 - ONEDAY LAUNDRY - IWAN MUCHAMMAD HIDAYATULLAH S, S.T. - 09/03/2026
A86: 5 | B86: 46090 | C86: Kelolaan | D86: PBGC 1 - Lidya | E86: 18116 | F86: Athaya Ocoy | G86: miwa / MIWA LAUNDRY | H86: 085778024944 | I86: Closing | J86: Aktivasi | K86: Pro 12 Bulan | L86: 1688000 | M86: Pro 12 Bulan | N86: 1688000 | R86: 18116 - Athaya Ocoy - miwa / MIWA LAUNDRY - 30/03/2026
A87: 6 | B87: 46098 | C87: Kelolaan | D87: PBGC 1 - Lidya | E87: 18051 | F87: Ingewati Puguh | G87: Happy Laundry | H87: 08123450292 | I87: Negoisasi | J87: No Package | K87: Pro 12 Bulan | L87: 1688000
A88: 7 | B88: 46105 | C88: Kelolaan | D88: PBGC 1 - Lidya | E88: 17941 | F88: Ribka Vatricia Malau | G88: Ok Loundry | H88: 081283414570 | I88: Potensi | J88: No Package | K88: Bisnis 12 Bulan | L88: 1298000
A89: 8 | B89: 46084 | C89: Mitra Taufik | D89: PBGC 1 - Lidya | E89: 17974 | F89: Eny Laundry 2 Kebagusan | G89: Eny Laundry 2 | H89: 08211664656 | I89: Potensi | J89: No Package | O89: 46083 | P89: Training Bulan ini | Q89: 17974 - Eny Laundry 2 Kebagusan - Eny Laundry 2 - 02/03/26
A90: 9 | B90: 46085 | C90: Kelolaan | D90: PBGC 1 - Lidya | E90: 17955 | F90: Rini Prastiwi11 | G90: ARESHA LAUNDRY | H90: 0882007287389 | I90: Potensi | J90: No Package
A91: 10 | B91: 46104 | C91: Kelolaan | D91: PBGC 4 - Laura | E91: 17785 | F91: The Laundry Lab | G91: The Lab Laundry | H91: 81231513674 | I91: Closing | J91: Aktivasi | K91: Basic 12 Bulan | L91: 858000 | M91: Pro 12 Bulan | N91: 1688000 | P91: Training Bulan ini | R91: 17785 - The Laundry Lab - The Lab Laundry - 24/03/2026
A92: 11 | B92: 46106 | C92: Kelolaan | D92: PBGC 4 - Laura | E92: 17732 | F92: Epi & a laundry | G92: Usaha Laundry Kiloan | H92: 81220358391 | I92: Potensi | J92: No Package
A93: 12 | B93: 46108 | C93: Kelolaan | D93: PBGC 4 - Laura | E93: 18154 | F93: Saril Ambal | G93: SARIL AMBAL WASH EXPRESS | H93: 85359993090 | I93: Potensi | J93: No Package
A94: 13 | B94: 46111 | C94: Kelolaan | D94: PBGC 4 - Laura | E94: 11924 | F94: Djoko Haryono | G94: AWW LAUNDRY | H94: 81382488741 | I94: Potensi | J94: No Package
A95: Total Pencapaian | K95: =sum(L82:L91) -> 10674000 | M95: =sum(N82:N92) -> 8390000
A97: Data Potensi & Demo
A98: 1 - 28 Februari 2026
A99: Urutan Nasabah : 1. Sudah diclosing, 2. Sudah Di Training, 3. Belum Ditraining
A100: No | B100: Tanggal input | C100: Sumber Data | D100: PIC Nasabah | E100: Kode Owner | F100: Nama Owner | G100: Project & Brand | H100: No. HP Owner | I100: Status | J100: Membership | K100: Target Paket Langganan | L100: Target Nominal Langganan | M100: Paket Aktual | N100: Nominal Aktual | O100: Tanggal Training | P100: Status Training | Q100: Timeline Training | R100: Rating Play Store
A101: 1 | C101: Kelolaan | D101: PBGC 1 - Lidya | E101: 17512 | F101: Golden Coin Laundry | G101: Golden Coin Laundry | H101: 082170574987 | I101: Closing | J101: Aktivasi | K101: Pro 12 Bulan | L101: 1688000 | M101: Jagoan Pro | N101: 2078000 | O101: 46073 | P101: Training Bulan ini
A102: 2 | C102: Mitra Taufik | D102: PBGC 1 - Lidya | E102: 17823 | F102: Noto Adiputro | G102: Laundry Clean star | H102: 0895320501711 | I102: Closing | J102: Aktivasi | K102: Pro 12 Bulan | L102: 1688000 | M102: Pro 12 Bulan | N102: 1683053
A103: 3 | C103: Kelolaan | D103: PBGC 1 - Lidya | E103: 17572 | F103: Indra Sukma Admadinata | G103: HAPPY CLEAN LAUNDRY | H103: 081349355323 | I103: Closing | J103: Aktivasi | K103: Bisnis 12 Bulan | L103: 1298000 | M103: Bisnis 12 Bulan | N103: 1298000 | R103: 17572 - Indra Sukma Admadinata - HAPPY CLEAN LAUNDRY - 09/02/2026
A104: 4 | C104: Mitra Taufik | D104: PBGC 1 - Lidya | E104: 17724 | F104: Ella | G104: Fresh Laundry | H104: 085714798707 | I104: Closing | J104: Aktivasi | K104: Basic 12 Bulan | L104: 858000 | M104: Basic 12 Bulan | N104: 858000
...

Sheet Copy of K.-Lidya (buat devi) 
A1: PT PIPOSMART DIGITAL INDONESIA
A2: Data Kelolaan Nasabah
A3: Pengertian Scorsing = 0. (Tidak Tertarik) 1. (New Download) 2. (Potensial) 3. (Berlangganan)
A4: Total Fu | B4: Tanggal Fu | C4: Tahun | D4: Bulan | E4: No | F4: Tanggal Dibagikan (Data) | G4: Status Akun | H4: Kode Baris | I4: Kode Owner | J4: Nama Owner | K4: Project/Brand | L4: Outlet | M4: No. HP Owner | N4: No. HP Outlet | O4: Create Date Project | P4: Expired Date | Q4: Total Transaksi | R4: Scor | S4: Call | T4: Chat | U4: Validitas | V4: Remaks | W4: Sumber Nasabah | X4: Finalisasi (Closing) | Y4: Nominal | Z4: Noted | AA4: Audit
A5: =COUNTIF('Call & Chat-Lidya'!$I$4:$I$2433,I5) -> 1 | B5: 18/05/26 | C5: 2026 | D5: Februari | E5: 450 | F5: 46069 | H5: 10691 | I5: 17869 | J5: Supreme Wash Laundry | K5: SW Laundry | L5: SW Laundry | M5: 08128566488 | O5: 46069 | P5: 46083 | Q5: 4 | R5: 3 | S5: NO CALL | T5: DELIVERED | U5: VALID | V5: (3) Berlangganan | W5: Mitra | X5: Pro | Y5: 1688000
A6: =COUNTIF('Call & Chat-Lidya'!$I$4:$I$2433,I6) -> 6 | B6: 46162 | C6: 2026 | D6: Mei | E6: 408 | F6: 46141 | G6: AKun Baru | H6: 11093 | I6: 18531 | J6: nurfiah | K6: Fatimah Laundry | L6: Fatimah Laundry | M6: 085824527826 | N6: 085824527826 | O6: 46141 | P6: 46155 | Q6: 0 | R6: 2 | S6: CONNECTED | T6: DELIVERED | U6: VALID | V6: (1) Rencana buka laundry
A7: =COUNTIF('Call & Chat-Lidya'!$I$4:$I$2433,I7) -> 6 | B7: 46162 | C7: 2026 | D7: Mei | E7: 295 | F7: 46084 | G7: AKun Baru | H7: 10679 | I7: 17843 | J7: Lusi qayyimah | K7: RUMAH LAUNDRY FRIZEL | L7: RUMAH LAUNDRY FRIZEL | M7: 082324386122 | N7: 082324386122 | O7: 46067 | P7: 46081 | Q7: 0 | R7: 1 | S7: CONTACTED | T7: DELIVERED | U7: VALID | V7: (1) Rencana buka laundry | W7: Tiktok
A8: =COUNTIF('Call & Chat-Lidya'!$I$4:$I$2433,I8) -> 5 | B8: 46162 | C8: 2026 | D8: Mei | E8: 436 | F8: 46073 | G8: AKun Baru | H8: 10726 | I8: 17915 | J8: K.Jamila | K8: Syamiar Laundry | L8: Syamiar Laundry | M8: 082331159747 | N8: 082331159747 | O8: 46073 | P8: 46087 | Q8: 1 | R8: 1 | S8: CONNECTED | T8: DELIVERED | U8: VALID | V8: (1) Rencana buka laundry | W8: Playstore | X8: Not yet
A9: =COUNTIF('Call & Chat-Lidya'!$I$4:$I$2433,I9) -> 6 | B9: 46162 | C9: 2026 | D9: Mei | E9: 475 | F9: 46062 | G9: AKun Baru | H9: 10635 | I9: 17775 | J9: Saleh arifin | K9: Amualfa Laundry | L9: Amualfa Laundry | M9: 081375201234 | N9: 081375201234 | O9: 46061 | P9: 46075 | Q9: 0 | R9: 1 | S9: CONNECTED | T9: DELIVERED | U9: VALID | V9: (1) Rencana buka laundry | W9: Tiktok | X9: Not yet
A10: =COUNTIF('Call & Chat-Lidya'!$I$4:$I$2433,I10) -> 8 | B10: 46162 | C10: 2026 | D10: Mei | E10: 333 | F10: 46134 | G10: AKun Baru | H10: 11009 | I10: 18375 | J10: siti maesaroh | K10: Siap Jaya Laundry | L10: Siap Jaya Laundry | M10: 085229873995 | N10: 08139908989 | O10: 46129 | P10: 46143 | Q10: 0 | R10: 2 | S10: CONNECTED | T10: DELIVERED | U10: VALID | V10: (0) Tidak Merespon
A11: =COUNTIF('Call & Chat-Lidya'!$I$4:$I$2433,I11) -> 6 | B11: 46162 | C11: 2026 | D11: Mei | E11: 344 | F11: 46134 | G11: AKun Baru | H11: 11040 | I11: 18447 | J11: Barossie Laundry | K11: Barossie | L11: Barossie | M11: 085711779968 | N11: 085711779968 | O11: 46134 | P11: 46148 | Q11: 0 | R11: 2 | S11: CONNECTED | T11: DELIVERED | U11: VALID | V11: (0) Tidak Merespon
A12: =COUNTIF('Call & Chat-Lidya'!$I$4:$I$2433,I12) -> 5 | B12: 46162 | C12: 2026 | D12: Mei | E12: 348 | F12: 46135 | G12: AKun Baru | H12: 11048 | I12: 18461 | J12: Dhioka lokesworo | K12: barossie | L12: barossie | M12: 082123411266 | O12: 46135 | P12: 46149 | Q12: 0 | R12: 2 | S12: CONNECTED | T12: DELIVERED | U12: VALID | V12: (0) Tidak Merespon
A13: =COUNTIF('Call & Chat-Lidya'!$I$4:$I$2433,I13) -> 5 | B13: 46162 | C13: 2026 | D13: Mei | E13: 394 | F13: 46139 | G13: AKun Baru | H13: 11082 | I13: 18513 | J13: monica | K13: PrimaX Laundry | L13: PrimaX Laundry | M13: 081265909182 | O13: 46139 | P13: 46153 | Q13: 1 | R13: 2 | S13: CONNECTED | T13: DELIVERED | U13: VALID | V13: (0) Tidak Merespon | W13: Playstore
A14: =COUNTIF('Call & Chat-Lidya'!$I$4:$I$2433,I14) -> 3 | B14: 46162 | C14: 2026 | D14: Mei | E14: 437 | F14: 46158 | G14: AKun Baru | H14: 11204 | I14: 18720 | J14: Ts Laundry | K14: TS LOUNDRY | L14: TS LOUNDRY | M14: 083169947029 | N14: 083169947029 | O14: 46158 | P14: 46172 | Q14: 0 | R14: 3 | S14: CONNECTED | T14: DELIVERED | U14: VALID | V14: (3) Berlangganan
A15: =COUNTIF('Call & Chat-Lidya'!$I$4:$I$2433,I15) -> 1 | B15: 46162 | C15: 2026 | D15: Mei | E15: 449 | F15: 46161 | G15: AKun Baru | H15: 11224 | I15: 18752 | J15: Mokhamad Prima Ramadhan | K15: abc | L15: abc | M15: 0811111111112 | N15: 0811111221111 | O15: 46161 | P15: 46175 | Q15: 0 | R15: 0 | S15: CONTACTED | T15: SENT | U15: INVALID | V15: (0) Tidak Merespon | Z15: Nomor tidak terhubung dengan wa
A16: =COUNTIF('Call & Chat-Lidya'!$I$4:$I$2433,I16) -> 6 | B16: 46164 | C16: 2026 | D16: Mei | E16: 450 | F16: 46161 | G16: AKun Baru | H16: 11225 | I16: 18753 | J16: aceng ulumuddin | K16: Vara Laundry | L16: Vara Laundry | M16: 08122314544 | N16: 08122314544 | O16: 46161 | P16: 46175 | Q16: 5 | R16: 2 | S16: CONNECTED | T16: DELIVERED | U16: VALID | V16: (2) Trial, Demo, Interaktif
A17: =COUNTIF('Call & Chat-Lidya'!$I$4:$I$2433,I17) -> 3 | B17: 46162 | C17: 2026 | D17: Mei | E17: 451 | F17: 46162 | G17: AKun Baru | H17: 11226 | I17: 18756 | J17: Iqbal Renaldo | K17: Khairin laundry | L17: Khairin laundry | M17: 082210460725 | N17: 082210460725 | O17: 46161 | P17: 46175 | Q17: 1 | R17: 1 | S17: CONNECTED | T17: DELIVERED | U17: VALID | V17: (0) Tidak Merespon
A18: =COUNTIF('Call & Chat-Lidya'!$I$4:$I$2433,I18) -> 3 | B18: 46162 | C18: 2026 | D18: Mei | E18: 452 | F18: 46162 | G18: AKun Baru | H18: 11229 | I18: 18762 | J18: julian | K18: nasa laundry | L18: nasa laundry | M18: 087796872260 | N18: 087796872260 | O18: 46162 | P18: 46176 | Q18: 0 | R18: 1 | S18: CONNECTED | T18: ENGAGE | U18: VALID | V18: (0) Data Karyawan dan Trial | Z18: Penjelasan cara penginputan jumlah item yang dicuci di aplikasi piposmart
A19: =COUNTIF('Call & Chat-Lidya'!$I$4:$I$2433,I19) -> 16 | B19: 46162 | C19: 2026 | D19: Mei | E19: 11 | F19: 46146 | G19: AKun Baru | H19: 11124 | I19: 18580 | J19: Osman Kadir | K19: BAMASS LAUNDRY | L19: BAMASS LAUNDRY | M19: 085251519797 | N19: 085251519797 | O19: 46146 | P19: 46160 | Q19: 0 | R19: 2 | S19: CONNECTED | T19: PROSPECT | U19: VALID | V19: (2) Trial, Demo, Interaktif | W19: Mitra | Z19: Reminder mengenai rencana penggunaan aplikasi piposmart dan saat ini bapaknya lagi di afrika dan nanti akan dihubungi kemnbali.
A20: =COUNTIF('Call & Chat-Lidya'!$I$4:$I$2433,I20) -> 13 | B20: 46164 | C20: 2026 | D20: Mei | E20: 38 | F20: 46148 | G20: AKun Baru | H20: 11137 | I20: 18604 | J20: Rizky Lia Febianty | K20: Laundrypedia | L20: Laundrypedia | M20: 081334611597 | N20: 081334611597 | O20: 05/05/26 | P20: 46161 | Q20: 0 | R20: 2 | S20: NO CALL | T20: DELIVERED | U20: VALID | V20: (2) Trial, Demo, Interaktif
A21: =COUNTIF('Call & Chat-Lidya'!$I$4:$I$2433,I21) -> 3 | B21: 46161 | C21: 2026 | D21: Mei | E21: 336 | F21: 46134 | G21: AKun Baru | H21: 11020 | I21: 18394 | J21: Muhammad Saifulloh | K21: SAIF laundry | L21: SAIF laundry | M21: 085607415717 | N21: 085607415717 | O21: 46130 | P21: 46144 | Q21: 1 | R21: 1 | S21: INTEREST | T21: DELIVERED | U21: VALID | V21: (0) Data Employee dan Trial | W21: Playstore | Z21: Aplikasi belum digunakan karna masih fokus ke keluarga karna saat ini lagi ada acara keluarga. Untuk saat ini laundry masih nota manual dan masih mencari karyawan yang compatable penggunaan piposmartnya. Saat ini masih melihat perkembangan laundry dan mau menyediakan device khusus laundry nanti
A22: =COUNTIF('Call & Chat-Lidya'!$I$4:$I$2433,I22) -> 3 | B22: 46161 | C22: 2026 | D22: Mei | E22: 365 | F22: 46139 | G22: AKun Baru | H22: 10764 | I22: 17963 | J22: I NYOMAN TEDI WIDNYANA | K22: 101 LAUNDRY | L22: 102 LAUNDRY | M22: 081339561151 | N22: 081239942510 | O22: 46079 | P22: 46093 | Q22: 0 | V22: (1) Rencana buka laundry
A23: =COUNTIF('Call & Chat-Lidya'!$I$4:$I$2433,I23) -> 3 | B23: 46161 | C23: 2026 | D23: Mei | E23: 389 | F23: 46138 | G23: Outlet Baru | H23: 11074 | I23: 18499 | J23: bagus Alwi Alimukti | K23: YOI LAUNDRY | L23: YOI LAUNDRY | M23: 082349968466 | N23: 082349968466 | O23: 46138 | P23: 46152 | Q23: 2 | V23: (1) Incoming
A24: =COUNTIF('Call & Chat-Lidya'!$I$4:$I$2433,I24) -> 3 | B24: 46161 | C24: 2026 | D24: Mei | E24: 30 | F24: 46148 | G24: AKun Baru | H24: 10063 | I24: 16740 | J24: said lutfi manfalutie | K24: SMA LAUNDRY | L24: SMA LAUNDRY | N24: 085370700942 | O24: 02/11/25 | P24: 45977 | Q24: 0 | V24: (1) Rencana buka laundry
A25: =COUNTIF('Call & Chat-Lidya'!$I$4:$I$2433,I25) -> 8 | B25: 46162 | C25: 2026 | D25: Mei | E25: 311 | F25: 46131 | G25: AKun Baru | H25: 11026 | I25: 18411 | J25: Ivo | K25: Zeline Laundry | L25: Zeline Laundry | M25: 081225752657 | N25: 081225752657 | O25: 46131 | P25: 46145 | Q25: 0 | R25: 2 | S25: CONNECTED | T25: DELIVERED | U25: VALID | V25: (2) Trial, Demo, Interaktif | W25: Playstore
A26: =COUNTIF('Call & Chat-Lidya'!$I$4:$I$2433,I26) -> 6 | B26: 46162 | C26: 2026 | D26: Mei | E26: 444 | F26: 46160 | G26: AKun Baru | H26: 11217 | I26: 18739 | J26: Andini Pratiwi | K26: Ratu Laundry | L26: Ratu Laundry | M26: 081211778498 | N26: 08131402848 | O26: 46160 | P26: 46174 | Q26: 5 | R26: 2 | S26: CONNECTED | T26: DELIVERED | U26: VALID | V26: (2) Trial, Demo, Interaktif | W26: Mitra
A27: =COUNTIF('Call & Chat-Lidya'!$I$4:$I$2433,I27) -> 8 | B27: 46164 | C27: 2026 | D27: Mei | E27: 446 | F27: 46160 | G27: AKun Baru | H27: 11218 | I27: 18742 | J27: Nana Kasterin | K27: Laundryku Bali | L27: Laundryku Bali | M27: 0818356761 | O27: 46160 | P27: 46174 | Q27: 1 | R27: 2 | S27: CONNECTED | T27: DELIVERED | U27: VALID | V27: (2) Trial, Demo, Interaktif
A28: =COUNTIF('Call & Chat-Lidya'!$I$4:$I$2433,I28) -> 10 | B28: 46164 | C28: 2026 | D28: Mei | E28: 447 | F28: 46160 | G28: AKun Baru | H28: 11219 | I28: 18745 | J28: jhoni ariyanto | K28: Fourkids laudry | L28: Fourkids laudry | M28: 089528002854 | O28: 46160 | P28: 46174 | Q28: 4 | R28: 2 | S28: CONNECTED | T28: ENGAGE | U28: VALID | V28: (1) Rencana buka laundry | Z28: Aplikasi sudah dicoba pelajari dan coba untuk nambah akun karyawan, tetapi yang terinput malah jadi akun owner dan suah arahin untuk akun karyawan bisa ditambah di menu karyawan di aplikasi owner
A29: =COUNTIF('Call & Chat-Lidya'!$I$4:$I$2433,I29) -> 3 | B29: 46161 | C29: 2026 | D29: Mei | E29: 448 | F29: 46161 | G29: AKun Baru | H29: 11222 | I29: 18748 | J29: Kapila karisma | K29: 99 Laundry | L29: 99 Laundry | M29: 085776151967 | N29: 081297813624 | O29: 46161 | P29: 46175 | Q29: 0 | R29: 1 | S29: CONNECTED | T29: DELIVERED | U29: VALID | V29: (0) Tidak Merespon
A30: =COUNTIF('Call & Chat-Lidya'!$I$4:$I$2433,I30) -> 3 | B30: 46164 | C30: 2026 | D30: Mei | E30: 449 | F30: 46164 | G30: AKun Baru | H30: 11248 | I30: 18791 | J30: nenci fitriani | K30: eci loundry | L30: eci loundry | M30: 085735360169 | N30: 085735360169 | O30: 46164 | P30: 46178 | Q30: 0 | R30: 1 | S30: CONNECTED | T30: DELIVERED | U30: VALID | V30: (0) Tidak Merespon
A31: =COUNTIF('Call & Chat-Lidya'!$I$4:$I$2433,I31) -> 3 | B31: 46164 | C31: 2026 | D31: Mei | E31: 450 | F31: 46164 | G31: AKun Baru | H31: 11250 | I31: 18793 | J31: silvia | K31: laundry viola | L31: laundry viola | M31: 081279585837 | N31: 085351278885 | O31: 46164 | P31: 46178 | Q31: 0 | R31: 1 | S31: CONNECTED | T31: DELIVERED | U31: VALID | V31: (0) Tidak Merespon
A32: =COUNTIF('Call & Chat-Lidya'!$I$4:$I$2433,I32) -> 3 | B32: 46164 | C32: 2026 | D32: Mei | E32: 451 | F32: 46164 | G32: Outlet Baru | H32: 9042 | I32: 14529 | J32: ulfa | K32: bintang laundry | L32: bintang laundry badas | M32: 085853958526 | N32: 085717901823 | O32: 46164 | P32: 46178 | Q32: 0 | R32: 3 | S32: PROSPECT | T32: PROSPECT | U32: VALID | V32: (3) Berlangganan | Z32: Training cara penggunaan aplikasi piposmart
A33: =COUNTIF('Call & Chat-Lidya'!$I$4:$I$2433,I33) -> 2 | B33: 46161 | C33: 2026 | D33: April | E33: 363 | F33: 46139 | G33: AKun Baru | H33: 10734 | I33: 17924 | J33: Yunita Trikumala dewi | K33: ZIE ZIE LAUNDRY | L33: ZIE ZIE LAUNDRY | M33: 087814545415 | N33: 087814545415 | O33: 46074 | P33: 46088 | Q33: 1 | R33: 1 | S33: CONTACTED | T33: DELIVERED | U33: VALID | V33: (0) Tidak Merespon
A34: =COUNTIF('Call & Chat-Lidya'!$I$4:$I$2433,I34) -> 2 | B34: 46161 | C34: 2026 | D34: April | E34: 364 | F34: 46139 | G34: AKun Baru | H34: 10757 | I34: 17952 | J34: Arkana Laundry | K34: Laundry Arkana | L34: Laundry Arkana | M34: 085161933969 | N34: 085161933969 | O34: 46078 | P34: 46092 | Q34: 0 | R34: 1 | S34: CONNECTED | T34: DELIVERED | U34: VALID | V34: (0) Tidak Merespon
A35: =COUNTIF('Call & Chat-Lidya'!$I$4:$I$2433,I35) -> 2 | B35: 46161 | C35: 2026 | D35: April | E35: 303 | F35: 46129 | G35: AKun Baru | H35: 10598 | I35: 17720 | J35: Yanti | K35: laundry | L35: laundry | M35: 085649780890 | N35: 085649780890 | O35: 46055 | P35: 46069 | Q35: 0 | R35: 1 | S35: CONNECTED | T35: DELIVERED | U35: VALID | V35: (0) Tidak Merespon
A36: =COUNTIF('Call & Chat-Lidya'!$I$4:$I$2433,I36) -> 2 | B36: 46161 | C36: 2026 | D36: April | E36: 304 | F36: 46129 | G36: AKun Baru | H36: 10612 | I36: 17742 | J36: MAYANG SRI ANTIKA | K36: rumoh laundry | L36: rumoh laundry | N36: 085269867679 | O36: 46057 | P36: 46071 | Q36: 0 | R36: 1 | S36: CONNECTED | T36: DELIVERED | U36: VALID | V36: (0) Tidak Merespon
A37: =COUNTIF('Call & Chat-Lidya'!$I$4:$I$2433,I37) -> 2 | B37: 46161 | C37: 2026 | D37: April | E37: 305 | F37: 46129 | G37: AKun Baru | H37: 10621 | I37: 17753 | J37: Zidah Laundry | K37: Zidah Laundry | L37: Zidah Laundry | M37: 082395005880 | N37: 082395005880 | O37: 46058 | P37: 46072 | Q37: 0 | R37: 1 | S37: ENGAGE | T37: DELIVERED | U37: VALID | V37: (0) Data Employee dan Trial | Z37: Aplikasi piposmartnya belum digunakan dan yang tau mengenai laundry adeknya dan adeknya lagi keluar. Saat ini di laundry sudah menggunakan sistem aplikasi dan tidak mau kasih tau nama aplikasi nya dan mengenai penjelasan piposmartnya boleh langsung ke adeknya aja nantu karna yang tau mengenai laundry adeknya
A38: =COUNTIF('Call & Chat-Lidya'!$I$4:$I$2433,I38) -> 2 | B38: 46161 | C38: 2026 | D38: April | E38: 306 | F38: 46129 | G38: AKun Baru | H38: 10626 | I38: 17761 | J38: M Ansori | K38: Viv Laundry | L38: Viv Laundry | M38: 087729867962 | N38: 087729867962 | O38: 46059 | P38: 46073 | Q38: 0 | R38: 1 | S38: CONTACTED | T38: DELIVERED | U38: VALID | V38: (0) Tidak Merespon
A39: =COUNTIF('Call & Chat-Lidya'!$I$4:$I$2433,I39) -> 3 | B39: 46161 | C39: 2026 | D39: April | E39: 358 | F39: 46139 | G39: AKun Baru | H39: 10671 | I39: 17830 | J39: Ramon Jun | K39: RaMoN Laundry | L39: RaMoN Laundry | M39: 085694544299 | N39: 085694544299 | O39: 46066 | P39: 46080 | Q39: 0 | R39: 1 | S39: CONNECTED | T39: DELIVERED | U39: VALID | V39: (0) Tidak Merespon
A40: =COUNTIF('Call & Chat-Lidya'!$I$4:$I$2433,I40) -> 1 | B40: 46161 | C40: 2026 | D40: April | E40: 301 | F40: 46129 | G40: AKun Baru | H40: 10592 | I40: 17711 | J40: Teguh Setiyono | K40: Toko Berkah Laundry Dan Water | L40: Toko Berkah Laundry Dan Water | M40: 0895342118401 | N40: 085727575179 | O40: 46054 | P40: 46068 | Q40: 2 | R40: 0 | S40: CONNECTED | T40: ENGAGE | U40: VALID | V40: (0) Tidak jadi buka laundry | Z40: Aplikasi piposmartnya belum digunakan karna laundry nya lagi off karna saat ini mesin laundry nya lagi rusak
A41: =COUNTIF('Call & Chat-Lidya'!$I$4:$I$2433,I41) -> 1 | B41: 46161 | C41: 2026 | D41: April | E41: 302 | F41: 46129 | G41: AKun Baru | H41: 10597 | I41: 17719 | J41: Agus Tangkas | K41: dd laundry | L41: dd laundry | M41: 081337349548 | N41: 081337349548 | O41: 46055 | P41: 46069 | Q41: 9 | R41: 1 | S41: ENGAGE | T41: DELIVERED | U41: VALID | V41: (0) Pakai Aplikasi Lain | Z41: Saat ini sudah menggunakan aplikasi edobi. Usaha laundry jalan 4 tahun dan dulu masih menggunakan nota manual dan baru" ini beralih ke sistem aplikasi. Penjelasan aplikasi piposmart dengan aplikasi edobi. Untuk aplikasi piposmart nanti akan dicoba peljari karna untuk di edobi membershipnya sampai akhir bulan ini, mungkin di bulan depan coba gunakan piposmart. Penjelasan biaya bulanan piposmart
A42: =COUNTIF('Call & Chat-Lidya'!$I$4:$I$2433,I42) -> 3 | B42: 46163 | C42: 2026 | D42: April | E42: 245 | F42: 46127 | G42: AKun Baru | H42: 10705 | I42: 17887 | J42: limasya | K42: limo | L42: limo | M42: 085524423120 | N42: 085524423131 | O42: 46071 | P42: 46085 | Q42: 5 | R42: 0 | S42: NO CALL | T42: UNINTEREST | U42: VALID | V42: (0) Tidak jadi buka laundry | Z42: Aplikasi tidak digunakan karna outlet laundry sudah tutup dan kedepannya tidak buka laundry lagi
A43: =COUNTIF('Call & Chat-Lidya'!$I$4:$I$2433,I43) -> 2 | B43: 46161 | C43: 2026 | D43: April | E43: 246 | F43: 46127 | G43: AKun Baru | H43: 10710 | I43: 17895 | J43: Setia Coin Laundry | K43: Setia Coin Laundry | L43: Setia Coin Laundry | M43: 089653077441 | O43: 46071 | P43: 46085 | Q43: 1 | R43: 1 | S43: CONTACTED | T43: DELIVERED | U43: VALID | V43: (0) Tidak Merespon
A44: =COUNTIF('Call & Chat-Lidya'!$I$4:$I$2433,I44) -> 2 | B44: 46161 | C44: 2026 | D44: April | E44: 247 | F44: 46127 | G44: AKun Baru | H44: 10713 | I44: 17900 | J44: Yenny Tahason | K44: Otello Laundry | L44: Otello Laundry | M44: 081357202912 | N44: 081357202912 | O44: 46071 | P44: 46085 | Q44: 0 | R44: 1 | S44: CONNECTED | T44: DELIVERED | U44: VALID | V44: (0) Tidak Merespon
A45: =COUNTIF('Call & Chat-Lidya'!$I$4:$I$2433,I45) -> 2 | B45: 46161 | C45: 2026 | D45: April | E45: 248 | F45: 46127 | G45: AKun Baru | H45: 10729 | I45: 17919 | J45: muhamad yukie hidayat | K45: ay laundry | L45: ay laundry | M45: 0895364741870 | N45: 0895330046925 | O45: 46073 | P45: 46087 | Q45: 0 | R45: 1 | S45: CONTACTED | T45: DELIVERED | U45: VALID | V45: (0) Tidak Merespon
A46: =COUNTIF('Call & Chat-Lidya'!$I$4:$I$2433,I46) -> 2 | B46: 46161 | C46: 2026 | D46: April | E46: 249 | F46: 46127 | G46: AKun Baru | H46: 10742 | I46: 17934 | J46: Dyah Candra | K46: Putra Ciber Laundry | L46: Putra Ciber Laundry | M46: 083832297011 | N46: 083832297011 | O46: 46075 | P46: 46089 | Q46: 0 | R46: 1 | S46: ENGAGE | T46: DELIVERED | U46: VALID | V46: (0) Tidak Merespon | Z46: Konfirmasi penggunaan aplikasi piposmart dan call langsung dimatikan
A47: =COUNTIF('Call & Chat-Lidya'!$I$4:$I$2433,I47) -> 2 | B47: 46161 | C47: 2026 | D47: April | E47: 250 | F47: 46127 | G47: AKun Baru | H47: 10743 | I47: 17935 | J47: Maulidia Putri | K47: Usaha Jasa Setrika | L47: Usaha Jasa Setrika | M47: 085706437702 | O47: 46075 | P47: 46089 | Q47: 0 | R47: 1 | S47: CONTACTED | T47: DELIVERED | U47: VALID | V47: (0) Tidak Merespon
A48: =COUNTIF('Call & Chat-Lidya'!$I$4:$I$2433,I48) -> 3 | B48: 46161 | C48: 2026 | D48: April | E48: 259 | F48: 46127 | G48: AKun Baru | H48: 10627 | I48: 17763 | J48: jawara Laundry | K48: jawara | L48: jawara | M48: 083879551357 | N48: 083879551357 | O48: 46059 | P48: 46073 | Q48: 1 | R48: 1 | S48: CONTACTED | T48: DELIVERED | U48: VALID | V48: (0) Tidak Merespon
A49: =COUNTIF('Call & Chat-Lidya'!$I$4:$I$2433,I49) -> 2 | B49: 46161 | C49: 2026 | D49: April | E49: 263 | F49: 46127 | G49: AKun Baru | H49: 10700 | I49: 17882 | J49: del | K49: home laundry | L49: home laundry | M49: 085342076719 | N49: 085342076719 | O49: 46071 | P49: 46085 | Q49: 1 | R49: 1 | S49: CONTACTED | T49: DELIVERED | U49: VALID | V49: (0) Tidak Merespon
A50: =COUNTIF('Call & Chat-Lidya'!$I$4:$I$2433,I50) -> 2 | B50: 46161 | C50: 2026 | D50: April | E50: 265 | F50: 46127 | G50: AKun Baru | H50: 10702 | I50: 17884 | J50: Oji S | K50: Loundryku | L50: Loundryku | M50: 087738155352 | O50: 46071 | P50: 46085 | Q50: 1 | R50: 1 | S50: CONNECTED | T50: DELIVERED | U50: VALID | V50: (0) Tidak Merespon
A51: =COUNTIF('Call & Chat-Lidya'!$I$4:$I$2433,I51) -> 2 | B51: 46161 | C51: 2026 | D51: April | E51: 266 | F51: 46127 | G51: AKun Baru | H51: 10703 | I51: 17885 | J51: Zuyy | K51: Merona Laundry | L51: Merona Laundry | M51: 081368186638 | O51: 46071 | P51: 46085 | Q51: 1 | R51: 1 | S51: CONNECTED | T51: DELIVERED | U51: VALID | V51: (0) Tidak Merespon
A52: =COUNTIF('Call & Chat-Lidya'!$I$4:$I$2433,I52) -> 2 | B52: 46161 | C52: 2026 | D52: April | E52: 268 | F52: 46127 | G52: AKun Baru | H52: 10722 | I52: 17910 | J52: Nor Chairunnisa | K52: D&W LAUNDRY | L52: D&W LAUNDRY | M52: 082352767466 | N52: 082352767466 | O52: 46072 | P52: 46086 | Q52: 0 | R52: 1 | S52: CONTACTED | T52: DELIVERED | U52: VALID | V52: (0) Tidak Merespon
A53: =COUNTIF('Call & Chat-Lidya'!$I$4:$I$2433,I53) -> 2 | B53: 46161 | C53: 2026 | D53: April | E53: 269 | F53: 46127 | G53: AKun Baru | H53: 10731 | I53: 17921 | J53: maya arsita devi | K53: juragan laundry | L53: juragan laundry | M53: 085177294830 | N53: 085280473665 | O53: 46073 | P53: 46087 | Q53: 0 | R53: 1 | S53: CONTACTED | T53: DELIVERED | U53: VALID | V53: (0) Tidak Merespon
A54: =COUNTIF('Call & Chat-Lidya'!$I$4:$I$2433,I54) -> 3 | B54: 46161 | C54: 2026 | D54: April | E54: 234 | F54: 46127 | G54: AKun Baru | H54: 10631 | I54: 17768 | J54: rosdianah | K54: AXAS laundry | L54: AXAS laundry | M54: 088223836719 | N54: 088223836719 | O54: 46060 | P54: 46074 | Q54: 0 | R54: 1 | S54: CONTACTED | T54: DELIVERED | U54: VALID | V54: (0) Tidak Merespon
A55: =COUNTIF('Call & Chat-Lidya'!$I$4:$I$2433,I55) -> 3 | B55: 46161 | C55: 2026 | D55: April | E55: 241 | F55: 46127 | G55: AKun Baru | H55: 10681 | I55: 17846 | J55: 1 | K55: 24 Laundry | L55: 25 Laundry | M55: 082142734617 | N55: 085156239895 | O55: 46067 | P55: 46081 | Q55: 10 | R55: 1 | S55: CONNECTED | T55: NO CHAT | U55: VALID | V55: (0) Tidak Merespon
A56: =COUNTIF('Call & Chat-Lidya'!$I$4:$I$2433,I56) -> 3 | B56: 46161 | C56: 2026 | D56: Maret | E56: 389 | F56: 46112 | G56: AKun Baru | H56: 10914 | I56: 18198 | J56: mendoza | K56: barokah laundry | L56: barokah laundry | M56: 082169323483 | N56: 082171661160 | O56: 46112 | P56: 46126 | Q56: 5 | R56: 1 | S56: CONNECTED | T56: DELIVERED | U56: VALID | V56: (0) Tidak Merespon
A57: =COUNTIF('Call & Chat-Lidya'!$I$4:$I$2433,I57) -> 5 | B57: 46160 | C57: 2026 | D57: Mei | E57: 46 | F57: 46150 | G57: AKun Baru | H57: 11152 | I57: 18632 | J57: Caca Laundry | K57: Caca laundry | L57: Caca laundry | M57: 0895414525201 | N57: 08227368303 | O57: 08/05/26 | P57: 46164 | Q57: 0 | R57: 1 | S57: ENGAGE | T57: DELIVERED | U57: VALID | V57: (0) Tidak Merespon | Z57: Konfirmasi penggunaan aplikasi piposmart, call langsung dimatikan
A58: =COUNTIF('Call & Chat-Lidya'!$I$4:$I$2433,I58) -> 3 | B58: 46164 | C58: 2026 | D58: Mei | E58: 47 | F58: 46151 | G58: Outlet Baru | H58: 4208 | I58: 5554 | J58: evikaban | K58: Charlos Loundry Expres | L58: charlos laundry 2 | M58: 081396343453 | N58: 081396343453 | O58: 08/05/26 | P58: 45751 | Q58: 0 | R58: 0 | S58: NO CALL | T58: DELIVERED | U58: VALID | V58: (0) Tidak jadi buka laundry | W58: Playstore | Z58: Aplikasi piposmartnya belum digunakan di outlet ke dua karna outlet ke dua nya belum buka dan belum tau kapan rencana pembukaannya. Bantu nasabah untuk reset password dan reset transaksi. Bantu nasabah dari hp call center
A59: =COUNTIF('Call & Chat-Lidya'!$I$4:$I$2433,I59) -> 5 | B59: 46160 | C59: 2026 | D59: Mei | E59: 49 | F59: 46151 | G59: AKun Baru | H59: 11155 | I59: 18635 | J59: Shafa Riah | K59: sidra laundry | L59: sidra laundry | M59: 0895365156909 | N59: 0895365156909 | O59: 09/05/26 | P59: 46165 | Q59: 0 | R59: 1 | S59: CONNECTED | T59: DELIVERED | U59: VALID | V59: (0) Tidak Merespon
A60: =COUNTIF('Call & Chat-Lidya'!$I$4:$I$2433,I60) -> 3 | B60: 46160 | C60: 2026 | D60: Mei | E60: 50 | F60: 46151 | G60: AKun Baru | H60: 11160 | I60: 18640 | J60: Ade Nofiani | K60: WASH MASTER LOUNDRY | L60: WASH MASTER LOUNDRY | M60: 089520557192 | N60: 089520557192 | O60: 09/05/26 | P60: 46165 | Q60: 0 | R60: 1 | S60: CONTACTED | T60: SENT | U60: INVALID | V60: (0) Nomor Diblokir | Z60: Konfirmasi penggunaan aplikasi piposmart, call langsung dimatikan
A61: =COUNTIF('Call & Chat-Lidya'!$I$4:$I$2433,I61) -> 3 | B61: 46160 | C61: 2026 | D61: Mei | E61: 44 | F61: 46149 | G61: AKun Baru | H61: 11145 | I61: 18620 | J61: Nana's Laundry | K61: nana's laundry | L61: nana's laundry | M61: 0882021701124 | N61: 0882021701124 | O61: 07/05/26 | P61: 46163 | Q61: 0 | R61: 0 | S61: CONTACTED | T61: NO CHAT | U61: INVALID | V61: (0) Tidak Merespon | Z61: Nomor tidak terhubung dengan wa
A62: =COUNTIF('Call & Chat-Lidya'!$I$4:$I$2433,I62) -> 5 | B62: 46160 | C62: 2026 | D62: Mei | E62: 45 | F62: 46150 | G62: AKun Baru | H62: 11147 | I62: 18623 | J62: Fatimah zahra | K62: ummi loundry | L62: ummi loundry | M62: 082368804792 | N62: 082368804792 | O62: 08/05/26 | P62: 46164 | Q62: 0 | R62: 1 | S62: ENGAGE | T62: DELIVERED | U62: VALID | V62: (0) Data Employee dan Trial | W62: Playstore | Z62: Aplikasi belum digunakan karna belum ada waktu, dan belum fokus di laundry karna lagi tahap renovasi. Usaha laundry buka di rumah dan masih hendel sendiri jadi pelanggannya juga masih tetangga aja. Penjelasan aplikasi piposmart dan perbedaannya dengan nota manual. Jika laundry nya sudah jadi dan aplikasi ada yang mau ditanyakan akan di hubungi kembali
A63: =COUNTIF('Call & Chat-Lidya'!$I$4:$I$2433,I63) -> 5 | B63: 46160 | C63: 2026 | D63: Mei | E63: 46 | F63: 46154 | G63: AKun Baru | H63: 11171 | I63: 18658 | J63: Noviyanti Dian | K63: Rezeki Laundry Express | L63: Rezeki Laundry Express | M63: 081259626119 | N63: 085754137663 | O63: 12/05/26 | P63: 46168 | Q63: 0 | R63: 1 | S63: CONNECTED | T63: DELIVERED | U63: VALID | V63: (0) Tidak Merespon
A64: =COUNTIF('Call & Chat-Lidya'!$I$4:$I$2433,I64) -> 5 | B64: 46160 | C64: 2026 | D64: Mei | E64: 47 | F64: 46154 | G64: AKun Baru | H64: 11172 | I64: 18660 | J64: Sherly Ana | K64: Nafil laundry | L64: Nafil laundry | M64: 085298164810 | N64: 085298164810 | O64: 12/05/26 | P64: 46168 | Q64: 0 | R64: 1 | S64: CONNECTED | T64: DELIVERED | U64: VALID | V64: (0) Tidak Merespon | Z64: Aplikasi belum dipelajari dan kirim video tutorial penggunaan aplikasi piposmart dan jika sudah datang mesin print nya aplikasi akan dicoba pelajari
A65: =COUNTIF('Call & Chat-Lidya'!$I$4:$I$2433,I65) -> 5 | B65: 46160 | C65: 2026 | D65: Mei | E65: 48 | F65: 46154 | G65: AKun Baru | H65: 11173 | I65: 18662 | J65: Riki Fajarisman | K65: Veeca Laundry | L65: Veeca Laundry | M65: 082221238840 | N65: 082221238840 | O65: 12/05/26 | P65: 46168 | Q65: 0 | R65: 1 | S65: CONNECTED | T65: DELIVERED | U65: VALID | V65: (0) Tidak Merespon
A66: =COUNTIF('Call & Chat-Lidya'!$I$4:$I$2433,I66) -> 5 | B66: 46160 | C66: 2026 | D66: Mei | E66: 49 | F66: 46149 | G66: Outlet Baru | H66: 7277 | I66: 10966 | J66: Rumah Cuci Jababeka | K66: Rumah Laundry Jababeka | L66: Rumah Cuci Cirebon | M66: 082277990202 | N66: 082277990202 | O66: 07/05/26 | P66: 46148 | Q66: 0 | R66: 1 | S66: NO CALL | T66: DELIVERED | U66: VALID | V66: (0) Tidak Merespon
